Workbook
Name cogs1: '[1]Income Statment'!$D$5
Name cogs2: '[1]Income Statment'!$E$5
Name cogs3: '[1]Income Statment'!$F$5
Name invent1: '[1]Financial Statment'!$E$8
Name invent2: '[1]Financial Statment'!$F$8
Name invent3: '[1]Financial Statment'!$G$8
Name payab1: '[1]Financial Statment'!$E$21
Name payab2: '[1]Financial Statment'!$F$21
Name payab3: '[1]Financial Statment'!$G$21
Name receiv1: '[1]Financial Statment'!$E$7
Name receiv2: '[1]Financial Statment'!$F$7
Name receiv3: '[1]Financial Statment'!$G$7
Name sales1: '[1]Income Statment'!$D$4
Name sales2: '[1]Income Statment'!$E$4
Name sales3: '[1]Income Statment'!$F$4
Name switch: [2]Info!$N$10

Sheet Main Model
A1: Projections Model
B3: Year | C3: 2016A | D3: 2022A | E3: 2023A | F3: 2024A | G3: 2025E | H3: 2026E | I3: 2027E | J3: 2028E
B4: GULF PACKAGING INDUSTRIES LTD | D4: His | E4: His | F4: His | G4: Proj | H4: Proj | I4: Proj | J4: Proj
B5: Switch | C5: 1
A7: Income Statement Assumptions
B8: 4Y CAGR Revenue
B9: Revenue growth | C9: 0 | D9: 0.05 | E9: =(E49/D49)-1 -> -0.24780895 | F9: =(F49/E49)-1 -> 0.4712745 | G9: 0 | H9: 0.04 | I9: 0.04 | J9: 0.02
B10: COGS % revenues | D10: =D50/D49 -> 0.69775449 | E10: =E50/E49 -> 0.85464686 | F10: =F50/F49 -> 0.81523921 | G10: 0.8 | H10: =G10 -> 0.8 | I10: =H10 -> 0.8 | J10: =I10 -> 0.8
B11: SG&A % revenues | D11: =D52/D$49 -> 0.13451303 | E11: =E52/E$49 -> 0.13160358 | F11: =F52/F$49 -> 0.13660525 | G11: 0.12 | H11: 0.12 | I11: 0.12 | J11: 0.12
B12: Depreciation % beginning net PP&E | D12: =D54/D$71 -> 0.058479507 | E12: =E54/E$71 -> 0.065921209 | F12: =F54/F$71 -> 0.084819865 | G12: =AVERAGE(D12:F12) -> 0.069740194 | H12: =AVERAGE(E12:G12) -> 0.073493756 | I12: =AVERAGE(F12:H12) -> 0.076017938 | J12: =AVERAGE(G12:I12) -> 0.073083963
B13: Other non operating (income) / expense | D13: =D58/D$49 -> -0.0019971879 | E13: =E58/E$49 -> -0.011301223 | F13: =F58/F$49 -> -0.0082112354 | G13: =AVERAGE(D13:F13) -> -0.007169882 | H13: =AVERAGE(E13:G13) -> -0.0088941133 | I13: =AVERAGE(F13:H13) -> -0.0080917435 | J13: =AVERAGE(G13:I13) -> -0.0080519129
B14: Zakt % | D14: =D59/(D53-D57-D58) -> 0.019012338 | E14: =E59/(E53-E57-E58) -> -0.093184717 | F14: =F59/(F53-F57-F58) -> 0.027968913 | G14: 0.07 | H14: 0.07 | I14: 0.07 | J14: 0.07
B15: Dividend % Net income | D15: =D61/D60 -> 1.0028189 | E15: =E61/E60 -> 0 | F15: =F61/F60 -> 0 | G15: 0 | H15: 0 | I15: 0 | J15: 0.5
A17: Balance Sheet/CF Assumptions
B18: Receivable days | D18: =D163 -> 93.367882 | E18: =E163 -> 109.49731 | F18: =F163 -> 73.285285 | G18: 73 | H18: 73 | I18: 73 | J18: 73
B19: Inventory days | D19: =D164 -> 55.186129 | E19: =E164 -> 77.645546 | F19: =F164 -> 68.027912 | G19: 68 | H19: 68 | I19: 68 | J19: 68
B20: Payable days | D20: =D165 -> 21.031745 | E20: =E165 -> 24.376041 | F20: =F165 -> 20.657445 | G20: 22 | H20: 22 | I20: 22 | J20: 22
B21: Other current assets % revenues | D21: =(D68)/D$49 -> 0.079650072 | E21: =(E68)/E$49 -> 0.097318551 | F21: =(F68)/F$49 -> 0.013807064 | G21: 0.04 | H21: 0.04 | I21: 0.04 | J21: 0.04
B22: Due from related % revenues | D22: =(D67)/D$49 -> 0.041859309 | E22: =(E67)/E$49 -> 1.7848524e-05 | F22: =(F67)/F$49 -> 0.004939022 | G22: 0.005 | H22: 0.005 | I22: 0.02 | J22: 0.02
B23: Other Current liabilities % revenue | D23: =D78/D$49 -> 0.11186513 | E23: =E78/E$49 -> 0.14636314 | F23: =F78/F$49 -> 0.1037026 | G23: 0.1037026 | H23: 0.1037026 | I23: 0.1037026 | J23: 0.1037026
B24: Capex % revenues | D24: =D34/D49 -> 0.3108844 | E24: =E34/E49 -> 0.15138489 | F24: =F34/F49 -> 0.04090155 | G24: 0.065 | H24: 0.065 | I24: 0.05 | J24: 0.05
B25: Intangible Assets % revenues | D25: =D72/D49 -> 0.0043569034 | E25: =E72/E49 -> 0.0056640027 | F25: =F72/F49 -> 0.0031978587 | G25: 0.0031978587 | H25: 0.0031978587 | I25: 0.0031978587 | J25: 0.0031978587
B26: Other long term assets % revenues | D26: =D73/D$49 -> 0.0027679325 | E26: =E73/E$49 -> 0.0026564154 | F26: =F73/F$49 -> 0.0013031244 | G26: =AVERAGE(D26:F26) -> 0.0022424908 | H26: =AVERAGE(E26:G26) -> 0.0020673435 | I26: =AVERAGE(F26:H26) -> 0.0018709862 | J26: =AVERAGE(G26:I26) -> 0.0020602735
B27: Other non current liabilities % revenues | D27: =D82/D$49 -> 0.020300059 | E27: =E82/E$49 -> 0.027588808 | F27: =F82/F$49 -> 0.01975448 | G27: 0.03 | H27: =G27 -> 0.03 | I27: =H27 -> 0.03 | J27: =I27 -> 0.03
A31: Balance Sheet Calculations
D32: =D48 -> 2022 | E32: =E48 -> 2023 | F32: =F48 -> 2024 | G32: =G48 -> 2025 | H32: =H48 -> 2026 | I32: =I48 -> 2027 | J32: =J48 -> 2028
B33: Beg. PPE | D33: 247178701 | E33: =D36 -> 504227333 | F33: =E36 -> 571504943 | G33: =F36 -> 565277861 | H33: =G36 -> 5.9120306e+08 | I33: =H36 -> 6.1575313e+08 | J33: =I36 -> 6.231542e+08
B34: Capex | D34: =D36-D33+D35 -> 286535598 | E34: =E36-E33+E35 -> 104951907 | F34: =F36-F33+F35 -> 41719710 | G34: =G24*G49 -> 66300205 | H34: =H24*H49 -> 68952214 | I34: =I24*I49 -> 55161771 | J34: =J24*J49 -> 56265006 | K34: =F34/G33 -> 0.073803899
B35: Dep. | D35: =D54 -> 29486966 | E35: =E54 -> 37674297 | F35: =F54 -> 47946792 | G35: =G12*G33 -> 39422588 | H35: =H12*H33 -> 43449734 | I35: =I12*I33 -> 46808284 | J35: =J12*J33 -> 45542579
B36: Ending PPE | D36: =D71 -> 504227333 | E36: =E71 -> 571504943 | F36: =F71 -> 565277861 | G36: =G33+G34-G35-G55 -> 5.9120306e+08 | H36: =H33+H34-H35-H55 -> 6.1575313e+08 | I36: =I33+I34-I35-I55 -> 6.231542e+08 | J36: =J33+J34-J35-J55 -> 6.3292422e+08
B38: Beginning equity | D38: =C42 -> 0 | E38: =D42 -> 502720325 | F38: =E42 -> 384531220 | G38: =F42 -> 353718300 | H38: =G42 -> 4.150357e+08 | I38: =H42 -> 4.8108856e+08 | J38: =I42 -> 5.5201979e+08
B39: Net income | D39: =D60 -> 149578348 | E39: =E60 -> 11742225 | F39: =F60 -> 39401076 | G39: =G60 -> 61317402 | H39: =H60 -> 66052855 | I39: =I60 -> 70931235 | J39: =J60 -> 74242200
B40: Dividends | D40: =D61*-1 -> -150000000 | E40: =E61*-1 -> 0 | F40: =F61*-1 -> 0 | G40: =G61*-1 -> 0 | H40: =H61*-1 -> 0 | I40: =I61*-1 -> 0 | J40: =J61*-1 -> -37121100
B41: Injection (Withdrawals) | D41: 150000000 | E41: -130000000 | F41: -70000000
B42: Ending equity | D42: =D85 -> 502720325 | E42: =E85 -> 384531220 | F42: =F85 -> 353718300 | G42: =SUM(G38:G41) -> 4.150357e+08 | H42: =SUM(H38:H41) -> 4.8108856e+08 | I42: =SUM(I38:I41) -> 5.5201979e+08 | J42: =SUM(J38:J41) -> 5.8914089e+08
A44: Net Debt and Interest Assumptions
B45: Short term borrowings interest rate | G45: 0.05 | H45: 0.05 | I45: 0.05 | J45: 0.05
B46: Long term debt interest rate | D46: =(D57)/(D79+D81) -> 0.042455292 | E46: =(E57)/(E79+E81) -> 0.032130913 | F46: =(F57)/(F79+F81) -> 0.070484199 | G46: 0.05 | H46: 0.05 | I46: 0.05 | J46: 0.05
A48: Income Statement | D48: 2022 | E48: 2023 | F48: 2024 | G48: 2025 | H48: 2026 | I48: 2027 | J48: 2028
B49: Revenue | D49: 921678907 | E49: 693278622 | F49: 1020003159 | G49: ='Recommended Loan '!E7 -> 1020003159 | H49: ='Recommended Loan '!F7 -> 1.0608033e+09 | I49: ='Recommended Loan '!G7 -> 1.1032354e+09 | J49: ='Recommended Loan '!H7 -> 1.1253001e+09
B50: COGS | D50: 643105599 | E50: 592508395 | F50: 831546566 | G50: =G10*G49 -> 8.1600253e+08 | H50: =H10*H49 -> 8.4864263e+08 | I50: =I10*I49 -> 8.8258833e+08 | J50: =J10*J49 -> 9.002401e+08
B51: GP | D51: =D49-D50 -> 278573308 | E51: =E49-E50 -> 100770227 | F51: =F49-F50 -> 188456593 | G51: =G49-G50 -> 2.0400063e+08 | H51: =H49-H50 -> 2.1216066e+08 | I51: =I49-I50 -> 2.2064708e+08 | J51: =J49-J50 -> 2.2506003e+08
B52: SG&A (with Dep and Amor) | D52: =95800719+28177101 -> 123977820 | E52: =63890358+27347590 -> 91237948 | F52: =102500411+34354316+2483064 -> 139337791 | G52: =G49*G11 -> 1.2240038e+08 | H52: =H49*H11 -> 1.2729639e+08 | I52: =I49*I11 -> 1.3238825e+08 | J52: =J49*J11 -> 1.3503602e+08
B53: Operating Income | D53: =D51-D52 -> 154595488 | E53: =E51-E52 -> 9532279 | F53: =F51-F52 -> 49118802 | G53: =G51-G52 -> 81600253 | H53: =H51-H52 -> 84864263 | I53: =I51-I52 -> 88258833 | J53: =J51-J52 -> 90024010
B54: Depreciation | D54: =29486966 -> 29486966 | E54: =37674297 -> 37674297 | F54: =47946792 -> 47946792 | G54: =G35 -> 39422588 | H54: =H35 -> 43449734 | I54: =I35 -> 46808284 | J54: =J35 -> 45542579
B55: Amortization | D55: 221799 | E55: 869617 | F55: =952414 -> 952414 | G55: =F55 -> 952414 | H55: =G55 -> 952414 | I55: =H55 -> 952414 | J55: =I55 -> 952414
B56: EBITDA | D56: =D53+D54+D55 -> 184304253 | E56: =E53+E54+E55 -> 48076193 | F56: =F53+F54+F55 -> 98018008 | G56: =G53+G54+G55 -> 1.2197525e+08 | H56: =H53+H54+H55 -> 1.2926641e+08 | I56: =I53+I54+I55 -> 1.3601953e+08 | J56: =J53+J54+J55 -> 1.36519e+08
B57: Finance Charges | D57: 3958956 | E57: 6625875 | F57: 16959498 | G57: =IF($C$5=1,G143+G151,0) -> 21684612 | H57: =IF($C$5=1,H143+H151,0) -> 19856737 | I57: =IF($C$5=1,I143+I151,0) -> 18005737 | J57: =IF($C$5=1,J143+J151,0) -> 16210737
B58: Others (Income)/expenses | D58: -1840766 | E58: -7834896 | F58: -8375486 | G58: =AVERAGE(D58:F58) -> -6017049.3 | H58: =G58 -> -6017049.3 | I58: =H58 -> -6017049.3 | J58: =I58 -> -6017049.3
B59: Zakat | D59: 2898950 | E59: -1000925 | F59: 1133714 | G59: =(G53-G57-G58)*G14 -> 4615288.3 | H59: =(H53-H57-H58)*H14 -> 4971720.3 | I59: =(I53-I57-I58)*I14 -> 5338910.2 | J59: =(J53-J57-J58)*J14 -> 5588122.6
B60: Net Income | D60: =D53-D57-D58-D59 -> 149578348 | E60: =E53-E57-E58-E59 -> 11742225 | F60: =F53-F57-F58-F59 -> 39401076 | G60: =G53-G57-G58-G59 -> 61317402 | H60: =H53-H57-H58-H59 -> 66052855 | I60: =I53-I57-I58-I59 -> 70931235 | J60: =J53-J57-J58-J59 -> 74242200
B61: Dividends | D61: 150000000 | E61: 0 | F61: 0 | G61: =G60*G15 -> 0 | H61: =H60*H15 -> 0 | I61: =I60*I15 -> 0 | J61: =J60*J15 -> 37121100
A63: Balance Sheet | D63: =D48 -> 2022 | E63: =E48 -> 2023 | F63: =F48 -> 2024 | G63: =G48 -> 2025 | H63: =H48 -> 2026 | I63: =I48 -> 2027 | J63: =J48 -> 2028
B64: Cash and equivalents | D64: 20292379 | E64: =9674628 -> 9674628 | F64: 13666666 | G64: =G124 -> 14768242 | H64: =H124 -> 18060365 | I64: =I124 -> 11514536 | J64: =J124 -> 6249453.2
B65: Receivables | D65: 235767691 | E65: =180189255 -> 180189255 | F65: =229406482 -> 229406482 | G65: =G49/365*G18 -> 2.0400063e+08 | H65: =H49/365*H18 -> 2.1216066e+08 | I65: =I49/365*I18 -> 2.2064708e+08 | J65: =J49/365*J18 -> 2.2506003e+08
B66: Inventories | D66: 97234270 | E66: =154851416 -> 154851416 | F66: =155112293 -> 155112293 | G66: =G50/365*G19 -> 1.5202239e+08 | H66: =H50/365*H19 -> 1.5810328e+08 | I66: =I50/365*I19 -> 1.6442742e+08 | J66: =J50/365*J19 -> 1.6771596e+08
B67: Due from related parties | D67: 38580842 | E67: 12374 | F67: 5037818 | G67: =G22*G49 -> 5100015.8 | H67: =H22*H49 -> 5304016.4 | I67: =I22*I49 -> 22064708 | J67: =J22*J49 -> 22506003
B68: Prepaids and other current assets | D68: =35130671+38281120 -> 73411791 | E68: =67468871 -> 67468871 | F68: =13422126+661123 -> 14083249 | G68: =G21*G49 -> 40800126 | H68: =H21*H49 -> 42432131 | I68: =I21*I49 -> 44129417 | J68: =J21*J49 -> 45012005
B69: Total current assets | D69: =SUM(D64:D68) -> 465286973 | E69: =SUM(E64:E68) -> 412196544 | F69: =SUM(F64:F68) -> 417306508 | G69: =SUM(G64:G68) -> 4.166914e+08 | H69: =SUM(H64:H68) -> 4.3606045e+08 | I69: =SUM(I64:I68) -> 4.6278316e+08 | J69: =SUM(J64:J68) -> 4.6654345e+08
B71: Net PP&E | D71: 504227333 | E71: 571504943 | F71: =565277861 -> 565277861 | G71: =G36 -> 5.9120306e+08 | H71: =H36 -> 6.1575313e+08 | I71: =I36 -> 6.231542e+08 | J71: =J36 -> 6.3292422e+08
B72: Intangible Assets | D72: 4015666 | E72: 3926732 | F72: =3261826 -> 3261826 | G72: =(G49*G25)-G55 -> 2309412 | H72: =(H49*H25)-H55 -> 2439885 | I72: =(I49*I25)-I55 -> 2575577 | J72: =(J49*J25)-J55 -> 2646136.8
B73: Right of use Assets | D73: =2551145 -> 2551145 | E73: =1841636 -> 1841636 | F73: =1329191 -> 1329191 | G73: =G26*G49 -> 2287347.7 | H73: =H26*H49 -> 2193044.8 | I73: =I26*I49 -> 2064138.3 | J73: =J26*J49 -> 2318426
B74: Total assets | D74: =SUM(D71:D73)+D69 -> 976081117 | E74: =SUM(E71:E73)+E69 -> 989469855 | F74: =SUM(F71:F73)+F69 -> 987175386 | G74: =SUM(G71:G73)+G69 -> 1.0124912e+09 | H74: =SUM(H71:H73)+H69 -> 1.0564465e+09 | I74: =TRUNC(SUM(I71:I73)+I69) -> 1090577078 | J74: =TRUNC(SUM(J71:J73)+J69) -> 1104432229
B76: Short term borrowings | D76: 221240396 | E76: 236043261 | F76: =214875559 -> 214875559 | G76: =G141 -> 200875559 | H76: =H141 -> 190875559 | I76: =I141 -> 175875559 | J76: =J141 -> 210875559
B77: Payables | D77: 37056528 | E77: =42083248 -> 42083248 | F77: =52040736 -> 52040736 | G77: =G50/365*G20 -> 49183714 | H77: =H50/365*H20 -> 51151063 | I77: =I50/365*I20 -> 53197105 | J77: =J50/365*J20 -> 54261047
B78: Other current liabilities | D78: =2576210+774026+92770045+6983451 -> 103103732 | E78: 101470435 | F78: 105776977 | G78: =G23*G49 -> 105776977 | H78: =H23*H49 -> 1.1000806e+08 | I78: =I23*I49 -> 1.1440838e+08 | J78: =J23*J49 -> 1.1669655e+08
B79: Current LT borrowings | E79: 16506500 | F79: =57456650 -> 57456650 | G79: =G152 -> 19520000 | H79: =H152 -> 29520000 | I79: =I152 -> 62280000 | J79: =J152 -> 0
B80: Total current liabilities | D80: =SUM(D76:D79) -> 361400656 | E80: =SUM(E76:E79) -> 396103444 | F80: =SUM(F76:F79) -> 430149922 | G80: =SUM(G76:G79) -> 3.7535625e+08 | H80: =SUM(H76:H79) -> 3.8155468e+08 | I80: =SUM(I76:I79) -> 4.0576104e+08 | J80: =SUM(J76:J79) -> 3.8183315e+08
B81: Long term debt | D81: 93250000 | E81: 189708460 | F81: 183157532 | G81: =G153 -> 191499182 | H81: =H153 -> 161979182 | I81: =I153 -> 99699182 | J81: =J153 -> 99699182
B82: Other non current liabilities | D82: 18710136 | E82: 19126731 | F82: 20149632 | G82: =G49*G27 -> 30600095 | H82: =H49*H27 -> 31824099 | I82: =I49*I27 -> 33097063 | J82: =J49*J27 -> 33759004
B83: Total liabilities | D83: =SUM(D81:D82)+D80 -> 473360792 | E83: =SUM(E81:E82)+E80 -> 604938635 | F83: =SUM(F81:F82)+F80 -> 633457086 | G83: =SUM(G81:G82)+G80 -> 5.9745553e+08 | H83: =SUM(H81:H82)+H80 -> 5.7535796e+08 | I83: =SUM(I81:I82)+I80 -> 5.3855729e+08 | J83: =SUM(J81:J82)+J80 -> 5.1529134e+08
B85: Total equity | D85: =136000000+200000000+40800000+125920325 -> 502720325 | E85: =136000000+70000000+40800000+137731220 -> 384531220 | F85: =136000000+40800000+176918300 -> 353718300 | G85: =G42 -> 4.150357e+08 | H85: =H42 -> 4.8108856e+08 | I85: =I42 -> 5.5201979e+08 | J85: =J42 -> 5.8914089e+08
B86: Total liabilities and equity | D86: =D83+D85 -> 976081117 | E86: =E83+E85 -> 989469855 | F86: =F83+F85 -> 987175386 | G86: =G83+G85 -> 1.0124912e+09 | H86: =H83+H85 -> 1.0564465e+09 | I86: =TRUNC(I83+I85) -> 1090577078 | J86: =TRUNC(J83+J85) -> 1104432229
B88: Check? | D88: =D86=D74 -> TRUE | E88: =E86=E74 -> TRUE | F88: =F86=F74 -> TRUE | G88: =G86=G74 -> TRUE | H88: =H86=H74 -> TRUE | I88: =I86=I74 -> TRUE | J88: =J86=J74 -> TRUE
G89: =G86-G74 -> 0 | H89: =H86-H74 -> 0 | I89: =I86-I74 -> 0 | J89: =J86-J74 -> 0
B90: Receivables | D90: =D65 -> 235767691 | E90: =E65 -> 180189255 | F90: =F65 -> 229406482 | G90: =G65 -> 2.0400063e+08 | H90: =H65 -> 2.1216066e+08 | I90: =I65 -> 2.2064708e+08 | J90: =J65 -> 2.2506003e+08
B91: Inventories | D91: =D66 -> 97234270 | E91: =E66 -> 154851416 | F91: =F66 -> 155112293 | G91: =G66 -> 1.5202239e+08 | H91: =H66 -> 1.5810328e+08 | I91: =I66 -> 1.6442742e+08 | J91: =J66 -> 1.6771596e+08
B92: Prepaids and other current assets | D92: =D68+D67 -> 111992633 | E92: =E68+E67 -> 67481245 | F92: =F68+F67 -> 19121067 | G92: =G68+G67 -> 45900142 | H92: =H68+H67 -> 47736148 | I92: =I68+I67 -> 66194125 | J92: =J68+J67 -> 67518008
B93: Payables | D93: =D77 -> 37056528 | E93: =E77 -> 42083248 | F93: =F77 -> 52040736 | G93: =G77 -> 49183714 | H93: =H77 -> 51151063 | I93: =I77 -> 53197105 | J93: =J77 -> 54261047
B94: Other current liabilities | D94: =D78 -> 103103732 | E94: =E78 -> 101470435 | F94: =F78 -> 105776977 | G94: =G78 -> 105776977 | H94: =H78 -> 1.1000806e+08 | I94: =I78 -> 1.1440838e+08 | J94: =J78 -> 1.1669655e+08
B95: Operating working capital | D95: =SUM(D90:D92)-SUM(D93:D94) -> 304834334 | E95: =SUM(E90:E92)-SUM(E93:E94) -> 258968233 | F95: =SUM(F90:F92)-SUM(F93:F94) -> 245822129 | G95: =SUM(G90:G92)-SUM(G93:G94) -> 2.4696247e+08 | H95: =SUM(H90:H92)-SUM(H93:H94) -> 2.5684097e+08 | I95: =SUM(I90:I92)-SUM(I93:I94) -> 2.8366314e+08 | J95: =SUM(J90:J92)-SUM(J93:J94) -> 2.893364e+08
A96: Cash Flow Statement
B97: Net income before Zakat | D97: =D60+D59 -> 152477298 | E97: =E60+E59 -> 10741300 | F97: =F60+F59 -> 40534790 | G97: =G60 -> 61317402 | H97: =H60 -> 66052855 | I97: =I60 -> 70931235 | J97: =J60 -> 74242200
B98: Depreciation | D98: =D35 -> 29486966 | E98: =E35 -> 37674297 | F98: =F35 -> 47946792 | G98: =G54 -> 39422588 | H98: =H54 -> 43449734 | I98: =I54 -> 46808284 | J98: =J54 -> 45542579
B99: Amortization | D99: =D55 -> 221799 | E99: =E55 -> 869617 | F99: =F55 -> 952414 | G99: =G55 -> 952414 | H99: =H55 -> 952414 | I99: =I55 -> 952414 | J99: =J55 -> 952414
B100: Change in OWC | E100: =D95-E95 -> 45866101 | F100: =E95-F95 -> 13146104 | G100: =F95-G95 -> -1140342.6 | H100: =G95-H95 -> -9878498.9 | I100: =H95-I95 -> -26822170 | J100: =I95-J95 -> -5673262.8
B101: Others (Allowances, paid zakat, gain, adj.) | D101: =-23773478-221799 -> -23995277 | E101: =2463122-869617 -> 1593505 | F101: =103464592-103163032-952414 -> -650854 | G101: 0 | H101: 0 | I101: 0 | J101: 0
B102: Change in other long term assets | E102: =D73-E73 -> 709509 | F102: =E73-F73 -> 512445 | G102: =F73-G73 -> -958156.66 | H102: =G73-H73 -> 94302.867 | I102: =H73-I73 -> 128906.53 | J102: =I73-J73 -> -254287.76
B103: Change in other non current liabilities | E103: =E82-D82 -> 416595 | F103: =F82-E82 -> 1022901 | G103: =G82-F82 -> 10450463 | H103: =H82-G82 -> 1224003.8 | I103: =I82-H82 -> 1272963.9 | J103: =J82-I82 -> 661941.25
B104: Cash flow from operations | D104: =SUM(D97:D103) -> 158190786 | E104: =SUM(E97:E103) -> 97870924 | F104: =SUM(F97:F103) -> 103464592 | G104: =SUM(G97:G103) -> 1.1004437e+08 | H104: =SUM(H97:H103) -> 1.0189481e+08 | I104: =SUM(I97:I103) -> 93271633 | J104: =SUM(J97:J103) -> 1.1547158e+08
B106: FFCF | D106: =D104-ABS(D109) -> -128344812 | E106: =E104-ABS(E109) -> -7080983 | F106: =F104-ABS(F109) -> 61744882 | G106: =G104-ABS(G109) -> 43744162 | H106: =H104-ABS(H109) -> 32942597 | I106: =I104-ABS(I109) -> 38109863 | J106: =J104-ABS(J109) -> 59206577
B107: Levered Free Cash Flow | D107: =D106+D114+D115+D116+D117 -> 20743626 | E107: =E106+E114+E115+E116+E117 -> 120686842 | F107: =F106+F114+F115+F116+F117 -> 74976402 | G107: =G106+G114+G115+G116+G117 -> 149161.54 | H107: =H106+H114+H115+H116+H117 -> 3422597 | I107: =I106+I114+I115+I116+I117 -> -6410137.4 | J107: =J106+J114+J115+J116+J117 -> 31926577
B109: (Capex) | D109: =D34*-1 -> -286535598 | E109: =E34*-1 -> -104951907 | F109: =-F34 -> -41719710 | G109: =-G34 -> -66300205 | H109: =-H34 -> -68952214 | I109: =-I34 -> -55161771 | J109: =-J34 -> -56265006
B110: Change in long term investments | D110: =D72-0 -> 4015666 | E110: =D72-E72 -> 88934 | F110: =E72-F72 -> 664906 | G110: =F72-G72 -> 952414 | H110: =G72-H72 -> -130473.04 | I110: =H72-I72 -> -135691.96 | J110: =I72-J72 -> -70559.82
B111: Others (Adj.) | D111: -8489509 | E111: -522504 | F111: =41054804-41706887 -> -652083
B112: Cash from investing activities | D112: =SUM(D109:D111) -> -291009441 | E112: =SUM(E109:E111) -> -105385477 | F112: =SUM(F109:F111) -> -41706887 | G112: =SUM(G109:G110) -> -65347791 | H112: =SUM(H109:H110) -> -69082687 | I112: =SUM(I109:I110) -> -55297463 | J112: =SUM(J109:J110) -> -56335566
B114: Issuance of ST | D114: 55838438 | E114: 14802865 | G114: =G140+G139 -> 200000000 | H114: =H139 -> 100000000 | I114: =I139 -> 110000000 | J114: =J139 -> 160000000
B115: (Payment of ST) | F115: -21167702 | G115: =G138 -> -214000000 | H115: =H138+H140 -> -110000000 | I115: =I138+I140 -> -125000000 | J115: =J138+J140 -> -125000000
B116: Issuance of LT | D116: 93250000 | E116: 112964960 | F116: 34399222 | G116: =G147 -> 0 | H116: =H147 -> 0 | I116: =I147 -> 0 | J116: =J147 -> 0
B117: (Payment of LT) | G117: =G148 -> -29595000 | H117: =H148 -> -19520000 | I117: =I148 -> -29520000 | J117: =J148 -> -62280000
...

Sheet Recommended Loan   
A1: GULF PACKAGING INDUSTRIES LTD
A3: Revenue Assumptions
B4: ='Main Model'!D3 -> 2022A | C4: ='Main Model'!E3 -> 2023A | D4: ='Main Model'!F3 -> 2024A | E4: ='Main Model'!G3 -> 2025E | F4: ='Main Model'!H3 -> 2026E | G4: ='Main Model'!I3 -> 2027E | H4: ='Main Model'!J3 -> 2028E
A5: Local (SR) | B5: =B7-B6 -> 1.2903505e+08 | C5: =C7-C6 -> 2.1491637e+08 | D5: =D7-D6 -> 1.3260041e+08 | E5: =E7-E6 -> 1.5300047e+08 | F5: =F7-F6 -> 1.5912049e+08 | G5: =G7-G6 -> 1.6548531e+08 | H5: =H7-H6 -> 1.6879502e+08
A6: Export (SR) | B6: =B7*B10 -> 7.9264386e+08 | C6: =C7*C10 -> 4.7836225e+08 | D6: =D7*D10 -> 8.8740275e+08 | E6: =E10*E7 -> 8.6700269e+08 | F6: =F10*F7 -> 9.0168279e+08 | G6: =G10*G7 -> 9.377501e+08 | H6: =H10*H7 -> 9.5650511e+08
A7: Total Revenue (SR) | B7: ='Main Model'!D49 -> 921678907 | C7: ='Main Model'!E49 -> 693278622 | D7: ='Main Model'!F49 -> 1020003159 | E7: =(1+E8)*D7 -> 1020003159 | F7: =(1+F8)*E7 -> 1.0608033e+09 | G7: =(1+G8)*F7 -> 1.1032354e+09 | H7: =(1+H8)*G7 -> 1.1253001e+09
A8: Growth | B8: ='Main Model'!D9 -> 0.05 | C8: ='Main Model'!E9 -> -0.24780895 | D8: ='Main Model'!F9 -> 0.4712745 | E8: ='Main Model'!G9 -> 0 | F8: ='Main Model'!H9 -> 0.04 | G8: ='Main Model'!I9 -> 0.04 | H8: ='Main Model'!J9 -> 0.02
A10: Export Sales % | B10: 0.86 | C10: 0.69 | D10: 0.87 | E10: 0.85 | F10: 0.85 | G10: 0.85 | H10: 0.85
A12: COGS | B12: ='Main Model'!D50 -> 643105599 | C12: ='Main Model'!E50 -> 592508395 | D12: ='Main Model'!F50 -> 831546566 | E12: ='Main Model'!G50 -> 8.1600253e+08 | F12: ='Main Model'!H50 -> 8.4864263e+08 | G12: ='Main Model'!I50 -> 8.8258833e+08 | H12: ='Main Model'!J50 -> 9.002401e+08
A13: Less: Depreciation | B13: ='Main Model'!D54 -> 29486966 | C13: ='Main Model'!E54 -> 37674297 | D13: ='Main Model'!F54 -> 47946792 | E13: ='Main Model'!G54 -> 39422588 | F13: ='Main Model'!H54 -> 43449734 | G13: ='Main Model'!I54 -> 46808284 | H13: ='Main Model'!J54 -> 45542579
A14: Less: Amortization | B14: ='Main Model'!D55 -> 221799 | C14: ='Main Model'!E55 -> 869617 | D14: ='Main Model'!F55 -> 952414 | E14: ='Main Model'!G55 -> 952414 | F14: ='Main Model'!H55 -> 952414 | G14: ='Main Model'!I55 -> 952414 | H14: ='Main Model'!J55 -> 952414
A15: Cash COGS | B15: =B12-B13-B14 -> 613396834 | C15: =C12-C13-C14 -> 553964481 | D15: =D12-D13-D14 -> 782647360 | E15: =E12-E13-E14 -> 7.7562753e+08 | F15: =F12-F13-F14 -> 8.0424048e+08 | G15: =G12-G13-G14 -> 8.3482764e+08 | H15: =H12-H13-H14 -> 8.5374511e+08
A16: Local Cash COGS | B16: =B15*(1-B10) -> 85875557 | C16: =C15*(1-C10) -> 1.7172899e+08 | D16: =D15*(1-D10) -> 1.0174416e+08 | E16: =E15*(1-E10) -> 1.1634413e+08 | F16: =F15*(1-F10) -> 1.2063607e+08 | G16: =G15*(1-G10) -> 1.2522415e+08 | H16: =H15*(1-H10) -> 1.2806177e+08
B17: CCC
A18: Receivable days | B18: ='Main Model'!D163 -> 93.367882 | C18: ='Main Model'!E163 -> 109.49731 | D18: ='Main Model'!F163 -> 73.285285 | E18: ='Main Model'!G163 -> 73 | F18: ='Main Model'!H163 -> 73 | G18: ='Main Model'!I163 -> 73 | H18: ='Main Model'!J163 -> 73
A19: Inventory days | B19: ='Main Model'!D164 -> 55.186129 | C19: ='Main Model'!E164 -> 77.645546 | D19: ='Main Model'!F164 -> 68.027912 | E19: ='Main Model'!G164 -> 68 | F19: ='Main Model'!H164 -> 68 | G19: ='Main Model'!I164 -> 68 | H19: ='Main Model'!J164 -> 68
A20: Payable days | B20: ='Main Model'!D165 -> 21.031745 | C20: ='Main Model'!E165 -> 24.376041 | D20: ='Main Model'!F165 -> 20.657445 | E20: ='Main Model'!G165 -> 22 | F20: ='Main Model'!H165 -> 22 | G20: ='Main Model'!I165 -> 22 | H20: ='Main Model'!J165 -> 22 | J20: Local CCC
A21: Cash Conversion Cycle of total sales | B21: =B18+B19-B20 -> 127.52227 | C21: =C18+C19-C20 -> 162.76681 | D21: =D18+D19-D20 -> 120.65575 | E21: =E18+E19-E20 -> 119 | F21: =F18+F19-F20 -> 119 | G21: =G18+G19-G20 -> 119 | H21: =H18+H19-H20 -> 119 | K21: 2022A | L21: 2023A | M21: 2024A | N21: 2025E | O21: 2026E | P21: 2027E | Q21: 2028E
A22: local sales CCC | B22: 127.52227 | C22: 162.76681 | D22: 120.65575 | E22: 166 | F22: 166 | G22: 166 | H22: 166 | J22: Local Receivable days | K22: 93.367882 | L22: 109.49731 | M22: 73.285285 | N22: 120 | O22: 120 | P22: 120 | Q22: 120
J23: Local Inventory days | K23: 55.186129 | L23: 77.645546 | M23: 68.027912 | N23: 68 | O23: 68 | P23: 68 | Q23: 68
A24: Working Capital Need | B24: =B15*(B21/365) -> 2.1430618e+08 | C24: =C15*(C21/365) -> 2.4703297e+08 | D24: =D15*(D21/365) -> 2.5871481e+08 | E24: =E15*(E21/365) -> 2.5287582e+08 | F24: =F15*(F21/365) -> 2.6220443e+08 | G24: =G15*(G21/365) -> 2.7217668e+08 | H24: =H15*(H21/365) -> 2.783443e+08 | J24: Local Payable days | K24: 21.031745 | L24: 24.376041 | M24: 20.657445 | N24: 22 | O24: 22 | P24: 22 | Q24: 22
A25: Local working capital need based on over all company's CCC | B25: =B24*(1-B10) -> 30002865 | C25: =C24*(1-C10) -> 76580220 | D25: =D24*(1-D10) -> 33632926 | E25: =E24*(1-E10) -> 37931374 | F25: =F24*(1-F10) -> 39330665 | G25: =G24*(1-G10) -> 40826502 | H25: =H24*(1-H10) -> 41751644 | J25: Cash Conversion Cycle of total sales | K25: =K22+K23-K24 -> 127.52227 | L25: =L22+L23-L24 -> 162.76681 | M25: =M22+M23-M24 -> 120.65575 | N25: =N22+N23-N24 -> 166 | O25: =O22+O23-O24 -> 166 | P25: =P22+P23-P24 -> 166 | Q25: =Q22+Q23-Q24 -> 166
A27: Working Capital Need need based on local CCC | B27: =B15*(B22/365) -> 2.1430618e+08 | C27: =C15*(C22/365) -> 2.4703297e+08 | D27: =D15*(D22/365) -> 2.5871481e+08 | E27: =E15*(E22/365) -> 3.5275115e+08 | F27: =F15*(F22/365) -> 3.6576416e+08 | G27: =G15*(G22/365) -> 3.7967503e+08 | H27: =H15*(H22/365) -> 3.882786e+08
A28: Local working capital need based on local CCC | B28: =B27*(1-B10) -> 30002865 | C28: =C27*(1-C10) -> 76580220 | D28: =D27*(1-D10) -> 33632926 | E28: =E27*(1-E10) -> 52912672 | F28: =F27*(1-F10) -> 54864625 | G28: =G27*(1-G10) -> 56951255 | H28: =H27*(1-H10) -> 58241790
A29: Operating Cash Flow | B29: ='Main Model'!D104 -> 158190786 | C29: ='Main Model'!E104 -> 97870924 | D29: ='Main Model'!F104 -> 103464592 | E29: ='Main Model'!G104 -> 1.1004437e+08 | F29: ='Main Model'!H104 -> 1.0189481e+08 | G29: ='Main Model'!I104 -> 93271633 | H29: ='Main Model'!J104 -> 1.1547158e+08
A33: Repayment Date | B33: 2027
A34: Requested Amount | B34: 50000000
A35: Working Capital Need | B35: =ROUNDDOWN(F24,-5) -> 262200000
A36: Local Working Capital Need | B36: =ROUNDDOWN(F28,-5) -> 54800000
A37: Repayment capacity | B37: =ROUNDDOWN(G29+F29,-5) -> 195100000
A38: Stressed Repayment Capacity (30% discount) | B38: =B37*0.7 -> 136570000
A40: Recommended Loan for Approval "SR" | B40: =#REF! -> #REF! | C40: 50000000
B53: Recommended | C53: Not Recommended
