Workbook
Name \0: #REF!
Name \0: #REF!
Name \0: #REF!
Name \0: #REF!
Name \0: #REF!
Name \0: #REF!
Name \BASE_YEAR: #REF!
Name \BASE_YEAR: #REF!
Name \BASE_YEAR: #REF!
Name \BASE_YEAR: #REF!
Name \BASE_YEAR: #REF!
Name \BASE_YEAR: #REF!
Name \L: #REF!
Name \L: #REF!
Name \L: #REF!
Name \L: #REF!
Name \L: #REF!
Name \L: #REF!
Name \M: #REF!
Name \M: #REF!
Name \M: #REF!
Name \M: #REF!
Name \M: #REF!
Name \M: #REF!
Name \N: #REF!
Name \N: #REF!
Name \N: #REF!
Name \N: #REF!
Name \N: #REF!
Name \N: #REF!
Name \T: Assumptions!$AB$406:$AJ$414
Name \T: Assumptions!$AB$406:$AJ$414
Name \T: #REF!
Name \W: #REF!
Name \W: #REF!
Name \W: #REF!
Name \W: #REF!
Name \W: #REF!
Name \W: #REF!
Name _1_1: Assumptions!$A$5:$A$5
Name _1_1: Assumptions!$A$5:$A$5
Name _1_1: #REF!
Name _10_19: Assumptions!$A$382:$A$382
Name _10_19: Assumptions!$A$382:$A$382
Name _10_19: #REF!
Name _11_2: Assumptions!$A$91:$A$91
Name _11_2: Assumptions!$A$91:$A$91
Name _11_2: #REF!
Name _12_20: Assumptions!$A$403:$A$403
Name _12_20: Assumptions!$A$403:$A$403
Name _12_20: #REF!
Name _13_5: Assumptions!$A$134:$A$134
Name _13_5: Assumptions!$A$134:$A$134
Name _13_5: #REF!
Name _14_6: Assumptions!$A$162:$A$162
Name _14_6: Assumptions!$A$162:$A$162
Name _14_6: #REF!
Name _15_9: Assumptions!$A$196:$A$196
Name _15_9: Assumptions!$A$196:$A$196
Name _15_9: #REF!

Sheet BSL_AC
A1: Year | B1: =#REF! -> #REF! | C1: =#REF! -> #REF! | D1: =#REF! -> #REF! | E1: =#REF! -> #REF! | F1: =#REF! -> #REF! | G1: =#REF! -> #REF! | H1: =#REF! -> #REF! | I1: =#REF! -> #REF! | ... Q1: =#REF! -> #REF!
A2: Acpay | B2: =#REF!*1000 -> #REF! | C2: =#REF!*1000 -> #REF! | D2: =#REF!*1000 -> #REF! | E2: =#REF!*1000 -> #REF! | F2: =#REF!*1000 -> #REF! | G2: =#REF!*1000 -> #REF! | H2: =#REF!*1000 -> #REF! | I2: =#REF!*1000 -> #REF! | ... Q2: =#REF!*1000 -> #REF!
A3: Std | B3: =#REF!*1000 -> #REF! | C3: =#REF!*1000 -> #REF! | D3: =#REF!*1000 -> #REF! | E3: =#REF!*1000 -> #REF! | F3: =#REF!*1000 -> #REF! | G3: =#REF!*1000 -> #REF! | H3: =#REF!*1000 -> #REF! | I3: =#REF!*1000 -> #REF! | ... Q3: =#REF!*1000 -> #REF!
A4: Accruals | B4: =#REF!*1000 -> #REF! | C4: =#REF!*1000 -> #REF! | D4: =#REF!*1000 -> #REF! | E4: =#REF!*1000 -> #REF! | F4: =#REF!*1000 -> #REF! | G4: =#REF!*1000 -> #REF! | H4: =#REF!*1000 -> #REF! | I4: =#REF!*1000 -> #REF! | ... Q4: =#REF!*1000 -> #REF!
A5: Cplsidf | B5: =#REF!*1000 -> #REF! | C5: =#REF!*1000 -> #REF! | D5: =#REF!*1000 -> #REF! | E5: =#REF!*1000 -> #REF! | F5: =#REF!*1000 -> #REF! | G5: =#REF!*1000 -> #REF! | H5: =#REF!*1000 -> #REF! | I5: =#REF!*1000 -> #REF! | ... Q5: =#REF!*1000 -> #REF!
A6: Cplbank | B6: =#REF!*1000 -> #REF! | C6: =#REF!*1000 -> #REF! | D6: =#REF!*1000 -> #REF! | E6: =#REF!*1000 -> #REF! | F6: =#REF!*1000 -> #REF! | G6: =#REF!*1000 -> #REF! | H6: =#REF!*1000 -> #REF! | I6: =#REF!*1000 -> #REF! | ... Q6: =#REF!*1000 -> #REF!
A7: Cplother | B7: =#REF!*1000 -> #REF! | C7: =#REF!*1000 -> #REF! | D7: =#REF!*1000 -> #REF! | E7: =#REF!*1000 -> #REF! | F7: =#REF!*1000 -> #REF! | G7: =#REF!*1000 -> #REF! | H7: =#REF!*1000 -> #REF! | I7: =#REF!*1000 -> #REF! | ... Q7: =#REF!*1000 -> #REF!
A8: Other1 | B8: =#REF!*1000 -> #REF! | C8: =#REF!*1000 -> #REF! | D8: =#REF!*1000 -> #REF! | E8: =#REF!*1000 -> #REF! | F8: =#REF!*1000 -> #REF! | G8: =#REF!*1000 -> #REF! | H8: =#REF!*1000 -> #REF! | I8: =#REF!*1000 -> #REF! | ... Q8: =#REF!*1000 -> #REF!
A9: Other2 | B9: =#REF!*1000 -> #REF! | C9: =#REF!*1000 -> #REF! | D9: =#REF!*1000 -> #REF! | E9: =#REF!*1000 -> #REF! | F9: =#REF!*1000 -> #REF! | G9: =#REF!*1000 -> #REF! | H9: =#REF!*1000 -> #REF! | I9: =#REF!*1000 -> #REF! | ... Q9: =#REF!*1000 -> #REF!
A10: Currentliab | B10: =#REF!*1000 -> #REF! | C10: =#REF!*1000 -> #REF! | D10: =#REF!*1000 -> #REF! | E10: =#REF!*1000 -> #REF! | F10: =#REF!*1000 -> #REF! | G10: =#REF!*1000 -> #REF! | H10: =#REF!*1000 -> #REF! | I10: =#REF!*1000 -> #REF! | ... Q10: =#REF!*1000 -> #REF!
A11: Ltdsidf | B11: =#REF!*1000 -> #REF! | C11: =#REF!*1000 -> #REF! | D11: =#REF!*1000 -> #REF! | E11: =#REF!*1000 -> #REF! | F11: =#REF!*1000 -> #REF! | G11: =#REF!*1000 -> #REF! | H11: =#REF!*1000 -> #REF! | I11: =#REF!*1000 -> #REF! | ... Q11: =#REF!*1000 -> #REF!
A12: Ltdbank | B12: =#REF!*1000 -> #REF! | C12: =#REF!*1000 -> #REF! | D12: =#REF!*1000 -> #REF! | E12: =#REF!*1000 -> #REF! | F12: =#REF!*1000 -> #REF! | G12: =#REF!*1000 -> #REF! | H12: =#REF!*1000 -> #REF! | I12: =#REF!*1000 -> #REF! | ... Q12: =#REF!*1000 -> #REF!
A13: Ltdother | B13: =#REF!*1000 -> #REF! | C13: =#REF!*1000 -> #REF! | D13: =#REF!*1000 -> #REF! | E13: =#REF!*1000 -> #REF! | F13: =#REF!*1000 -> #REF! | G13: =#REF!*1000 -> #REF! | H13: =#REF!*1000 -> #REF! | I13: =#REF!*1000 -> #REF! | ... Q13: =#REF!*1000 -> #REF!
... A23: Totliabeq | B23: =#REF!*1000 -> #REF! | C23: =#REF!*1000 -> #REF! | D23: =#REF!*1000 -> #REF! | E23: =#REF!*1000 -> #REF! | F23: =#REF!*1000 -> #REF! | G23: =#REF!*1000 -> #REF! | H23: =#REF!*1000 -> #REF! | I23: =#REF!*1000 -> #REF! | ... Q23: =#REF!*1000 -> #REF!
A24: Months | B24: 12 | C24: 12 | D24: 12 | E24: 12 | F24: 12 | G24: 12 | H24: 12 | I24: 12 | J24: 12 | K24: 12 | L24: 12 | M24: 12 | N24: 12 | O24: 12 | P24: 12 | Q24: 12

Sheet BSA_AC
A1: Year | B1: =#REF! -> #REF! | C1: =#REF! -> #REF! | D1: =#REF! -> #REF! | E1: =#REF! -> #REF! | F1: =#REF! -> #REF! | G1: =#REF! -> #REF! | H1: =#REF! -> #REF! | I1: =#REF! -> #REF! | ... Q1: =#REF! -> #REF!
A2: Factorycash | B2: =#REF!*1000 -> #REF! | C2: =#REF!*1000 -> #REF! | D2: =#REF!*1000 -> #REF! | E2: =#REF!*1000 -> #REF! | F2: =#REF!*1000 -> #REF! | G2: =#REF!*1000 -> #REF! | H2: =#REF!*1000 -> #REF! | I2: =#REF!*1000 -> #REF! | ... Q2: =#REF!*1000 -> #REF!
A3: Accntsrec | B3: =#REF!*1000 -> #REF! | C3: =#REF!*1000 -> #REF! | D3: =#REF!*1000 -> #REF! | E3: =#REF!*1000 -> #REF! | F3: =#REF!*1000 -> #REF! | G3: =#REF!*1000 -> #REF! | H3: =#REF!*1000 -> #REF! | I3: =#REF!*1000 -> #REF! | ... Q3: =#REF!*1000 -> #REF!
A4: Inventory | B4: =#REF!*1000 -> #REF! | C4: =#REF!*1000 -> #REF! | D4: =#REF!*1000 -> #REF! | E4: =#REF!*1000 -> #REF! | F4: =#REF!*1000 -> #REF! | G4: =#REF!*1000 -> #REF! | H4: =#REF!*1000 -> #REF! | I4: =#REF!*1000 -> #REF! | ... Q4: =#REF!*1000 -> #REF!
A5: Lcmargins | B5: =#REF!*1000 -> #REF! | C5: =#REF!*1000 -> #REF! | D5: =#REF!*1000 -> #REF! | E5: =#REF!*1000 -> #REF! | F5: =#REF!*1000 -> #REF! | G5: =#REF!*1000 -> #REF! | H5: =#REF!*1000 -> #REF! | I5: =#REF!*1000 -> #REF! | ... Q5: =#REF!*1000 -> #REF!
A6: Prepaid | B6: =#REF!*1000 -> #REF! | C6: =#REF!*1000 -> #REF! | D6: =#REF!*1000 -> #REF! | E6: =#REF!*1000 -> #REF! | F6: =#REF!*1000 -> #REF! | G6: =#REF!*1000 -> #REF! | H6: =#REF!*1000 -> #REF! | I6: =#REF!*1000 -> #REF! | ... Q6: =#REF!*1000 -> #REF!
A7: Other1 | B7: =#REF!*1000 -> #REF! | C7: =#REF!*1000 -> #REF! | D7: =#REF!*1000 -> #REF! | E7: =#REF!*1000 -> #REF! | F7: =#REF!*1000 -> #REF! | G7: =#REF!*1000 -> #REF! | H7: =#REF!*1000 -> #REF! | I7: =#REF!*1000 -> #REF! | ... Q7: =#REF!*1000 -> #REF!
A8: Currentassets | B8: =#REF!*1000 -> #REF! | C8: =#REF!*1000 -> #REF! | D8: =#REF!*1000 -> #REF! | E8: =#REF!*1000 -> #REF! | F8: =#REF!*1000 -> #REF! | G8: =#REF!*1000 -> #REF! | H8: =#REF!*1000 -> #REF! | I8: =#REF!*1000 -> #REF! | ... Q8: =#REF!*1000 -> #REF!
A9: Land | B9: =#REF!*1000 -> #REF! | C9: =#REF!*1000 -> #REF! | D9: =#REF!*1000 -> #REF! | E9: =#REF!*1000 -> #REF! | F9: =#REF!*1000 -> #REF! | G9: =#REF!*1000 -> #REF! | H9: =#REF!*1000 -> #REF! | I9: =#REF!*1000 -> #REF! | ... Q9: =#REF!*1000 -> #REF!
A10: Buildings | B10: =#REF!*1000 -> #REF! | C10: =#REF!*1000 -> #REF! | D10: =#REF!*1000 -> #REF! | E10: =#REF!*1000 -> #REF! | F10: =#REF!*1000 -> #REF! | G10: =#REF!*1000 -> #REF! | H10: =#REF!*1000 -> #REF! | I10: =#REF!*1000 -> #REF! | ... Q10: =#REF!*1000 -> #REF!
A11: Machinery | B11: =#REF!*1000 -> #REF! | C11: =#REF!*1000 -> #REF! | D11: =#REF!*1000 -> #REF! | E11: =#REF!*1000 -> #REF! | F11: =#REF!*1000 -> #REF! | G11: =#REF!*1000 -> #REF! | H11: =#REF!*1000 -> #REF! | I11: =#REF!*1000 -> #REF! | ... Q11: =#REF!*1000 -> #REF!
A12: Furniture | B12: =#REF!*1000 -> #REF! | C12: =#REF!*1000 -> #REF! | D12: =#REF!*1000 -> #REF! | E12: =#REF!*1000 -> #REF! | F12: =#REF!*1000 -> #REF! | G12: =#REF!*1000 -> #REF! | H12: =#REF!*1000 -> #REF! | I12: =#REF!*1000 -> #REF! | ... Q12: =#REF!*1000 -> #REF!
A13: Vehicles | B13: =#REF!*1000 -> #REF! | C13: =#REF!*1000 -> #REF! | D13: =#REF!*1000 -> #REF! | E13: =#REF!*1000 -> #REF! | F13: =#REF!*1000 -> #REF! | G13: =#REF!*1000 -> #REF! | H13: =#REF!*1000 -> #REF! | I13: =#REF!*1000 -> #REF! | ... Q13: =#REF!*1000 -> #REF!
... A26: Totassets | B26: =#REF!*1000 -> #REF! | C26: =#REF!*1000 -> #REF! | D26: =#REF!*1000 -> #REF! | E26: =#REF!*1000 -> #REF! | F26: =#REF!*1000 -> #REF! | G26: =#REF!*1000 -> #REF! | H26: =#REF!*1000 -> #REF! | I26: =#REF!*1000 -> #REF! | ... Q26: =#REF!*1000 -> #REF!
A27: Months | B27: 12 | C27: 12 | D27: 12 | E27: 12 | F27: 12 | G27: 12 | H27: 12 | I27: 12 | J27: 12 | K27: 12 | L27: 12 | M27: 12 | N27: 12 | O27: 12 | P27: 12 | Q27: 12

Sheet IS_AC
A1: Year | B1: =#REF! -> #REF! | C1: =#REF! -> #REF! | D1: =#REF! -> #REF! | E1: =#REF! -> #REF! | F1: =#REF! -> #REF! | G1: =#REF! -> #REF! | H1: =#REF! -> #REF! | I1: =#REF! -> #REF! | ... Q1: =#REF! -> #REF!
A2: Sales | B2: =#REF!*1000 -> #REF! | C2: =#REF!*1000 -> #REF! | D2: =#REF!*1000 -> #REF! | E2: =#REF!*1000 -> #REF! | F2: =#REF!*1000 -> #REF! | G2: =#REF!*1000 -> #REF! | H2: =#REF!*1000 -> #REF! | I2: =#REF!*1000 -> #REF! | ... Q2: =#REF!*1000 -> #REF!
A3: Rawmat | B3: =#REF!*1000 -> #REF! | C3: =#REF!*1000 -> #REF! | D3: =#REF!*1000 -> #REF! | E3: =#REF!*1000 -> #REF! | F3: =#REF!*1000 -> #REF! | G3: =#REF!*1000 -> #REF! | H3: =#REF!*1000 -> #REF! | I3: =#REF!*1000 -> #REF! | ... Q3: =#REF!*1000 -> #REF!
A4: Dirlab | B4: =#REF!*1000 -> #REF! | C4: =#REF!*1000 -> #REF! | D4: =#REF!*1000 -> #REF! | E4: =#REF!*1000 -> #REF! | F4: =#REF!*1000 -> #REF! | G4: =#REF!*1000 -> #REF! | H4: =#REF!*1000 -> #REF! | I4: =#REF!*1000 -> #REF! | ... Q4: =#REF!*1000 -> #REF!
A5: Utils | B5: =#REF!*1000 -> #REF! | C5: =#REF!*1000 -> #REF! | D5: =#REF!*1000 -> #REF! | E5: =#REF!*1000 -> #REF! | F5: =#REF!*1000 -> #REF! | G5: =#REF!*1000 -> #REF! | H5: =#REF!*1000 -> #REF! | I5: =#REF!*1000 -> #REF! | ... Q5: =#REF!*1000 -> #REF!
A6: Maint | B6: =#REF!*1000 -> #REF! | C6: =#REF!*1000 -> #REF! | D6: =#REF!*1000 -> #REF! | E6: =#REF!*1000 -> #REF! | F6: =#REF!*1000 -> #REF! | G6: =#REF!*1000 -> #REF! | H6: =#REF!*1000 -> #REF! | I6: =#REF!*1000 -> #REF! | ... Q6: =#REF!*1000 -> #REF!
A7: Deprec | B7: =#REF!*1000 -> #REF! | C7: =#REF!*1000 -> #REF! | D7: =#REF!*1000 -> #REF! | E7: =#REF!*1000 -> #REF! | F7: =#REF!*1000 -> #REF! | G7: =#REF!*1000 -> #REF! | H7: =#REF!*1000 -> #REF! | I7: =#REF!*1000 -> #REF! | ... Q7: =#REF!*1000 -> #REF!
A8: Amort | B8: =#REF!*1000 -> #REF! | C8: =#REF!*1000 -> #REF! | D8: =#REF!*1000 -> #REF! | E8: =#REF!*1000 -> #REF! | F8: =#REF!*1000 -> #REF! | G8: =#REF!*1000 -> #REF! | H8: =#REF!*1000 -> #REF! | I8: =#REF!*1000 -> #REF! | ... Q8: =#REF!*1000 -> #REF!
A9: Othdirexp | B9: =#REF!*1000 -> #REF! | C9: =#REF!*1000 -> #REF! | D9: =#REF!*1000 -> #REF! | E9: =#REF!*1000 -> #REF! | F9: =#REF!*1000 -> #REF! | G9: =#REF!*1000 -> #REF! | H9: =#REF!*1000 -> #REF! | I9: =#REF!*1000 -> #REF! | ... Q9: =#REF!*1000 -> #REF!
A10: Cgs | B10: =#REF!*1000 -> #REF! | C10: =#REF!*1000 -> #REF! | D10: =#REF!*1000 -> #REF! | E10: =#REF!*1000 -> #REF! | F10: =#REF!*1000 -> #REF! | G10: =#REF!*1000 -> #REF! | H10: =#REF!*1000 -> #REF! | I10: =#REF!*1000 -> #REF! | ... Q10: =#REF!*1000 -> #REF!
A11: Grossmar | B11: =#REF!*1000 -> #REF! | C11: =#REF!*1000 -> #REF! | D11: =#REF!*1000 -> #REF! | E11: =#REF!*1000 -> #REF! | F11: =#REF!*1000 -> #REF! | G11: =#REF!*1000 -> #REF! | H11: =#REF!*1000 -> #REF! | I11: =#REF!*1000 -> #REF! | ... Q11: =#REF!*1000 -> #REF!
A12: Salesad | B12: =#REF!*1000 -> #REF! | C12: =#REF!*1000 -> #REF! | D12: =#REF!*1000 -> #REF! | E12: =#REF!*1000 -> #REF! | F12: =#REF!*1000 -> #REF! | G12: =#REF!*1000 -> #REF! | H12: =#REF!*1000 -> #REF! | I12: =#REF!*1000 -> #REF! | ... Q12: =#REF!*1000 -> #REF!
A13: Salar | B13: =#REF!*1000 -> #REF! | C13: =#REF!*1000 -> #REF! | D13: =#REF!*1000 -> #REF! | E13: =#REF!*1000 -> #REF! | F13: =#REF!*1000 -> #REF! | G13: =#REF!*1000 -> #REF! | H13: =#REF!*1000 -> #REF! | I13: =#REF!*1000 -> #REF! | ... Q13: =#REF!*1000 -> #REF!
... A22: Retear | B22: =#REF!*1000 -> #REF! | C22: =#REF!*1000 -> #REF! | D22: =#REF!*1000 -> #REF! | E22: =#REF!*1000 -> #REF! | F22: =#REF!*1000 -> #REF! | G22: =#REF!*1000 -> #REF! | H22: =#REF!*1000 -> #REF! | I22: =#REF!*1000 -> #REF! | ... Q22: =#REF!*1000 -> #REF!
A23: Months | B23: 12 | C23: 12 | D23: 12 | E23: 12 | F23: 12 | G23: 12 | H23: 12 | I23: 12 | J23: 12 | K23: 12 | L23: 12 | M23: 12 | N23: 12 | O23: 12 | P23: 12 | Q23: 12

Sheet FS
A1: FSYEAR | B1: =#REF! -> #REF! | C1: =#REF! -> #REF! | D1: =#REF! -> #REF! | E1: =#REF! -> #REF! | F1: =#REF! -> #REF! | G1: =#REF! -> #REF! | H1: =#REF! -> #REF! | I1: =#REF! -> #REF! | ... Q1: =#REF! -> #REF!
A2: =SUBSTITUTE(#REF!," ","") -> #REF! | B2: =#REF!*1000 -> #REF! | C2: =#REF! -> #REF! | D2: =#REF! -> #REF! | E2: =#REF! -> #REF! | F2: =#REF! -> #REF! | G2: =#REF! -> #REF! | H2: =#REF! -> #REF! | I2: =#REF! -> #REF! | J2: =#REF! -> #REF! | ... Q2: =#REF! -> #REF!
A3: =SUBSTITUTE(#REF!," ","") -> #REF! | B3: =#REF!*1000 -> #REF! | C3: =#REF! -> #REF! | D3: =#REF! -> #REF! | E3: =#REF! -> #REF! | F3: =#REF! -> #REF! | G3: =#REF! -> #REF! | H3: =#REF! -> #REF! | I3: =#REF! -> #REF! | J3: =#REF! -> #REF! | ... Q3: =#REF! -> #REF!
A4: =SUBSTITUTE(#REF!," ","") -> #REF! | B4: =#REF!*1000 -> #REF! | C4: =#REF! -> #REF! | D4: =#REF! -> #REF! | E4: =#REF! -> #REF! | F4: =#REF! -> #REF! | G4: =#REF! -> #REF! | H4: =#REF! -> #REF! | I4: =#REF! -> #REF! | J4: =#REF! -> #REF! | ... Q4: =#REF! -> #REF!
A5: =SUBSTITUTE(#REF!," ","") -> #REF! | B5: =#REF!*1000 -> #REF! | C5: =#REF! -> #REF! | D5: =#REF! -> #REF! | E5: =#REF! -> #REF! | F5: =#REF! -> #REF! | G5: =#REF! -> #REF! | H5: =#REF! -> #REF! | I5: =#REF! -> #REF! | J5: =#REF! -> #REF! | ... Q5: =#REF! -> #REF!
A6: =SUBSTITUTE(#REF!," ","") -> #REF! | B6: =#REF!*1000 -> #REF! | C6: =#REF! -> #REF! | D6: =#REF! -> #REF! | E6: =#REF! -> #REF! | F6: =#REF! -> #REF! | G6: =#REF! -> #REF! | H6: =#REF! -> #REF! | I6: =#REF! -> #REF! | J6: =#REF! -> #REF! | ... Q6: =#REF! -> #REF!
A7: =SUBSTITUTE(#REF!," ","") -> #REF! | B7: =#REF!*1000 -> #REF! | C7: =#REF! -> #REF! | D7: =#REF! -> #REF! | E7: =#REF! -> #REF! | F7: =#REF! -> #REF! | G7: =#REF! -> #REF! | H7: =#REF! -> #REF! | I7: =#REF! -> #REF! | J7: =#REF! -> #REF! | ... Q7: =#REF! -> #REF!
A8: =SUBSTITUTE(#REF!," ","") -> #REF! | B8: =#REF!*1000 -> #REF! | C8: =#REF! -> #REF! | D8: =#REF! -> #REF! | E8: =#REF! -> #REF! | F8: =#REF! -> #REF! | G8: =#REF! -> #REF! | H8: =#REF! -> #REF! | I8: =#REF! -> #REF! | J8: =#REF! -> #REF! | ... Q8: =#REF! -> #REF!
A9: =SUBSTITUTE(#REF!," ","") -> #REF! | B9: =#REF!*1000 -> #REF! | C9: =#REF! -> #REF! | D9: =#REF! -> #REF! | E9: =#REF! -> #REF! | F9: =#REF! -> #REF! | G9: =#REF! -> #REF! | H9: =#REF! -> #REF! | I9: =#REF! -> #REF! | J9: =#REF! -> #REF! | ... Q9: =#REF! -> #REF!
A10: =#REF! -> #REF! | B10: =#REF!*1000 -> #REF! | C10: =#REF! -> #REF! | D10: =#REF! -> #REF! | E10: =#REF! -> #REF! | F10: =#REF! -> #REF! | G10: =#REF! -> #REF! | H10: =#REF! -> #REF! | I10: =#REF! -> #REF! | J10: =#REF! -> #REF! | ... Q10: =#REF! -> #REF!
A11: =SUBSTITUTE(#REF!," ","") -> #REF! | B11: =#REF!*1000 -> #REF! | C11: =#REF! -> #REF! | D11: =#REF! -> #REF! | E11: =#REF! -> #REF! | F11: =#REF! -> #REF! | G11: =#REF! -> #REF! | H11: =#REF! -> #REF! | I11: =#REF! -> #REF! | J11: =#REF! -> #REF! | ... Q11: =#REF! -> #REF!
A12: =SUBSTITUTE(#REF!," ","") -> #REF! | B12: =#REF!*1000 -> #REF! | C12: =#REF! -> #REF! | D12: =#REF! -> #REF! | E12: =#REF! -> #REF! | F12: =#REF! -> #REF! | G12: =#REF! -> #REF! | H12: =#REF! -> #REF! | I12: =#REF! -> #REF! | J12: =#REF! -> #REF! | ... Q12: =#REF! -> #REF!
A13: =SUBSTITUTE(#REF!," ","") -> #REF! | B13: =#REF!*1000 -> #REF! | C13: =#REF! -> #REF! | D13: =#REF! -> #REF! | E13: =#REF! -> #REF! | F13: =#REF! -> #REF! | G13: =#REF! -> #REF! | H13: =#REF! -> #REF! | I13: =#REF! -> #REF! | J13: =#REF! -> #REF! | ... Q13: =#REF! -> #REF!
A14: =SUBSTITUTE(#REF!," ","") -> #REF! | B14: =#REF!*1000 -> #REF! | C14: =#REF! -> #REF! | D14: =#REF! -> #REF! | E14: =#REF! -> #REF! | F14: =#REF! -> #REF! | G14: =#REF! -> #REF! | H14: =#REF! -> #REF! | I14: =#REF! -> #REF! | J14: =#REF! -> #REF! | ... Q14: =#REF! -> #REF!
A15: =#REF! -> #REF! | B15: =#REF!*1000 -> #REF! | C15: =#REF! -> #REF! | D15: =#REF! -> #REF! | E15: =#REF! -> #REF! | F15: =#REF! -> #REF! | G15: =#REF! -> #REF! | H15: =#REF! -> #REF! | I15: =#REF! -> #REF! | J15: =#REF! -> #REF! | ... Q15: =#REF! -> #REF!
A16: =SUBSTITUTE(#REF!," ","") -> #REF! | B16: =#REF! -> #REF! | C16: =#REF! -> #REF! | D16: =#REF! -> #REF! | E16: =#REF! -> #REF! | F16: =#REF! -> #REF! | G16: =#REF! -> #REF! | H16: =#REF! -> #REF! | I16: =#REF! -> #REF! | ... R16: =#REF! -> #REF!
A17: =SUBSTITUTE(#REF!," ","") -> #REF! | B17: =#REF! -> #REF! | C17: =#REF! -> #REF! | D17: =#REF! -> #REF! | E17: =#REF! -> #REF! | F17: =#REF! -> #REF! | G17: =#REF! -> #REF! | H17: =#REF! -> #REF! | I17: =#REF! -> #REF! | ... Q17: =#REF! -> #REF!
A18: =SUBSTITUTE(#REF!," ","") -> #REF! | B18: =#REF! -> #REF! | C18: =#REF! -> #REF! | D18: =#REF! -> #REF! | E18: =#REF! -> #REF! | F18: =#REF! -> #REF! | G18: =#REF! -> #REF! | H18: =#REF! -> #REF! | I18: =#REF! -> #REF! | ... Q18: =#REF! -> #REF!
A19: =SUBSTITUTE(#REF!," ","") -> #REF! | B19: =#REF! -> #REF! | C19: =#REF! -> #REF! | D19: =#REF! -> #REF! | E19: =#REF! -> #REF! | F19: =#REF! -> #REF! | G19: =#REF! -> #REF! | H19: =#REF! -> #REF! | I19: =#REF! -> #REF! | ... Q19: =#REF! -> #REF!
A20: =SUBSTITUTE(#REF!," ","") -> #REF! | B20: =#REF! -> #REF! | C20: =#REF! -> #REF! | D20: =#REF! -> #REF! | E20: =#REF! -> #REF! | F20: =#REF! -> #REF! | G20: =#REF! -> #REF! | H20: =#REF! -> #REF! | I20: =#REF! -> #REF! | ... Q20: =#REF! -> #REF!
A21: =SUBSTITUTE(#REF!," ","") -> #REF! | B21: =#REF! -> #REF! | C21: =#REF! -> #REF! | D21: =#REF! -> #REF! | E21: =#REF! -> #REF! | F21: =#REF! -> #REF! | G21: =#REF! -> #REF! | H21: =#REF! -> #REF! | I21: =#REF! -> #REF! | ... Q21: =#REF! -> #REF!

Sheet GAV
A1: =#REF! -> #REF!
A2: =#REF! -> #REF!

Sheet Assumptions
J1: FORECAST ASSUMPTIONS | P1: Attachment C-1
A5: 1. | B5: Sales Assumptions: The following tables set out the selling price per product, raw material cost per product and quantities of the various product lines to be sold in each of the forecast years. It further show the contributin per product (percentage o
B6: margine left after deducting the RM cost from the selling price).
C8: Product Line | D8: Unit | E8: SR | G8: Contribution | H8: ='Financial Stat.'!C318 -> 2026 | I8: =""&'Financial Stat.'!D318 -> 2027 | J8: =""&'Financial Stat.'!E318 -> 2028 | K8: =""&'Financial Stat.'!F318 -> 2029 | L8: =""&'Financial Stat.'!G318 -> 2030 | M8: =""&'Financial Stat.'!H318 -> 2031 | N8: =""&'Financial Stat.'!I318 -> 2032 | O8: =""&'Financial Stat.'!J318 -> 2033 | P8: =""&'Financial Stat.'!K318 -> 2034 | ... V8: =""&'Financial Stat.'!Q318 -> 2040 | X8: =""&'Financial Stat.'!S318 -> 2042 | Y8: =""&'Financial Stat.'!T318 -> 2043
D9: Type | E9: Selling Price | F9: RM Cost | G9: Per Product | H9: Volume | I9: Volume | J9: Volume | K9: Volume | L9: Volume | M9: Volume | N9: Volume | O9: Volume | P9: Volume | Q9: Volume | R9: Volume | S9: Volume | T9: Volume | U9: Volume | V9: Volume | X9: Volume | Y9: Volume
G10: =IF(E10=0," ",1-(F10/E10))
C11: PET Cups Local | E11: =8190*0.8 -> 6552 | F11: =3648 -> 3648 | G11: =IF(E11=0," ",1-(F11/E11)) -> 0.44322344 | H11: 625 | I11: 800 | J11: 1050 | K11: 1400 | L11: 1800 | M11: 1800 | N11: 1800 | O11: 1800 | P11: 1800 | Q11: 1800 | R11: 1800 | S11: 1800 | T11: 1800 | U11: 1800 | V11: 1800
C12: PET Cups (Export) | E12: =8190*0.8 -> 6552 | F12: =3648 -> 3648 | G12: =IF(E12=0," ",1-(F12/E12)) -> 0.44322344 | H12: 75 | I12: 100 | J12: 150 | K12: 200 | L12: 300 | M12: 300 | N12: 300 | O12: 300 | P12: 300 | Q12: 300 | R12: 300 | S12: 300 | T12: 300 | U12: 300 | V12: 300
C13: PP Containers Local | E13: =9178*0.8 -> 7342.4 | F13: =3497 -> 3497 | G13: =IF(E13=0," ",1-(F13/E13)) -> 0.52372521 | H13: 1440 | I13: 1530 | J13: 1575 | K13: 1600 | L13: 1650 | M13: 1650 | N13: 1650 | O13: 1650 | P13: 1650 | Q13: 1650 | R13: 1650 | S13: 1650 | T13: 1650 | U13: 1650 | V13: 1650
C14: PP Containers (Export) | E14: =8911*0.8 -> 7128.8 | F14: =3497 -> 3497 | G14: =IF(E14=0," ",1-(F14/E14)) -> 0.50945461 | H14: 195 | I14: 205 | J14: 215 | K14: 225 | L14: 230 | M14: 230 | N14: 230 | O14: 230 | P14: 230 | Q14: 230 | R14: 230 | S14: 230 | T14: 230 | U14: 230 | V14: 230
C15: PET Containers Local | E15: =6256*0.8 -> 5004.8 | F15: =3648 -> 3648 | G15: =IF(E15=0," ",1-(F15/E15)) -> 0.27109974 | H15: 285 | I15: 300 | J15: 330 | K15: 350 | L15: 365 | M15: 365 | N15: 365 | O15: 365 | P15: 365 | Q15: 365 | R15: 365 | S15: 365 | T15: 365 | U15: 365 | V15: 365
C16: PET Containers (Export) | E16: =6764*0.8 -> 5411.2 | F16: =3648 -> 3648 | G16: =IF(E16=0," ",1-(F16/E16)) -> 0.3258427 | H16: 45 | I16: 50 | J16: 55 | K16: 60 | L16: 70 | M16: 70 | N16: 70 | O16: 70 | P16: 70 | Q16: 70 | R16: 70 | S16: 70 | T16: 70 | U16: 70 | V16: 70
G17: =IF(E17=0," ",1-(F17/E17))
G18: =IF(E18=0," ",1-(F18/E18))
G19: =IF(E19=0," ",1-(F19/E19))
G20: =IF(E20=0," ",1-(F20/E20))
G21: =IF(E21=0," ",1-(F21/E21))
G22: =IF(E22=0," ",1-(F22/E22))
G23: =IF(E23=0," ",1-(F23/E23))
G24: =IF(E24=0," ",1-(F24/E24))
G25: =IF(E25=0," ",1-(F25/E25))
G26: =IF(E26=0," ",1-(F26/E26))
G27: =IF(E27=0," ",1-(F27/E27))
G28: =IF(E28=0," ",1-(F28/E28))
... G41: =IF(E41=0," ",1-(F41/E41))
D42: Total Units | H42: =SUM(H11:H40) -> 2665 | I42: =SUM(I11:I40) -> 2985 | J42: =SUM(J11:J40) -> 3375 | K42: =SUM(K11:K40) -> 3835 | L42: =SUM(L11:L40) -> 4415 | M42: =SUM(M11:M40) -> 4415 | N42: =SUM(N11:N40) -> 4415 | O42: =SUM(O11:O40) -> 4415 | ... V42: =SUM(V11:V40) -> 4415
A49: 2 | B49: Revenues Per Products: (SR'000) | L49: Attachment C-2
C52: Product Line | D52: =" "&'Financial Stat.'!C318 -> 2026 | E52: =" "&'Financial Stat.'!D318 -> 2027 | F52: =" "&'Financial Stat.'!E318 -> 2028 | G52: =" "&'Financial Stat.'!F318 -> 2029 | H52: =" "&'Financial Stat.'!G318 -> 2030 | I52: =" "&'Financial Stat.'!H318 -> 2031 | J52: =" "&'Financial Stat.'!I318 -> 2032 | K52: =" "&'Financial Stat.'!J318 -> 2033 | ... R52: =" "&'Financial Stat.'!Q318 -> 2040
D53: Revnue | E53: Revnue | F53: Revnue | G53: Revnue | H53: Revnue | I53: Revnue | J53: Revnue | K53: Revnue | L53: Revnue | M53: Revnue | N53: Revnue | O53: Revnue | P53: Revnue | Q53: Revnue | R53: Revnue
B55: =B11 -> 0 | C55: =IF(ISERR(TRIM(C11)),"",TRIM(C11)) -> PET Cups Local | D55: =ROUND((+H11*$E11)/1000,0) -> 4095 | E55: =ROUND((+I11*$E11)/1000,0) -> 5242 | F55: =ROUND((+J11*$E11)/1000,0) -> 6880 | G55: =ROUND((+K11*$E11)/1000,0) -> 9173 | H55: =ROUND((+L11*$E11)/1000,0) -> 11794 | I55: =ROUND((+M11*$E11)/1000,0) -> 11794 | J55: =ROUND((+N11*$E11)/1000,0) -> 11794 | K55: =ROUND((+O11*$E11)/1000,0) -> 11794 | ... R55: =ROUND((+V11*$E11)/1000,0) -> 11794
B56: =B12 -> 0 | C56: =IF(ISERR(TRIM(C12)),"",TRIM(C12)) -> PET Cups (Export) | D56: =ROUND((+H12*$E12)/1000,0) -> 491 | E56: =ROUND((+I12*$E12)/1000,0) -> 655 | F56: =ROUND((+J12*$E12)/1000,0) -> 983 | G56: =ROUND((+K12*$E12)/1000,0) -> 1310 | H56: =ROUND((+L12*$E12)/1000,0) -> 1966 | I56: =ROUND((+M12*$E12)/1000,0) -> 1966 | J56: =ROUND((+N12*$E12)/1000,0) -> 1966 | K56: =ROUND((+O12*$E12)/1000,0) -> 1966 | ... R56: =ROUND((+V12*$E12)/1000,0) -> 1966
B57: =B13 -> 0 | C57: =IF(ISERR(TRIM(C13)),"",TRIM(C13)) -> PP Containers Local | D57: =ROUND((+H13*$E13)/1000,0) -> 10573 | E57: =ROUND((+I13*$E13)/1000,0) -> 11234 | F57: =ROUND((+J13*$E13)/1000,0) -> 11564 | G57: =ROUND((+K13*$E13)/1000,0) -> 11748 | H57: =ROUND((+L13*$E13)/1000,0) -> 12115 | I57: =ROUND((+M13*$E13)/1000,0) -> 12115 | J57: =ROUND((+N13*$E13)/1000,0) -> 12115 | K57: =ROUND((+O13*$E13)/1000,0) -> 12115 | ... R57: =ROUND((+V13*$E13)/1000,0) -> 12115
B58: =B14 -> 0 | C58: =IF(ISERR(TRIM(C14)),"",TRIM(C14)) -> PP Containers (Export) | D58: =ROUND((+H14*$E14)/1000,0) -> 1390 | E58: =ROUND((+I14*$E14)/1000,0) -> 1461 | F58: =ROUND((+J14*$E14)/1000,0) -> 1533 | G58: =ROUND((+K14*$E14)/1000,0) -> 1604 | H58: =ROUND((+L14*$E14)/1000,0) -> 1640 | I58: =ROUND((+M14*$E14)/1000,0) -> 1640 | J58: =ROUND((+N14*$E14)/1000,0) -> 1640 | K58: =ROUND((+O14*$E14)/1000,0) -> 1640 | ... R58: =ROUND((+V14*$E14)/1000,0) -> 1640
B59: =B15 -> 0 | C59: =IF(ISERR(TRIM(C15)),"",TRIM(C15)) -> PET Containers Local | D59: =ROUND((+H15*$E15)/1000,0) -> 1426 | E59: =ROUND((+I15*$E15)/1000,0) -> 1501 | F59: =ROUND((+J15*$E15)/1000,0) -> 1652 | G59: =ROUND((+K15*$E15)/1000,0) -> 1752 | H59: =ROUND((+L15*$E15)/1000,0) -> 1827 | I59: =ROUND((+M15*$E15)/1000,0) -> 1827 | J59: =ROUND((+N15*$E15)/1000,0) -> 1827 | K59: =ROUND((+O15*$E15)/1000,0) -> 1827 | ... R59: =ROUND((+V15*$E15)/1000,0) -> 1827
B60: =B16 -> 0 | C60: =IF(ISERR(TRIM(C16)),"",TRIM(C16)) -> PET Containers (Export) | D60: =ROUND((+H16*$E16)/1000,0) -> 244 | E60: =ROUND((+I16*$E16)/1000,0) -> 271 | F60: =ROUND((+J16*$E16)/1000,0) -> 298 | G60: =ROUND((+K16*$E16)/1000,0) -> 325 | H60: =ROUND((+L16*$E16)/1000,0) -> 379 | I60: =ROUND((+M16*$E16)/1000,0) -> 379 | J60: =ROUND((+N16*$E16)/1000,0) -> 379 | K60: =ROUND((+O16*$E16)/1000,0) -> 379 | ... R60: =ROUND((+V16*$E16)/1000,0) -> 379
B61: =B17 -> 0 | C61: =IF(ISERR(TRIM(C17)),"",TRIM(C17)) | D61: =ROUND((+H17*$E17)/1000,0) -> 0 | E61: =ROUND((+I17*$E17)/1000,0) -> 0 | F61: =ROUND((+J17*$E17)/1000,0) -> 0 | G61: =ROUND((+K17*$E17)/1000,0) -> 0 | H61: =ROUND((+L17*$E17)/1000,0) -> 0 | I61: =ROUND((+M17*$E17)/1000,0) -> 0 | J61: =ROUND((+N17*$E17)/1000,0) -> 0 | K61: =ROUND((+O17*$E17)/1000,0) -> 0 | ... R61: =ROUND((+V17*$E17)/1000,0) -> 0
B62: =B18 -> 0 | C62: =IF(ISERR(TRIM(C18)),"",TRIM(C18)) | D62: =ROUND((+H18*$E18)/1000,0) -> 0 | E62: =ROUND((+I18*$E18)/1000,0) -> 0 | F62: =ROUND((+J18*$E18)/1000,0) -> 0 | G62: =ROUND((+K18*$E18)/1000,0) -> 0 | H62: =ROUND((+L18*$E18)/1000,0) -> 0 | I62: =ROUND((+M18*$E18)/1000,0) -> 0 | J62: =ROUND((+N18*$E18)/1000,0) -> 0 | K62: =ROUND((+O18*$E18)/1000,0) -> 0 | ... R62: =ROUND((+V18*$E18)/1000,0) -> 0
B63: =B19 -> 0 | C63: =IF(ISERR(TRIM(C19)),"",TRIM(C19)) | D63: =ROUND((+H19*$E19)/1000,0) -> 0 | E63: =ROUND((+I19*$E19)/1000,0) -> 0 | F63: =ROUND((+J19*$E19)/1000,0) -> 0 | G63: =ROUND((+K19*$E19)/1000,0) -> 0 | H63: =ROUND((+L19*$E19)/1000,0) -> 0 | I63: =ROUND((+M19*$E19)/1000,0) -> 0 | J63: =ROUND((+N19*$E19)/1000,0) -> 0 | K63: =ROUND((+O19*$E19)/1000,0) -> 0 | ... R63: =ROUND((+V19*$E19)/1000,0) -> 0
B64: =B20 -> 0 | C64: =IF(ISERR(TRIM(C20)),"",TRIM(C20)) | D64: =ROUND((+H20*$E20)/1000,0) -> 0 | E64: =ROUND((+I20*$E20)/1000,0) -> 0 | F64: =ROUND((+J20*$E20)/1000,0) -> 0 | G64: =ROUND((+K20*$E20)/1000,0) -> 0 | H64: =ROUND((+L20*$E20)/1000,0) -> 0 | I64: =ROUND((+M20*$E20)/1000,0) -> 0 | J64: =ROUND((+N20*$E20)/1000,0) -> 0 | K64: =ROUND((+O20*$E20)/1000,0) -> 0 | ... R64: =ROUND((+V20*$E20)/1000,0) -> 0
B65: =B21 -> 0 | C65: =IF(ISERR(TRIM(C21)),"",TRIM(C21)) | D65: =ROUND((+H21*$E21)/1000,0) -> 0 | E65: =ROUND((+I21*$E21)/1000,0) -> 0 | F65: =ROUND((+J21*$E21)/1000,0) -> 0 | G65: =ROUND((+K21*$E21)/1000,0) -> 0 | H65: =ROUND((+L21*$E21)/1000,0) -> 0 | I65: =ROUND((+M21*$E21)/1000,0) -> 0 | J65: =ROUND((+N21*$E21)/1000,0) -> 0 | K65: =ROUND((+O21*$E21)/1000,0) -> 0 | ... R65: =ROUND((+V21*$E21)/1000,0) -> 0
B66: =B22 -> 0 | C66: =IF(ISERR(TRIM(C22)),"",TRIM(C22)) | D66: =ROUND((+H22*$E22)/1000,0) -> 0 | E66: =ROUND((+I22*$E22)/1000,0) -> 0 | F66: =ROUND((+J22*$E22)/1000,0) -> 0 | G66: =ROUND((+K22*$E22)/1000,0) -> 0 | H66: =ROUND((+L22*$E22)/1000,0) -> 0 | I66: =ROUND((+M22*$E22)/1000,0) -> 0 | J66: =ROUND((+N22*$E22)/1000,0) -> 0 | K66: =ROUND((+O22*$E22)/1000,0) -> 0 | ... R66: =ROUND((+V22*$E22)/1000,0) -> 0
... B84: =B40 -> 0 | C84: =IF(ISERR(TRIM(C40)),"",TRIM(C40)) | D84: =ROUND((+H40*$E40)/1000,0) -> 0 | E84: =ROUND((+I40*$E40)/1000,0) -> 0 | F84: =ROUND((+J40*$E40)/1000,0) -> 0 | G84: =ROUND((+K40*$E40)/1000,0) -> 0 | H84: =ROUND((+L40*$E40)/1000,0) -> 0 | I84: =ROUND((+M40*$E40)/1000,0) -> 0 | J84: =ROUND((+N40*$E40)/1000,0) -> 0 | K84: =ROUND((+O40*$E40)/1000,0) -> 0 | ... R84: =ROUND((+V40*$E40)/1000,0) -> 0
D86: =ROUND(SUM(D55:D84),0) -> 18219 | E86: =ROUND(SUM(E55:E84),0) -> 20364 | F86: =ROUND(SUM(F55:F84),0) -> 22910 | G86: =ROUND(SUM(G55:G84),0) -> 25912 | H86: =ROUND(SUM(H55:H84),0) -> 29721 | I86: =ROUND(SUM(I55:I84),0) -> 29721 | J86: =ROUND(SUM(J55:J84),0) -> 29721 | K86: =ROUND(SUM(K55:K84),0) -> 29721 | ... R86: =ROUND(SUM(R55:R84),0) -> 29721
AF88: Alt A | AG88: Print Out Income Statement
AE89: 0 | AG89: {goto}it~{goto}v6~{windowsoff}{paneloff}
AG90: {s}pssra1..l39~qagpq
A91: 3. | B91: Raw Material Cost Per product : (SR'000) | L91: Attachment C- 3 | AG91: {if t42=1}{branch v49}
AG92: {windowson}{panelon}{beep}{quit}
AG94: {if t42=1}{branch v55}
C95: Product Line | D95: =" "&'Financial Stat.'!C318 -> 2026 | E95: =" "&'Financial Stat.'!D318 -> 2027 | F95: =" "&'Financial Stat.'!E318 -> 2028 | G95: =" "&'Financial Stat.'!F318 -> 2029 | H95: =" "&'Financial Stat.'!G318 -> 2030 | I95: =" "&'Financial Stat.'!H318 -> 2031 | J95: =" "&'Financial Stat.'!I318 -> 2032 | K95: =" "&'Financial Stat.'!J318 -> 2033 | ... R95: =" "&'Financial Stat.'!Q318 -> 2040
D96: RM Cost | E96: RM Cost | F96: RM Cost | G96: RM Cost | H96: RM Cost | I96: RM Cost | J96: RM Cost | K96: RM Cost | L96: RM Cost | M96: RM Cost | N96: RM Cost | O96: RM Cost | P96: RM Cost | Q96: RM Cost | R96: RM Cost
B98: =B55 -> 0 | C98: =IF(ISERR(TRIM(C11)),"",TRIM(C11)) -> PET Cups Local | D98: =ROUND((+H11*$F11)/1000,0) -> 2280 | E98: =ROUND((+I11*$F11)/1000,0) -> 2918 | F98: =ROUND((+J11*$F11)/1000,0) -> 3830 | G98: =ROUND((+K11*$F11)/1000,0) -> 5107 | H98: =ROUND((+L11*$F11)/1000,0) -> 6566 | I98: =ROUND((+M11*$F11)/1000,0) -> 6566 | J98: =ROUND((+N11*$F11)/1000,0) -> 6566 | K98: =ROUND((+O11*$F11)/1000,0) -> 6566 | ... R98: =ROUND((+V11*$F11)/1000,0) -> 6566
B99: =B56 -> 0 | C99: =IF(ISERR(TRIM(C12)),"",TRIM(C12)) -> PET Cups (Export) | D99: =ROUND((+H12*$F12)/1000,0) -> 274 | E99: =ROUND((+I12*$F12)/1000,0) -> 365 | F99: =ROUND((+J12*$F12)/1000,0) -> 547 | G99: =ROUND((+K12*$F12)/1000,0) -> 730 | H99: =ROUND((+L12*$F12)/1000,0) -> 1094 | I99: =ROUND((+M12*$F12)/1000,0) -> 1094 | J99: =ROUND((+N12*$F12)/1000,0) -> 1094 | K99: =ROUND((+O12*$F12)/1000,0) -> 1094 | ... R99: =ROUND((+V12*$F12)/1000,0) -> 1094
B100: =B57 -> 0 | C100: =IF(ISERR(TRIM(C13)),"",TRIM(C13)) -> PP Containers Local | D100: =ROUND((+H13*$F13)/1000,0) -> 5036 | E100: =ROUND((+I13*$F13)/1000,0) -> 5350 | F100: =ROUND((+J13*$F13)/1000,0) -> 5508 | G100: =ROUND((+K13*$F13)/1000,0) -> 5595 | H100: =ROUND((+L13*$F13)/1000,0) -> 5770 | I100: =ROUND((+M13*$F13)/1000,0) -> 5770 | J100: =ROUND((+N13*$F13)/1000,0) -> 5770 | K100: =ROUND((+O13*$F13)/1000,0) -> 5770 | ... R100: =ROUND((+V13*$F13)/1000,0) -> 5770
B101: =B58 -> 0 | C101: =IF(ISERR(TRIM(C14)),"",TRIM(C14)) -> PP Containers (Export) | D101: =ROUND((+H14*$F14)/1000,0) -> 682 | E101: =ROUND((+I14*$F14)/1000,0) -> 717 | F101: =ROUND((+J14*$F14)/1000,0) -> 752 | G101: =ROUND((+K14*$F14)/1000,0) -> 787 | H101: =ROUND((+L14*$F14)/1000,0) -> 804 | I101: =ROUND((+M14*$F14)/1000,0) -> 804 | J101: =ROUND((+N14*$F14)/1000,0) -> 804 | K101: =ROUND((+O14*$F14)/1000,0) -> 804 | ... R101: =ROUND((+V14*$F14)/1000,0) -> 804
B102: =B59 -> 0 | C102: =IF(ISERR(TRIM(C15)),"",TRIM(C15)) -> PET Containers Local | D102: =ROUND((+H15*$F15)/1000,0) -> 1040 | E102: =ROUND((+I15*$F15)/1000,0) -> 1094 | F102: =ROUND((+J15*$F15)/1000,0) -> 1204 | G102: =ROUND((+K15*$F15)/1000,0) -> 1277 | H102: =ROUND((+L15*$F15)/1000,0) -> 1332 | I102: =ROUND((+M15*$F15)/1000,0) -> 1332 | J102: =ROUND((+N15*$F15)/1000,0) -> 1332 | K102: =ROUND((+O15*$F15)/1000,0) -> 1332 | ... R102: =ROUND((+V15*$F15)/1000,0) -> 1332
B103: =B60 -> 0 | C103: =IF(ISERR(TRIM(C16)),"",TRIM(C16)) -> PET Containers (Export) | D103: =ROUND((+H16*$F16)/1000,0) -> 164 | E103: =ROUND((+I16*$F16)/1000,0) -> 182 | F103: =ROUND((+J16*$F16)/1000,0) -> 201 | G103: =ROUND((+K16*$F16)/1000,0) -> 219 | H103: =ROUND((+L16*$F16)/1000,0) -> 255 | I103: =ROUND((+M16*$F16)/1000,0) -> 255 | J103: =ROUND((+N16*$F16)/1000,0) -> 255 | K103: =ROUND((+O16*$F16)/1000,0) -> 255 | ... R103: =ROUND((+V16*$F16)/1000,0) -> 255
B104: =B61 -> 0 | C104: =IF(ISERR(TRIM(C17)),"",TRIM(C17)) | D104: =ROUND((+H17*$F17)/1000,0) -> 0 | E104: =ROUND((+I17*$F17)/1000,0) -> 0 | F104: =ROUND((+J17*$F17)/1000,0) -> 0 | G104: =ROUND((+K17*$F17)/1000,0) -> 0 | H104: =ROUND((+L17*$F17)/1000,0) -> 0 | I104: =ROUND((+M17*$F17)/1000,0) -> 0 | J104: =ROUND((+N17*$F17)/1000,0) -> 0 | K104: =ROUND((+O17*$F17)/1000,0) -> 0 | ... R104: =ROUND((+V17*$F17)/1000,0) -> 0
B105: =B62 -> 0 | C105: =IF(ISERR(TRIM(C18)),"",TRIM(C18)) | D105: =ROUND((+H18*$F18)/1000,0) -> 0 | E105: =ROUND((+I18*$F18)/1000,0) -> 0 | F105: =ROUND((+J18*$F18)/1000,0) -> 0 | G105: =ROUND((+K18*$F18)/1000,0) -> 0 | H105: =ROUND((+L18*$F18)/1000,0) -> 0 | I105: =ROUND((+M18*$F18)/1000,0) -> 0 | J105: =ROUND((+N18*$F18)/1000,0) -> 0 | K105: =ROUND((+O18*$F18)/1000,0) -> 0 | ... R105: =ROUND((+V18*$F18)/1000,0) -> 0
B106: =B63 -> 0 | C106: =IF(ISERR(TRIM(C19)),"",TRIM(C19)) | D106: =ROUND((+H19*$F19)/1000,0) -> 0 | E106: =ROUND((+I19*$F19)/1000,0) -> 0 | F106: =ROUND((+J19*$F19)/1000,0) -> 0 | G106: =ROUND((+K19*$F19)/1000,0) -> 0 | H106: =ROUND((+L19*$F19)/1000,0) -> 0 | I106: =ROUND((+M19*$F19)/1000,0) -> 0 | J106: =ROUND((+N19*$F19)/1000,0) -> 0 | K106: =ROUND((+O19*$F19)/1000,0) -> 0 | ... R106: =ROUND((+V19*$F19)/1000,0) -> 0
B107: =B64 -> 0 | C107: =IF(ISERR(TRIM(C20)),"",TRIM(C20)) | D107: =ROUND((+H20*$F20)/1000,0) -> 0 | E107: =ROUND((+I20*$F20)/1000,0) -> 0 | F107: =ROUND((+J20*$F20)/1000,0) -> 0 | G107: =ROUND((+K20*$F20)/1000,0) -> 0 | H107: =ROUND((+L20*$F20)/1000,0) -> 0 | I107: =ROUND((+M20*$F20)/1000,0) -> 0 | J107: =ROUND((+N20*$F20)/1000,0) -> 0 | K107: =ROUND((+O20*$F20)/1000,0) -> 0 | ... R107: =ROUND((+V20*$F20)/1000,0) -> 0
B108: =B65 -> 0 | C108: =IF(ISERR(TRIM(C21)),"",TRIM(C21)) | D108: =ROUND((+H21*$F21)/1000,0) -> 0 | E108: =ROUND((+I21*$F21)/1000,0) -> 0 | F108: =ROUND((+J21*$F21)/1000,0) -> 0 | G108: =ROUND((+K21*$F21)/1000,0) -> 0 | H108: =ROUND((+L21*$F21)/1000,0) -> 0 | I108: =ROUND((+M21*$F21)/1000,0) -> 0 | J108: =ROUND((+N21*$F21)/1000,0) -> 0 | K108: =ROUND((+O21*$F21)/1000,0) -> 0 | ... R108: =ROUND((+V21*$F21)/1000,0) -> 0
B109: =B66 -> 0 | C109: =IF(ISERR(TRIM(C22)),"",TRIM(C22)) | D109: =ROUND((+H22*$F22)/1000,0) -> 0 | E109: =ROUND((+I22*$F22)/1000,0) -> 0 | F109: =ROUND((+J22*$F22)/1000,0) -> 0 | G109: =ROUND((+K22*$F22)/1000,0) -> 0 | H109: =ROUND((+L22*$F22)/1000,0) -> 0 | I109: =ROUND((+M22*$F22)/1000,0) -> 0 | J109: =ROUND((+N22*$F22)/1000,0) -> 0 | K109: =ROUND((+O22*$F22)/1000,0) -> 0 | ... R109: =ROUND((+V22*$F22)/1000,0) -> 0
... B127: =B84 -> 0 | C127: =IF(ISERR(TRIM(C40)),"",TRIM(C40)) | D127: =ROUND((+H40*$F40)/1000,0) -> 0 | E127: =ROUND((+I40*$F40)/1000,0) -> 0 | F127: =ROUND((+J40*$F40)/1000,0) -> 0 | G127: =ROUND((+K40*$F40)/1000,0) -> 0 | H127: =ROUND((+L40*$F40)/1000,0) -> 0 | I127: =ROUND((+M40*$F40)/1000,0) -> 0 | J127: =ROUND((+N40*$F40)/1000,0) -> 0 | K127: =ROUND((+O40*$F40)/1000,0) -> 0 | ... R127: =ROUND((+V40*$F40)/1000,0) -> 0
D129: =ROUND(SUM(D98:D127),0) -> 9476 | E129: =ROUND(SUM(E98:E127),0) -> 10626 | F129: =ROUND(SUM(F98:F127),0) -> 12042 | G129: =ROUND(SUM(G98:G127),0) -> 13715 | H129: =ROUND(SUM(H98:H127),0) -> 15821 | I129: =ROUND(SUM(I98:I127),0) -> 15821 | J129: =ROUND(SUM(J98:J127),0) -> 15821 | K129: =ROUND(SUM(K98:K127),0) -> 15821 | ... R129: =ROUND(SUM(R98:R127),0) -> 15821
O132: Attachment C- 4
AF133: 1 | AG133: {let u130,1}{calc}
A134: 4 | B134: Manning Assumptions: The following tables set out the total manning requirements of the project broken down into years and positions. Positions are further summed up into either salaries (indirect) and wages | AF134: {panelon}{beep}{beep}{quit}
B135: (direct). The wages and salaries shown are annual amounts.
C139: Indirect | D139: Basic Salary | E139: Benefit | F139: =" "&'Financial Stat.'!C318 -> 2026 | G139: =" "&'Financial Stat.'!D318 -> 2027 | H139: =" "&'Financial Stat.'!E318 -> 2028 | I139: =" "&'Financial Stat.'!F318 -> 2029 | J139: =" "&'Financial Stat.'!G318 -> 2030 | K139: =" "&'Financial Stat.'!H318 -> 2031 | L139: =" "&'Financial Stat.'!I318 -> 2032 | M139: =" "&'Financial Stat.'!J318 -> 2033 | ... T139: =" "&'Financial Stat.'!Q318 -> 2040
C140: Positions | D140: in SR | E140: Rate | F140: No. of Staff | G140: No. of Staff | H140: No. of Staff | I140: No. of Staff | J140: No. of Staff | K140: No. of Staff | L140: No. of Staff | M140: No. of Staff | N140: No. of Staff | O140: No. of Staff | P140: No. of Staff | Q140: No. of Staff | R140: No. of Staff | S140: No. of Staff | T140: No. of Staff
C162: Total | D162: Annual Cost (SR'000) | F162: =ROUND((SUMPRODUCT($D142:$D161,F142:F161)+SUMPRODUCT($D142:$D161,$E142:$E161,F142:F161))/1000,0) -> 0 | G162: =ROUND((SUMPRODUCT($D142:$D161,G142:G161)+SUMPRODUCT($D142:$D161,$E142:$E161,G142:G161))/1000,0) -> 0 | H162: =ROUND((SUMPRODUCT($D142:$D161,H142:H161)+SUMPRODUCT($D142:$D161,$E142:$E161,H142:H161))/1000,0) -> 0 | I162: =ROUND((SUMPRODUCT($D142:$D161,I142:I161)+SUMPRODUCT($D142:$D161,$E142:$E161,I142:I161))/1000,0) -> 0 | J162: =ROUND((SUMPRODUCT($D142:$D161,J142:J161)+SUMPRODUCT($D142:$D161,$E142:$E161,J142:J161))/1000,0) -> 0 | K162: =ROUND((SUMPRODUCT($D142:$D161,K142:K161)+SUMPRODUCT($D142:$D161,$E142:$E161,K142:K161))/1000,0) -> 0 | L162: =ROUND((SUMPRODUCT($D142:$D161,L142:L161)+SUMPRODUCT($D142:$D161,$E142:$E161,L142:L161))/1000,0) -> 0 | M162: =ROUND((SUMPRODUCT($D142:$D161,M142:M161)+SUMPRODUCT($D142:$D161,$E142:$E161,M142:M161))/1000,0) -> 0 | ... T162: =ROUND((SUMPRODUCT($D142:$D161,T142:T161)+SUMPRODUCT($D142:$D161,$E142:$E161,T142:T161))/1000,0) -> 0
C166: Direct | D166: Basic Salary | E166: Benefit | F166: =" "&'Financial Stat.'!C318 -> 2026 | G166: =" "&'Financial Stat.'!D318 -> 2027 | H166: =" "&'Financial Stat.'!E318 -> 2028 | I166: =" "&'Financial Stat.'!F318 -> 2029 | J166: =" "&'Financial Stat.'!G318 -> 2030 | K166: =" "&'Financial Stat.'!H318 -> 2031 | L166: =" "&'Financial Stat.'!I318 -> 2032 | M166: =" "&'Financial Stat.'!J318 -> 2033 | ... T166: =" "&'Financial Stat.'!Q318 -> 2040
C167: Positions | D167: in SR | E167: Rate | F167: No. of Staff | G167: No. of Staff | H167: No. of Staff | I167: No. of Staff | J167: No. of Staff | K167: No. of Staff | L167: No. of Staff | M167: No. of Staff | N167: No. of Staff | O167: No. of Staff | P167: No. of Staff | Q167: No. of Staff | R167: No. of Staff | S167: No. of Staff | T167: No. of Staff
C169: Man power | D169: 2233308 | F169: 1 | G169: 1 | H169: 1 | I169: 1 | J169: 1 | K169: 1 | L169: 1 | M169: 1 | N169: 1 | O169: 1 | P169: 1 | Q169: 1 | R169: 1 | S169: 1 | T169: 1
C189: Total | D189: Annual Cost (SR'000) | F189: =ROUND((SUMPRODUCT($D169:$D188,F169:F188)+SUMPRODUCT($D169:$D188,$E169:$E188,F169:F188))/1000,0) -> 2233 | G189: =ROUND((SUMPRODUCT($D169:$D188,G169:G188)+SUMPRODUCT($D169:$D188,$E169:$E188,G169:G188))/1000,0) -> 2233 | H189: =ROUND((SUMPRODUCT($D169:$D188,H169:H188)+SUMPRODUCT($D169:$D188,$E169:$E188,H169:H188))/1000,0) -> 2233 | I189: =ROUND((SUMPRODUCT($D169:$D188,I169:I188)+SUMPRODUCT($D169:$D188,$E169:$E188,I169:I188))/1000,0) -> 2233 | J189: =ROUND((SUMPRODUCT($D169:$D188,J169:J188)+SUMPRODUCT($D169:$D188,$E169:$E188,J169:J188))/1000,0) -> 2233 | K189: =ROUND((SUMPRODUCT($D169:$D188,K169:K188)+SUMPRODUCT($D169:$D188,$E169:$E188,K169:K188))/1000,0) -> 2233 | L189: =ROUND((SUMPRODUCT($D169:$D188,L169:L188)+SUMPRODUCT($D169:$D188,$E169:$E188,L169:L188))/1000,0) -> 2233 | M189: =ROUND((SUMPRODUCT($D169:$D188,M169:M188)+SUMPRODUCT($D169:$D188,$E169:$E188,M169:M188))/1000,0) -> 2233 | ... T189: =ROUND((SUMPRODUCT($D169:$D188,T169:T188)+SUMPRODUCT($D169:$D188,$E169:$E188,T169:T188))/1000,0) -> 2233
P194: Attachment C- 5
A196: 5. | C196: Utilities Assumptions: Utilities expense is prorated based on sales and will not exceed that in the Maximum column. The capacity utilization figures are also based on sales. The capacity percent shown in
C197: the Maximum column is the maximum capacity utilization achieved. All values are SR in 000's.
D200: Maximum | E200: =" "&'Financial Stat.'!C318 -> 2026 | F200: =" "&'Financial Stat.'!D318 -> 2027 | G200: =" "&'Financial Stat.'!E318 -> 2028 | H200: =" "&'Financial Stat.'!F318 -> 2029 | I200: =" "&'Financial Stat.'!G318 -> 2030 | J200: =" "&'Financial Stat.'!H318 -> 2031 | K200: =" "&'Financial Stat.'!I318 -> 2032 | L200: =" "&'Financial Stat.'!J318 -> 2033 | ... S200: =" "&'Financial Stat.'!Q318 -> 2040
D201: Cost | E201: Cost | F201: Cost | G201: Cost | H201: Cost | I201: Cost | J201: Cost | K201: Cost | L201: Cost | M201: Cost | N201: Cost | O201: Cost | P201: Cost | Q201: Cost | R201: Cost | S201: Cost
AC202: =BASEYEAR -> 2025 | AD202: =AC202+1 -> 2026 | AE202: =AD202+1 -> 2027 | AF202: =AE202+1 -> 2028 | AG202: =AF202+1 -> 2029 | AH202: =AG202+1 -> 2030 | AI202: =AH202+1 -> 2031 | AJ202: =AI202+1 -> 2032 | AK202: =AJ202+1 -> 2033 | ... AV202: =AU202+1 -> 2044
C203: Capacity Used | D203: 0.97 | E203: =IF(ISERR((H42/MAX($H42:$Q42))*$D203),0,(H42/MAX($H42:$Q42))*$D203) -> 0.58551529 | F203: =IF(ISERR((I42/MAX($H42:$Q42))*$D203),0,(I42/MAX($H42:$Q42))*$D203) -> 0.65582106 | G203: =IF(ISERR((J42/MAX($H42:$Q42))*$D203),0,(J42/MAX($H42:$Q42))*$D203) -> 0.74150623 | H203: =IF(ISERR((K42/MAX($H42:$Q42))*$D203),0,(K42/MAX($H42:$Q42))*$D203) -> 0.84257078 | I203: =IF(ISERR((L42/MAX($H42:$Q42))*$D203),0,(L42/MAX($H42:$Q42))*$D203) -> 0.97 | J203: =IF(ISERR((M42/MAX($H42:$Q42))*$D203),0,(M42/MAX($H42:$Q42))*$D203) -> 0.97 | K203: =IF(ISERR((N42/MAX($H42:$Q42))*$D203),0,(N42/MAX($H42:$Q42))*$D203) -> 0.97 | L203: =IF(ISERR((O42/MAX($H42:$Q42))*$D203),0,(O42/MAX($H42:$Q42))*$D203) -> 0.97 | ... S203: =IF(ISERR((V42/MAX($H42:$Q42))*$D203),0,(V42/MAX($H42:$Q42))*$D203) -> 0.97 | AB203: Existing FA
AB204: Buildings | AC204: =IF($D334=0,0,ROUND(IF($D334*$D227>$D334-$E334,$D334-$E334,$D334*$D227),0)) -> 0 | AD204: =IF($D334=0,0,ROUND(IF($D334*$D227>$D334-($E334+AC204),$D334-$E334-AC204,$D334*$D227),0)) -> 0 | AE204: =IF($D334=0,0,ROUND(IF($D334*$D227>$D334-($E334+SUM($AC204:AD204)),$D334-$E334-SUM($AC204:AD204),$D334*$D227),0)) -> 0 | AF204: =IF($D334=0,0,ROUND(IF($D334*$D227>$D334-($E334+SUM($AC204:AE204)),$D334-$E334-SUM($AC204:AE204),$D334*$D227),0)) -> 0 | AG204: =IF($D334=0,0,ROUND(IF($D334*$D227>$D334-($E334+SUM($AC204:AF204)),$D334-$E334-SUM($AC204:AF204),$D334*$D227),0)) -> 0 | AH204: =IF($D334=0,0,ROUND(IF($D334*$D227>$D334-($E334+SUM($AC204:AG204)),$D334-$E334-SUM($AC204:AG204),$D334*$D227),0)) -> 0 | AI204: =IF($D334=0,0,ROUND(IF($D334*$D227>$D334-($E334+SUM($AC204:AH204)),$D334-$E334-SUM($AC204:AH204),$D334*$D227),0)) -> 0 | AJ204: =IF($D334=0,0,ROUND(IF($D334*$D227>$D334-($E334+SUM($AC204:AI204)),$D334-$E334-SUM($AC204:AI204),$D334*$D227),0)) -> 0 | AK204: =IF($D334=0,0,ROUND(IF($D334*$D227>$D334-($E334+SUM($AC204:AJ204)),$D334-$E334-SUM($AC204:AJ204),$D334*$D227),0)) -> 0 | AL204: =IF($D334=0,0,ROUND(IF($D334*$D227>$D334-($E334+SUM($AC204:AK204)),$D334-$E334-SUM($AC204:AK204),$D334*$D227),0)) -> 0 | ... AV204: =IF($D334=0,0,ROUND(IF($D334*$D227>$D334-($E334+SUM($AC204:AU204)),$D334-$E334-SUM($AC204:AU204),$D334*$D227),0)) -> 0
C205: Water | D205: 25 | E205: =IF(ISERR((E$203/$D$203)*$D205),0,ROUND((E$203/$D$203)*$D205,0)) -> 15 | F205: =IF(ISERR((F$203/$D$203)*$D205),0,ROUND((F$203/$D$203)*$D205,0)) -> 17 | G205: =IF(ISERR((G$203/$D$203)*$D205),0,ROUND((G$203/$D$203)*$D205,0)) -> 19 | H205: =IF(ISERR((H$203/$D$203)*$D205),0,ROUND((H$203/$D$203)*$D205,0)) -> 22 | I205: =IF(ISERR((I$203/$D$203)*$D205),0,ROUND((I$203/$D$203)*$D205,0)) -> 25 | J205: =IF(ISERR((J$203/$D$203)*$D205),0,ROUND((J$203/$D$203)*$D205,0)) -> 25 | K205: =IF(ISERR((K$203/$D$203)*$D205),0,ROUND((K$203/$D$203)*$D205,0)) -> 25 | L205: =IF(ISERR((L$203/$D$203)*$D205),0,ROUND((L$203/$D$203)*$D205,0)) -> 25 | ... S205: =IF(ISERR((S$203/$D$203)*$D205),0,ROUND((S$203/$D$203)*$D205,0)) -> 25 | AB205: Machinery | AC205: =IF($D335=0,0,ROUND(IF($D335*$D228>$D335-$E335,$D335-$E335,$D335*$D228),0)) -> 0 | AD205: =IF($D335=0,0,ROUND(IF($D335*$D228>$D335-($E335+AC205),$D335-$E335-AC205,$D335*$D228),0)) -> 0 | AE205: =IF($D335=0,0,ROUND(IF($D335*$D228>$D335-($E335+SUM($AC205:AD205)),$D335-$E335-SUM($AC205:AD205),$D335*$D228),0)) -> 0 | AF205: =IF($D335=0,0,ROUND(IF($D335*$D228>$D335-($E335+SUM($AC205:AE205)),$D335-$E335-SUM($AC205:AE205),$D335*$D228),0)) -> 0 | AG205: =IF($D335=0,0,ROUND(IF($D335*$D228>$D335-($E335+SUM($AC205:AF205)),$D335-$E335-SUM($AC205:AF205),$D335*$D228),0)) -> 0 | AH205: =IF($D335=0,0,ROUND(IF($D335*$D228>$D335-($E335+SUM($AC205:AG205)),$D335-$E335-SUM($AC205:AG205),$D335*$D228),0)) -> 0 | AI205: =IF($D335=0,0,ROUND(IF($D335*$D228>$D335-($E335+SUM($AC205:AH205)),$D335-$E335-SUM($AC205:AH205),$D335*$D228),0)) -> 0 | AJ205: =IF($D335=0,0,ROUND(IF($D335*$D228>$D335-($E335+SUM($AC205:AI205)),$D335-$E335-SUM($AC205:AI205),$D335*$D228),0)) -> 0 | AK205: =IF($D335=0,0,ROUND(IF($D335*$D228>$D335-($E335+SUM($AC205:AJ205)),$D335-$E335-SUM($AC205:AJ205),$D335*$D228),0)) -> 0 | AL205: =IF($D335=0,0,ROUND(IF($D335*$D228>$D335-($E335+SUM($AC205:AK205)),$D335-$E335-SUM($AC205:AK205),$D335*$D228),0)) -> 0 | ... AV205: =IF($D335=0,0,ROUND(IF($D335*$D228>$D335-($E335+SUM($AC205:AU205)),$D335-$E335-SUM($AC205:AU205),$D335*$D228),0)) -> 0
C206: Electricity | D206: 1880 | E206: =IF(ISERR((E$203/$D$203)*$D206),0,ROUND((E$203/$D$203)*$D206,0)) -> 1135 | F206: =IF(ISERR((F$203/$D$203)*$D206),0,ROUND((F$203/$D$203)*$D206,0)) -> 1271 | G206: =IF(ISERR((G$203/$D$203)*$D206),0,ROUND((G$203/$D$203)*$D206,0)) -> 1437 | H206: =IF(ISERR((H$203/$D$203)*$D206),0,ROUND((H$203/$D$203)*$D206,0)) -> 1633 | I206: =IF(ISERR((I$203/$D$203)*$D206),0,ROUND((I$203/$D$203)*$D206,0)) -> 1880 | J206: =IF(ISERR((J$203/$D$203)*$D206),0,ROUND((J$203/$D$203)*$D206,0)) -> 1880 | K206: =IF(ISERR((K$203/$D$203)*$D206),0,ROUND((K$203/$D$203)*$D206,0)) -> 1880 | L206: =IF(ISERR((L$203/$D$203)*$D206),0,ROUND((L$203/$D$203)*$D206,0)) -> 1880 | ... S206: =IF(ISERR((S$203/$D$203)*$D206),0,ROUND((S$203/$D$203)*$D206,0)) -> 1880 | AB206: Furniture | AC206: =IF($D336=0,0,ROUND(IF($D336*$D229>$D336-$E336,$D336-$E336,$D336*$D229),0)) -> 0 | AD206: =IF($D336=0,0,ROUND(IF($D336*$D229>$D336-($E336+AC206),$D336-$E336-AC206,$D336*$D229),0)) -> 0 | AE206: =IF($D336=0,0,ROUND(IF($D336*$D229>$D336-($E336+SUM($AC206:AD206)),$D336-$E336-SUM($AC206:AD206),$D336*$D229),0)) -> 0 | AF206: =IF($D336=0,0,ROUND(IF($D336*$D229>$D336-($E336+SUM($AC206:AE206)),$D336-$E336-SUM($AC206:AE206),$D336*$D229),0)) -> 0 | AG206: =IF($D336=0,0,ROUND(IF($D336*$D229>$D336-($E336+SUM($AC206:AF206)),$D336-$E336-SUM($AC206:AF206),$D336*$D229),0)) -> 0 | AH206: =IF($D336=0,0,ROUND(IF($D336*$D229>$D336-($E336+SUM($AC206:AG206)),$D336-$E336-SUM($AC206:AG206),$D336*$D229),0)) -> 0 | AI206: =IF($D336=0,0,ROUND(IF($D336*$D229>$D336-($E336+SUM($AC206:AH206)),$D336-$E336-SUM($AC206:AH206),$D336*$D229),0)) -> 0 | AJ206: =IF($D336=0,0,ROUND(IF($D336*$D229>$D336-($E336+SUM($AC206:AI206)),$D336-$E336-SUM($AC206:AI206),$D336*$D229),0)) -> 0 | AK206: =IF($D336=0,0,ROUND(IF($D336*$D229>$D336-($E336+SUM($AC206:AJ206)),$D336-$E336-SUM($AC206:AJ206),$D336*$D229),0)) -> 0 | AL206: =IF($D336=0,0,ROUND(IF($D336*$D229>$D336-($E336+SUM($AC206:AK206)),$D336-$E336-SUM($AC206:AK206),$D336*$D229),0)) -> 0 | AM206: =IF($D336=0,0,ROUND(IF($D336*$D229>$D336-($E336+SUM($AC206:AL206)),$D336-$E336-SUM($AC206:AL206),$D336*$D229),0)) -> 0 | AO206: =IF($D336=0,0,ROUND(IF($D336*$D229>$D336-($E336+SUM($AC206:AN206)),$D336-$E336-SUM($AC206:AN206),$D336*$D229),0)) -> 0 | AP206: =IF($D336=0,0,ROUND(IF($D336*$D229>$D336-($E336+SUM($AC206:AO206)),$D336-$E336-SUM($AC206:AO206),$D336*$D229),0)) -> 0 | AQ206: =IF($D336=0,0,ROUND(IF($D336*$D229>$D336-($E336+SUM($AC206:AP206)),$D336-$E336-SUM($AC206:AP206),$D336*$D229),0)) -> 0 | AR206: =IF($D336=0,0,ROUND(IF($D336*$D229>$D336-($E336+SUM($AC206:AQ206)),$D336-$E336-SUM($AC206:AQ206),$D336*$D229),0)) -> 0 | AS206: =IF($D336=0,0,ROUND(IF($D336*$D229>$D336-($E336+SUM($AC206:AR206)),$D336-$E336-SUM($AC206:AR206),$D336*$D229),0)) -> 0 | AT206: =IF($D336=0,0,ROUND(IF($D336*$D229>$D336-($E336+SUM($AC206:AS206)),$D336-$E336-SUM($AC206:AS206),$D336*$D229),0)) -> 0 | AU206: =IF($D336=0,0,ROUND(IF($D336*$D229>$D336-($E336+SUM($AC206:AT206)),$D336-$E336-SUM($AC206:AT206),$D336*$D229),0)) -> 0 | AV206: =IF($D336=0,0,ROUND(IF($D336*$D229>$D336-($E336+SUM($AC206:AU206)),$D336-$E336-SUM($AC206:AU206),$D336*$D229),0)) -> 0
C207: Telephone & Tlx | E207: =IF(ISERR((E$203/$D$203)*$D207),0,ROUND((E$203/$D$203)*$D207,0)) -> 0 | F207: =IF(ISERR((F$203/$D$203)*$D207),0,ROUND((F$203/$D$203)*$D207,0)) -> 0 | G207: =IF(ISERR((G$203/$D$203)*$D207),0,ROUND((G$203/$D$203)*$D207,0)) -> 0 | H207: =IF(ISERR((H$203/$D$203)*$D207),0,ROUND((H$203/$D$203)*$D207,0)) -> 0 | I207: =IF(ISERR((I$203/$D$203)*$D207),0,ROUND((I$203/$D$203)*$D207,0)) -> 0 | J207: =IF(ISERR((J$203/$D$203)*$D207),0,ROUND((J$203/$D$203)*$D207,0)) -> 0 | K207: =IF(ISERR((K$203/$D$203)*$D207),0,ROUND((K$203/$D$203)*$D207,0)) -> 0 | L207: =IF(ISERR((L$203/$D$203)*$D207),0,ROUND((L$203/$D$203)*$D207,0)) -> 0 | ... S207: =IF(ISERR((S$203/$D$203)*$D207),0,ROUND((S$203/$D$203)*$D207,0)) -> 0 | AB207: Vehicles | AC207: =IF($D337=0,0,ROUND(IF($D337*$D230>$D337-$E337,$D337-$E337,$D337*$D230),0)) -> 0 | AD207: =IF($D337=0,0,ROUND(IF($D337*$D230>$D337-($E337+AC207),$D337-$E337-AC207,$D337*$D230),0)) -> 0 | AE207: =IF($D337=0,0,ROUND(IF($D337*$D230>$D337-($E337+SUM($AC207:AD207)),$D337-$E337-SUM($AC207:AD207),$D337*$D230),0)) -> 0 | AF207: =IF($D337=0,0,ROUND(IF($D337*$D230>$D337-($E337+SUM($AC207:AE207)),$D337-$E337-SUM($AC207:AE207),$D337*$D230),0)) -> 0 | AG207: =IF($D337=0,0,ROUND(IF($D337*$D230>$D337-($E337+SUM($AC207:AF207)),$D337-$E337-SUM($AC207:AF207),$D337*$D230),0)) -> 0 | AH207: =IF($D337=0,0,ROUND(IF($D337*$D230>$D337-($E337+SUM($AC207:AG207)),$D337-$E337-SUM($AC207:AG207),$D337*$D230),0)) -> 0 | AI207: =IF($D337=0,0,ROUND(IF($D337*$D230>$D337-($E337+SUM($AC207:AH207)),$D337-$E337-SUM($AC207:AH207),$D337*$D230),0)) -> 0 | AJ207: =IF($D337=0,0,ROUND(IF($D337*$D230>$D337-($E337+SUM($AC207:AI207)),$D337-$E337-SUM($AC207:AI207),$D337*$D230),0)) -> 0 | AK207: =IF($D337=0,0,ROUND(IF($D337*$D230>$D337-($E337+SUM($AC207:AJ207)),$D337-$E337-SUM($AC207:AJ207),$D337*$D230),0)) -> 0 | AL207: =IF($D337=0,0,ROUND(IF($D337*$D230>$D337-($E337+SUM($AC207:AK207)),$D337-$E337-SUM($AC207:AK207),$D337*$D230),0)) -> 0 | ... AV207: =IF($D337=0,0,ROUND(IF($D337*$D230>$D337-($E337+SUM($AC207:AU207)),$D337-$E337-SUM($AC207:AU207),$D337*$D230),0)) -> 0
C208: Other | E208: =IF(ISERR((E$203/$D$203)*$D208),0,ROUND((E$203/$D$203)*$D208,0)) -> 0 | F208: =IF(ISERR((F$203/$D$203)*$D208),0,ROUND((F$203/$D$203)*$D208,0)) -> 0 | G208: =IF(ISERR((G$203/$D$203)*$D208),0,ROUND((G$203/$D$203)*$D208,0)) -> 0 | H208: =IF(ISERR((H$203/$D$203)*$D208),0,ROUND((H$203/$D$203)*$D208,0)) -> 0 | I208: =IF(ISERR((I$203/$D$203)*$D208),0,ROUND((I$203/$D$203)*$D208,0)) -> 0 | J208: =IF(ISERR((J$203/$D$203)*$D208),0,ROUND((J$203/$D$203)*$D208,0)) -> 0 | K208: =IF(ISERR((K$203/$D$203)*$D208),0,ROUND((K$203/$D$203)*$D208,0)) -> 0 | L208: =IF(ISERR((L$203/$D$203)*$D208),0,ROUND((L$203/$D$203)*$D208,0)) -> 0 | ... S208: =IF(ISERR((S$203/$D$203)*$D208),0,ROUND((S$203/$D$203)*$D208,0)) -> 0 | AB208: Loss Prevention | AC208: =IF($D338=0,0,ROUND(IF($D338*$D231>$D338-$E338,$D338-$E338,$D338*$D231),0)) -> 0 | AD208: =IF($D338=0,0,ROUND(IF($D338*$D231>$D338-($E338+AC208),$D338-$E338-AC208,$D338*$D231),0)) -> 0 | AE208: =IF($D338=0,0,ROUND(IF($D338*$D231>$D338-($E338+SUM($AC208:AD208)),$D338-$E338-SUM($AC208:AD208),$D338*$D231),0)) -> 0 | AF208: =IF($D338=0,0,ROUND(IF($D338*$D231>$D338-($E338+SUM($AC208:AE208)),$D338-$E338-SUM($AC208:AE208),$D338*$D231),0)) -> 0 | AG208: =IF($D338=0,0,ROUND(IF($D338*$D231>$D338-($E338+SUM($AC208:AF208)),$D338-$E338-SUM($AC208:AF208),$D338*$D231),0)) -> 0 | AH208: =IF($D338=0,0,ROUND(IF($D338*$D231>$D338-($E338+SUM($AC208:AG208)),$D338-$E338-SUM($AC208:AG208),$D338*$D231),0)) -> 0 | AI208: =IF($D338=0,0,ROUND(IF($D338*$D231>$D338-($E338+SUM($AC208:AH208)),$D338-$E338-SUM($AC208:AH208),$D338*$D231),0)) -> 0 | AJ208: =IF($D338=0,0,ROUND(IF($D338*$D231>$D338-($E338+SUM($AC208:AI208)),$D338-$E338-SUM($AC208:AI208),$D338*$D231),0)) -> 0 | AK208: =IF($D338=0,0,ROUND(IF($D338*$D231>$D338-($E338+SUM($AC208:AJ208)),$D338-$E338-SUM($AC208:AJ208),$D338*$D231),0)) -> 0 | AL208: =IF($D338=0,0,ROUND(IF($D338*$D231>$D338-($E338+SUM($AC208:AK208)),$D338-$E338-SUM($AC208:AK208),$D338*$D231),0)) -> 0 | ... AV208: =IF($D338=0,0,ROUND(IF($D338*$D231>$D338-($E338+SUM($AC208:AU208)),$D338-$E338-SUM($AC208:AU208),$D338*$D231),0)) -> 0
E209: =IF(ISERR((E$203/$D$203)*$D209),0,ROUND((E$203/$D$203)*$D209,0)) -> 0 | F209: =IF(ISERR((F$203/$D$203)*$D209),0,ROUND((F$203/$D$203)*$D209,0)) -> 0 | G209: =IF(ISERR((G$203/$D$203)*$D209),0,ROUND((G$203/$D$203)*$D209,0)) -> 0 | H209: =IF(ISERR((H$203/$D$203)*$D209),0,ROUND((H$203/$D$203)*$D209,0)) -> 0 | I209: =IF(ISERR((I$203/$D$203)*$D209),0,ROUND((I$203/$D$203)*$D209,0)) -> 0 | J209: =IF(ISERR((J$203/$D$203)*$D209),0,ROUND((J$203/$D$203)*$D209,0)) -> 0 | K209: =IF(ISERR((K$203/$D$203)*$D209),0,ROUND((K$203/$D$203)*$D209,0)) -> 0 | L209: =IF(ISERR((L$203/$D$203)*$D209),0,ROUND((L$203/$D$203)*$D209,0)) -> 0 | ... S209: =IF(ISERR((S$203/$D$203)*$D209),0,ROUND((S$203/$D$203)*$D209,0)) -> 0 | AB209: Other | AC209: =IF($D339=0,0,ROUND(IF($D339*$D232>$D339-$E339,$D339-$E339,$D339*$D232),0)) -> 0 | AD209: =IF($D339=0,0,ROUND(IF($D339*$D232>$D339-($E339+AC209),$D339-$E339-AC209,$D339*$D232),0)) -> 0 | AE209: =IF($D339=0,0,ROUND(IF($D339*$D232>$D339-($E339+SUM($AC209:AD209)),$D339-$E339-SUM($AC209:AD209),$D339*$D232),0)) -> 0 | AF209: =IF($D339=0,0,ROUND(IF($D339*$D232>$D339-($E339+SUM($AC209:AE209)),$D339-$E339-SUM($AC209:AE209),$D339*$D232),0)) -> 0 | AG209: =IF($D339=0,0,ROUND(IF($D339*$D232>$D339-($E339+SUM($AC209:AF209)),$D339-$E339-SUM($AC209:AF209),$D339*$D232),0)) -> 0 | AH209: =IF($D339=0,0,ROUND(IF($D339*$D232>$D339-($E339+SUM($AC209:AG209)),$D339-$E339-SUM($AC209:AG209),$D339*$D232),0)) -> 0 | AI209: =IF($D339=0,0,ROUND(IF($D339*$D232>$D339-($E339+SUM($AC209:AH209)),$D339-$E339-SUM($AC209:AH209),$D339*$D232),0)) -> 0 | AJ209: =IF($D339=0,0,ROUND(IF($D339*$D232>$D339-($E339+SUM($AC209:AI209)),$D339-$E339-SUM($AC209:AI209),$D339*$D232),0)) -> 0 | AK209: =IF($D339=0,0,ROUND(IF($D339*$D232>$D339-($E339+SUM($AC209:AJ209)),$D339-$E339-SUM($AC209:AJ209),$D339*$D232),0)) -> 0 | AL209: =IF($D339=0,0,ROUND(IF($D339*$D232>$D339-($E339+SUM($AC209:AK209)),$D339-$E339-SUM($AC209:AK209),$D339*$D232),0)) -> 0 | ... AV209: =IF($D339=0,0,ROUND(IF($D339*$D232>$D339-($E339+SUM($AC209:AU209)),$D339-$E339-SUM($AC209:AU209),$D339*$D232),0)) -> 0
AB210: SIDF Charge | AC210: =IF($D343=0,0,ROUND(IF($D343*$D236>$D343-$E343,$D343-$E343,$D343*$D236),0)) -> 0 | AD210: =IF($D343=0,0,ROUND(IF($D343*$D236>$D343-($E343+AC210),$D343-$E343-AC210,$D343*$D236),0)) -> 0 | AE210: =IF($D343=0,0,ROUND(IF($D343*$D236>$D343-($E343+SUM($AC210:AD210)),$D343-$E343-SUM($AC210:AD210),$D343*$D236),0)) -> 0 | AF210: =IF($D343=0,0,ROUND(IF($D343*$D236>$D343-($E343+SUM($AC210:AE210)),$D343-$E343-SUM($AC210:AE210),$D343*$D236),0)) -> 0 | AG210: =IF($D343=0,0,ROUND(IF($D343*$D236>$D343-($E343+SUM($AC210:AF210)),$D343-$E343-SUM($AC210:AF210),$D343*$D236),0)) -> 0 | AH210: =IF($D343=0,0,ROUND(IF($D343*$D236>$D343-($E343+SUM($AC210:AG210)),$D343-$E343-SUM($AC210:AG210),$D343*$D236),0)) -> 0 | AI210: =IF($D343=0,0,ROUND(IF($D343*$D236>$D343-($E343+SUM($AC210:AH210)),$D343-$E343-SUM($AC210:AH210),$D343*$D236),0)) -> 0 | AJ210: =IF($D343=0,0,ROUND(IF($D343*$D236>$D343-($E343+SUM($AC210:AI210)),$D343-$E343-SUM($AC210:AI210),$D343*$D236),0)) -> 0 | AK210: =IF($D343=0,0,ROUND(IF($D343*$D236>$D343-($E343+SUM($AC210:AJ210)),$D343-$E343-SUM($AC210:AJ210),$D343*$D236),0)) -> 0 | AL210: =IF($D343=0,0,ROUND(IF($D343*$D236>$D343-($E343+SUM($AC210:AK210)),$D343-$E343-SUM($AC210:AK210),$D343*$D236),0)) -> 0 | ... AV210: =IF($D343=0,0,ROUND(IF($D343*$D236>$D343-($E343+SUM($AC210:AU210)),$D343-$E343-SUM($AC210:AU210),$D343*$D236),0)) -> 0
C211: Total (000's) | D211: =ROUND(SUM(D205:D209),1) -> 1905 | E211: =SUM(E205:E209) -> 1150 | F211: =SUM(F205:F209) -> 1288 | G211: =SUM(G205:G209) -> 1456 | H211: =SUM(H205:H209) -> 1655 | I211: =SUM(I205:I209) -> 1905 | J211: =SUM(J205:J209) -> 1905 | K211: =SUM(K205:K209) -> 1905 | L211: =SUM(L205:L209) -> 1905 | ... S211: =SUM(S205:S209) -> 1905 | AB211: Preop. Exp. | AC211: =IF($D344=0,0,ROUND(IF($D344*$D237>$D344-$E344,$D344-$E344,$D344*$D237),0)) -> 0 | AD211: =IF($D344=0,0,ROUND(IF($D344*$D237>$D344-($E344+AC211),$D344-$E344-AC211,$D344*$D237),0)) -> 0 | AE211: =IF($D344=0,0,ROUND(IF($D344*$D237>$D344-($E344+SUM($AC211:AD211)),$D344-$E344-SUM($AC211:AD211),$D344*$D237),0)) -> 0 | AF211: =IF($D344=0,0,ROUND(IF($D344*$D237>$D344-($E344+SUM($AC211:AE211)),$D344-$E344-SUM($AC211:AE211),$D344*$D237),0)) -> 0 | AG211: =IF($D344=0,0,ROUND(IF($D344*$D237>$D344-($E344+SUM($AC211:AF211)),$D344-$E344-SUM($AC211:AF211),$D344*$D237),0)) -> 0 | AH211: =IF($D344=0,0,ROUND(IF($D344*$D237>$D344-($E344+SUM($AC211:AG211)),$D344-$E344-SUM($AC211:AG211),$D344*$D237),0)) -> 0 | AI211: =IF($D344=0,0,ROUND(IF($D344*$D237>$D344-($E344+SUM($AC211:AH211)),$D344-$E344-SUM($AC211:AH211),$D344*$D237),0)) -> 0 | AJ211: =IF($D344=0,0,ROUND(IF($D344*$D237>$D344-($E344+SUM($AC211:AI211)),$D344-$E344-SUM($AC211:AI211),$D344*$D237),0)) -> 0 | AK211: =IF($D344=0,0,ROUND(IF($D344*$D237>$D344-($E344+SUM($AC211:AJ211)),$D344-$E344-SUM($AC211:AJ211),$D344*$D237),0)) -> 0 | AL211: =IF($D344=0,0,ROUND(IF($D344*$D237>$D344-($E344+SUM($AC211:AK211)),$D344-$E344-SUM($AC211:AK211),$D344*$D237),0)) -> 0 | ... AV211: =IF($D344=0,0,ROUND(IF($D344*$D237>$D344-($E344+SUM($AC211:AU211)),$D344-$E344-SUM($AC211:AU211),$D344*$D237),0)) -> 0
AB214: ='Financial Stat.'!B318&" Expenditure" -> 2025 Expenditure
AB215: Buildings | AD215: =F227*D227 -> 38.5 | AE215: =IF($AD215*2>$F227,IF($AD215*2-$F227<$AD215,$F227-$AD215*1,0),$AD215) -> 38.5 | AF215: =IF($AD215*3>$F227,IF($AD215*3-$F227<$AD215,$F227-$AD215*2,0),$AD215) -> 38.5 | AG215: =IF($AD215*4>$F227,IF($AD215*4-$F227<$AD215,$F227-$AD215*3,0),$AD215) -> 38.5 | AH215: =IF($AD215*5>$F227,IF($AD215*5-$F227<$AD215,$F227-$AD215*4,0),$AD215) -> 38.5 | AI215: =IF($AD215*6>$F227,IF($AD215*6-$F227<$AD215,$F227-$AD215*5,0),$AD215) -> 38.5 | AJ215: =IF($AD215*7>$F227,IF($AD215*7-$F227<$AD215,$F227-$AD215*6,0),$AD215) -> 38.5 | AK215: =IF($AD215*8>$F227,IF($AD215*8-$F227<$AD215,$F227-$AD215*7,0),$AD215) -> 38.5 | AL215: =IF($AD215*9>$F227,IF($AD215*9-$F227<$AD215,$F227-$AD215*8,0),$AD215) -> 38.5 | AM215: =IF($AD215*10>$F227,IF($AD215*10-$F227<$AD215,$F227-$AD215*9,0),$AD215) -> 38.5 | AN215: =IF($AD215*11>$F227,IF($AD215*11-$F227<$AD215,$F227-$AD215*10,0),$AD215) -> 38.5 | AO215: =IF($AD215*12>$F227,IF($AD215*12-$F227<$AD215,$F227-$AD215*11,0),$AD215) -> 38.5 | AP215: =IF($AD215*13>$F227,IF($AD215*13-$F227<$AD215,$F227-$AD215*12,0),$AD215) -> 38.5 | AQ215: =IF($AD215*14>$F227,IF($AD215*14-$F227<$AD215,$F227-$AD215*13,0),$AD215) -> 38.5 | AR215: =IF($AD215*15>$F227,IF($AD215*15-$F227<$AD215,$F227-$AD215*14,0),$AD215) -> 38.5 | AS215: =IF($AD215*16>$F227,IF($AD215*16-$F227<$AD215,$F227-$AD215*15,0),$AD215) -> 38.5 | AT215: =IF($AD215*17>$F227,IF($AD215*17-$F227<$AD215,$F227-$AD215*16,0),$AD215) -> 38.5 | AU215: =IF($AD215*18>$F227,IF($AD215*18-$F227<$AD215,$F227-$AD215*17,0),$AD215) -> 38.5 | AV215: =IF($AD215*19>$F227,IF($AD215*19-$F227<$AD215,$F227-$AD215*18,0),$AD215) -> 38.5
AB216: Machinery | AD216: =F228*D228 -> 567.65 | AE216: =IF($AD216*2>$F228,IF($AD216*2-$F228<$AD216,$F228-$AD216*1,0),$AD216) -> 567.65 | AF216: =IF($AD216*3>$F228,IF($AD216*3-$F228<$AD216,$F228-$AD216*2,0),$AD216) -> 567.65 | AG216: =IF($AD216*4>$F228,IF($AD216*4-$F228<$AD216,$F228-$AD216*3,0),$AD216) -> 567.65 | AH216: =IF($AD216*5>$F228,IF($AD216*5-$F228<$AD216,$F228-$AD216*4,0),$AD216) -> 567.65 | AI216: =IF($AD216*6>$F228,IF($AD216*6-$F228<$AD216,$F228-$AD216*5,0),$AD216) -> 567.65 | AJ216: =IF($AD216*7>$F228,IF($AD216*7-$F228<$AD216,$F228-$AD216*6,0),$AD216) -> 567.65 | AK216: =IF($AD216*8>$F228,IF($AD216*8-$F228<$AD216,$F228-$AD216*7,0),$AD216) -> 567.65 | AL216: =IF($AD216*9>$F228,IF($AD216*9-$F228<$AD216,$F228-$AD216*8,0),$AD216) -> 567.65 | AM216: =IF($AD216*10>$F228,IF($AD216*10-$F228<$AD216,$F228-$AD216*9,0),$AD216) -> 567.65 | AN216: =IF($AD216*11>$F228,IF($AD216*11-$F228<$AD216,$F228-$AD216*10,0),$AD216) -> 567.65 | AO216: =IF($AD216*12>$F228,IF($AD216*12-$F228<$AD216,$F228-$AD216*11,0),$AD216) -> 567.65 | AP216: =IF($AD216*13>$F228,IF($AD216*13-$F228<$AD216,$F228-$AD216*12,0),$AD216) -> 567.65 | AQ216: =IF($AD216*14>$F228,IF($AD216*14-$F228<$AD216,$F228-$AD216*13,0),$AD216) -> 567.65 | AR216: =IF($AD216*15>$F228,IF($AD216*15-$F228<$AD216,$F228-$AD216*14,0),$AD216) -> 567.65 | AS216: =IF($AD216*16>$F228,IF($AD216*16-$F228<$AD216,$F228-$AD216*15,0),$AD216) -> 567.65 | AT216: =IF($AD216*17>$F228,IF($AD216*17-$F228<$AD216,$F228-$AD216*16,0),$AD216) -> 567.65 | AU216: =IF($AD216*18>$F228,IF($AD216*18-$F228<$AD216,$F228-$AD216*17,0),$AD216) -> 567.65 | AV216: =IF($AD216*19>$F228,IF($AD216*19-$F228<$AD216,$F228-$AD216*18,0),$AD216) -> 567.65
AB217: Furniture | AD217: =F229*D229 -> 0 | AE217: =IF($AD217*2>$F229,IF($AD217*2-$F229<$AD217,$F229-$AD217*1,0),$AD217) -> 0 | AF217: =IF($AD217*3>$F229,IF($AD217*3-$F229<$AD217,$F229-$AD217*2,0),$AD217) -> 0 | AG217: =IF($AD217*4>$F229,IF($AD217*4-$F229<$AD217,$F229-$AD217*3,0),$AD217) -> 0 | AH217: =IF($AD217*5>$F229,IF($AD217*5-$F229<$AD217,$F229-$AD217*4,0),$AD217) -> 0 | AI217: =IF($AD217*6>$F229,IF($AD217*6-$F229<$AD217,$F229-$AD217*5,0),$AD217) -> 0 | AJ217: =IF($AD217*7>$F229,IF($AD217*7-$F229<$AD217,$F229-$AD217*6,0),$AD217) -> 0 | AK217: =IF($AD217*8>$F229,IF($AD217*8-$F229<$AD217,$F229-$AD217*7,0),$AD217) -> 0 | AL217: =IF($AD217*9>$F229,IF($AD217*9-$F229<$AD217,$F229-$AD217*8,0),$AD217) -> 0 | AM217: =IF($AD217*10>$F229,IF($AD217*10-$F229<$AD217,$F229-$AD217*9,0),$AD217) -> 0 | AN217: =IF($AD217*11>$F229,IF($AD217*11-$F229<$AD217,$F229-$AD217*10,0),$AD217) -> 0 | AO217: =IF($AD217*12>$F229,IF($AD217*12-$F229<$AD217,$F229-$AD217*11,0),$AD217) -> 0 | AP217: =IF($AD217*13>$F229,IF($AD217*13-$F229<$AD217,$F229-$AD217*12,0),$AD217) -> 0 | AQ217: =IF($AD217*14>$F229,IF($AD217*14-$F229<$AD217,$F229-$AD217*13,0),$AD217) -> 0 | AR217: =IF($AD217*15>$F229,IF($AD217*15-$F229<$AD217,$F229-$AD217*14,0),$AD217) -> 0 | AS217: =IF($AD217*16>$F229,IF($AD217*16-$F229<$AD217,$F229-$AD217*15,0),$AD217) -> 0 | AT217: =IF($AD217*17>$F229,IF($AD217*17-$F229<$AD217,$F229-$AD217*16,0),$AD217) -> 0 | AU217: =IF($AD217*18>$F229,IF($AD217*18-$F229<$AD217,$F229-$AD217*17,0),$AD217) -> 0 | AV217: =IF($AD217*19>$F229,IF($AD217*19-$F229<$AD217,$F229-$AD217*18,0),$AD217) -> 0
A218: 6. | C218: Capital Expenditure, Depreciation, Amortization and Maintenance Assumptions: | O218: Attachment C- 6 | AB218: Vehicles | AD218: =F230*D230 -> 71.8 | AE218: =IF($AD218*2>$F230,IF($AD218*2-$F230<$AD218,$F230-$AD218*1,0),$AD218) -> 71.8 | AF218: =IF($AD218*3>$F230,IF($AD218*3-$F230<$AD218,$F230-$AD218*2,0),$AD218) -> 71.8 | AG218: =IF($AD218*4>$F230,IF($AD218*4-$F230<$AD218,$F230-$AD218*3,0),$AD218) -> 71.8 | AH218: =IF($AD218*5>$F230,IF($AD218*5-$F230<$AD218,$F230-$AD218*4,0),$AD218) -> 71.8 | AI218: =IF($AD218*6>$F230,IF($AD218*6-$F230<$AD218,$F230-$AD218*5,0),$AD218) -> 0 | AJ218: =IF($AD218*7>$F230,IF($AD218*7-$F230<$AD218,$F230-$AD218*6,0),$AD218) -> 0 | AK218: =IF($AD218*8>$F230,IF($AD218*8-$F230<$AD218,$F230-$AD218*7,0),$AD218) -> 0 | AL218: =IF($AD218*9>$F230,IF($AD218*9-$F230<$AD218,$F230-$AD218*8,0),$AD218) -> 0 | AM218: =IF($AD218*10>$F230,IF($AD218*10-$F230<$AD218,$F230-$AD218*9,0),$AD218) -> 0 | AN218: =IF($AD218*11>$F230,IF($AD218*11-$F230<$AD218,$F230-$AD218*10,0),$AD218) -> 0 | AO218: =IF($AD218*12>$F230,IF($AD218*12-$F230<$AD218,$F230-$AD218*11,0),$AD218) -> 0 | AP218: =IF($AD218*13>$F230,IF($AD218*13-$F230<$AD218,$F230-$AD218*12,0),$AD218) -> 0 | AQ218: =IF($AD218*14>$F230,IF($AD218*14-$F230<$AD218,$F230-$AD218*13,0),$AD218) -> 0 | AR218: =IF($AD218*15>$F230,IF($AD218*15-$F230<$AD218,$F230-$AD218*14,0),$AD218) -> 0 | AS218: =IF($AD218*16>$F230,IF($AD218*16-$F230<$AD218,$F230-$AD218*15,0),$AD218) -> 0 | AT218: =IF($AD218*17>$F230,IF($AD218*17-$F230<$AD218,$F230-$AD218*16,0),$AD218) -> 0 | AU218: =IF($AD218*18>$F230,IF($AD218*18-$F230<$AD218,$F230-$AD218*17,0),$AD218) -> 0 | AV218: =IF($AD218*19>$F230,IF($AD218*19-$F230<$AD218,$F230-$AD218*18,0),$AD218) -> 0
C219: The following table sets out the Capital Expenditures plus the depreciation, amortization and maintenance rates used for the entire forecast. | AB219: Loss Prevention | AD219: =F231*D231 -> 22.9 | AE219: =IF($AD219*2>$F231,IF($AD219*2-$F231<$AD219,$F231-$AD219*1,0),$AD219) -> 22.9 | AF219: =IF($AD219*3>$F231,IF($AD219*3-$F231<$AD219,$F231-$AD219*2,0),$AD219) -> 22.9 | AG219: =IF($AD219*4>$F231,IF($AD219*4-$F231<$AD219,$F231-$AD219*3,0),$AD219) -> 22.9 | AH219: =IF($AD219*5>$F231,IF($AD219*5-$F231<$AD219,$F231-$AD219*4,0),$AD219) -> 22.9 | AI219: =IF($AD219*6>$F231,IF($AD219*6-$F231<$AD219,$F231-$AD219*5,0),$AD219) -> 22.9 | AJ219: =IF($AD219*7>$F231,IF($AD219*7-$F231<$AD219,$F231-$AD219*6,0),$AD219) -> 22.9 | AK219: =IF($AD219*8>$F231,IF($AD219*8-$F231<$AD219,$F231-$AD219*7,0),$AD219) -> 22.9 | AL219: =IF($AD219*9>$F231,IF($AD219*9-$F231<$AD219,$F231-$AD219*8,0),$AD219) -> 22.9 | AM219: =IF($AD219*10>$F231,IF($AD219*10-$F231<$AD219,$F231-$AD219*9,0),$AD219) -> 22.9 | AN219: =IF($AD219*11>$F231,IF($AD219*11-$F231<$AD219,$F231-$AD219*10,0),$AD219) -> 22.9 | AO219: =IF($AD219*12>$F231,IF($AD219*12-$F231<$AD219,$F231-$AD219*11,0),$AD219) -> 22.9 | AP219: =IF($AD219*13>$F231,IF($AD219*13-$F231<$AD219,$F231-$AD219*12,0),$AD219) -> 22.9 | AQ219: =IF($AD219*14>$F231,IF($AD219*14-$F231<$AD219,$F231-$AD219*13,0),$AD219) -> 22.9 | AR219: =IF($AD219*15>$F231,IF($AD219*15-$F231<$AD219,$F231-$AD219*14,0),$AD219) -> 22.9 | AS219: =IF($AD219*16>$F231,IF($AD219*16-$F231<$AD219,$F231-$AD219*15,0),$AD219) -> 22.9 | AT219: =IF($AD219*17>$F231,IF($AD219*17-$F231<$AD219,$F231-$AD219*16,0),$AD219) -> 22.9 | AU219: =IF($AD219*18>$F231,IF($AD219*18-$F231<$AD219,$F231-$AD219*17,0),$AD219) -> 22.9 | AV219: =IF($AD219*19>$F231,IF($AD219*19-$F231<$AD219,$F231-$AD219*18,0),$AD219) -> 22.9
AB220: Other | AD220: =F232*D232 -> 0 | AE220: =IF($AD220*2>$F232,IF($AD220*2-$F232<$AD220,$F232-$AD220*1,0),$AD220) -> 0 | AF220: =IF($AD220*3>$F232,IF($AD220*3-$F232<$AD220,$F232-$AD220*2,0),$AD220) -> 0 | AG220: =IF($AD220*4>$F232,IF($AD220*4-$F232<$AD220,$F232-$AD220*3,0),$AD220) -> 0 | AH220: =IF($AD220*5>$F232,IF($AD220*5-$F232<$AD220,$F232-$AD220*4,0),$AD220) -> 0 | AI220: =IF($AD220*6>$F232,IF($AD220*6-$F232<$AD220,$F232-$AD220*5,0),$AD220) -> 0 | AJ220: =IF($AD220*7>$F232,IF($AD220*7-$F232<$AD220,$F232-$AD220*6,0),$AD220) -> 0 | AK220: =IF($AD220*8>$F232,IF($AD220*8-$F232<$AD220,$F232-$AD220*7,0),$AD220) -> 0 | AL220: =IF($AD220*9>$F232,IF($AD220*9-$F232<$AD220,$F232-$AD220*8,0),$AD220) -> 0 | AM220: =IF($AD220*10>$F232,IF($AD220*10-$F232<$AD220,$F232-$AD220*9,0),$AD220) -> 0 | AN220: =IF($AD220*11>$F232,IF($AD220*11-$F232<$AD220,$F232-$AD220*10,0),$AD220) -> 0 | AO220: =IF($AD220*12>$F232,IF($AD220*12-$F232<$AD220,$F232-$AD220*11,0),$AD220) -> 0 | AP220: =IF($AD220*13>$F232,IF($AD220*13-$F232<$AD220,$F232-$AD220*12,0),$AD220) -> 0 | AQ220: =IF($AD220*14>$F232,IF($AD220*14-$F232<$AD220,$F232-$AD220*13,0),$AD220) -> 0 | AR220: =IF($AD220*15>$F232,IF($AD220*15-$F232<$AD220,$F232-$AD220*14,0),$AD220) -> 0 | AS220: =IF($AD220*16>$F232,IF($AD220*16-$F232<$AD220,$F232-$AD220*15,0),$AD220) -> 0 | AT220: =IF($AD220*17>$F232,IF($AD220*17-$F232<$AD220,$F232-$AD220*16,0),$AD220) -> 0 | AU220: =IF($AD220*18>$F232,IF($AD220*18-$F232<$AD220,$F232-$AD220*17,0),$AD220) -> 0 | AV220: =IF($AD220*19>$F232,IF($AD220*19-$F232<$AD220,$F232-$AD220*18,0),$AD220) -> 0
AB221: Contingencies | AD221: =F233*D233 -> 0 | AE221: =IF($AD221*2>$F233,IF($AD221*2-$F233<$AD221,$F233-$AD221*1,0),$AD221) -> 0 | AF221: =IF($AD221*3>$F233,IF($AD221*3-$F233<$AD221,$F233-$AD221*2,0),$AD221) -> 0 | AG221: =IF($AD221*4>$F233,IF($AD221*4-$F233<$AD221,$F233-$AD221*3,0),$AD221) -> 0 | AH221: =IF($AD221*5>$F233,IF($AD221*5-$F233<$AD221,$F233-$AD221*4,0),$AD221) -> 0 | AI221: =IF($AD221*6>$F233,IF($AD221*6-$F233<$AD221,$F233-$AD221*5,0),$AD221) -> 0 | AJ221: =IF($AD221*7>$F233,IF($AD221*7-$F233<$AD221,$F233-$AD221*6,0),$AD221) -> 0 | AK221: =IF($AD221*8>$F233,IF($AD221*8-$F233<$AD221,$F233-$AD221*7,0),$AD221) -> 0 | AL221: =IF($AD221*9>$F233,IF($AD221*9-$F233<$AD221,$F233-$AD221*8,0),$AD221) -> 0 | AM221: =IF($AD221*10>$F233,IF($AD221*10-$F233<$AD221,$F233-$AD221*9,0),$AD221) -> 0 | AN221: =IF($AD221*11>$F233,IF($AD221*11-$F233<$AD221,$F233-$AD221*10,0),$AD221) -> 0 | AO221: =IF($AD221*12>$F233,IF($AD221*12-$F233<$AD221,$F233-$AD221*11,0),$AD221) -> 0 | AP221: =IF($AD221*13>$F233,IF($AD221*13-$F233<$AD221,$F233-$AD221*12,0),$AD221) -> 0 | AQ221: =IF($AD221*14>$F233,IF($AD221*14-$F233<$AD221,$F233-$AD221*13,0),$AD221) -> 0 | AR221: =IF($AD221*15>$F233,IF($AD221*15-$F233<$AD221,$F233-$AD221*14,0),$AD221) -> 0 | AS221: =IF($AD221*16>$F233,IF($AD221*16-$F233<$AD221,$F233-$AD221*15,0),$AD221) -> 0 | AT221: =IF($AD221*17>$F233,IF($AD221*17-$F233<$AD221,$F233-$AD221*16,0),$AD221) -> 0 | AU221: =IF($AD221*18>$F233,IF($AD221*18-$F233<$AD221,$F233-$AD221*17,0),$AD221) -> 0 | AV221: =IF($AD221*19>$F233,IF($AD221*19-$F233<$AD221,$F233-$AD221*18,0),$AD221) -> 0
AB222: SIDF Evaluation charge | AD222: =F236*D236 -> 300 | AE222: =IF($AD222*2>$F236,IF($AD222*2-$F236<$AD222,$F236-$AD222*1,0),$AD222) -> 0 | AF222: =IF($AD222*3>$F236,IF($AD222*3-$F236<$AD222,$F236-$AD222*2,0),$AD222) -> 0 | AG222: =IF($AD222*4>$F236,IF($AD222*4-$F236<$AD222,$F236-$AD222*3,0),$AD222) -> 0 | AH222: =IF($AD222*5>$F236,IF($AD222*5-$F236<$AD222,$F236-$AD222*4,0),$AD222) -> 0 | AI222: =IF($AD222*6>$F236,IF($AD222*6-$F236<$AD222,$F236-$AD222*5,0),$AD222) -> 0 | AJ222: =IF($AD222*7>$F236,IF($AD222*7-$F236<$AD222,$F236-$AD222*6,0),$AD222) -> 0 | AK222: =IF($AD222*8>$F236,IF($AD222*8-$F236<$AD222,$F236-$AD222*7,0),$AD222) -> 0 | AL222: =IF($AD222*9>$F236,IF($AD222*9-$F236<$AD222,$F236-$AD222*8,0),$AD222) -> 0 | AM222: =IF($AD222*10>$F236,IF($AD222*10-$F236<$AD222,$F236-$AD222*9,0),$AD222) -> 0 | AN222: =IF($AD222*11>$F236,IF($AD222*11-$F236<$AD222,$F236-$AD222*10,0),$AD222) -> 0 | AO222: =IF($AD222*12>$F236,IF($AD222*12-$F236<$AD222,$F236-$AD222*11,0),$AD222) -> 0 | AP222: =IF($AD222*13>$F236,IF($AD222*13-$F236<$AD222,$F236-$AD222*12,0),$AD222) -> 0 | AQ222: =IF($AD222*14>$F236,IF($AD222*14-$F236<$AD222,$F236-$AD222*13,0),$AD222) -> 0 | AR222: =IF($AD222*15>$F236,IF($AD222*15-$F236<$AD222,$F236-$AD222*14,0),$AD222) -> 0 | AS222: =IF($AD222*16>$F236,IF($AD222*16-$F236<$AD222,$F236-$AD222*15,0),$AD222) -> 0 | AT222: =IF($AD222*17>$F236,IF($AD222*17-$F236<$AD222,$F236-$AD222*16,0),$AD222) -> 0 | AU222: =IF($AD222*18>$F236,IF($AD222*18-$F236<$AD222,$F236-$AD222*17,0),$AD222) -> 0 | AV222: =IF($AD222*19>$F236,IF($AD222*19-$F236<$AD222,$F236-$AD222*18,0),$AD222) -> 0
...

Sheet Financial Stat.
K1: Income Statement | P1: Attachment B-1
R4: (SR in 000s)
C5: HISTORICAL | G5: PROJECTIONS
B6: =IF(H_1=0," ",H_1) | C6: =IF(H_2=0," ",H_2) | D6: =IF(H_3=0," ",H_3) | E6: =IF(H_4=0," ",H_4) | F6: =IF(H_5=0," ",H_5) | G6: =B318 -> 2025 | H6: =C318 -> 2026 | I6: =D318 -> 2027 | J6: =E318 -> 2028 | K6: =F318 -> 2029 | L6: =G318 -> 2030 | M6: =H318 -> 2031 | N6: =I318 -> 2032 | ... V6: =Q318 -> 2040
A8: Sales | G8: 19700 | H8: =Assumptions!D86 -> 18219 | I8: =Assumptions!E86 -> 20364 | J8: =Assumptions!F86 -> 22910 | K8: =Assumptions!G86 -> 25912 | L8: =Assumptions!H86 -> 29721 | M8: =Assumptions!I86 -> 29721 | N8: =Assumptions!J86 -> 29721 | O8: =Assumptions!K86 -> 29721 | ... V8: =Assumptions!R86 -> 29721
A10: Cost of Goods Sold:
A11: Raw Materials | G11: 8136 | H11: =Assumptions!D129 -> 9476 | I11: =Assumptions!E129 -> 10626 | J11: =Assumptions!F129 -> 12042 | K11: =Assumptions!G129 -> 13715 | L11: =Assumptions!H129 -> 15821 | M11: =Assumptions!I129 -> 15821 | N11: =Assumptions!J129 -> 15821 | O11: =Assumptions!K129 -> 15821 | ... V11: =Assumptions!R129 -> 15821
A12: Labour | G12: 2233 | H12: =Assumptions!F189 -> 2233 | I12: =Assumptions!G189 -> 2233 | J12: =Assumptions!H189 -> 2233 | K12: =Assumptions!I189 -> 2233 | L12: =Assumptions!J189 -> 2233 | M12: =Assumptions!K189 -> 2233 | N12: =Assumptions!L189 -> 2233 | O12: =Assumptions!M189 -> 2233 | ... V12: =Assumptions!T189 -> 2233
A13: Utilities | G13: 990 | H13: =ROUND(Assumptions!E211,0) -> 1150 | I13: =ROUND(Assumptions!F211,0) -> 1288 | J13: =ROUND(Assumptions!G211,0) -> 1456 | K13: =ROUND(Assumptions!H211,0) -> 1655 | L13: =ROUND(Assumptions!I211,0) -> 1905 | M13: =ROUND(Assumptions!J211,0) -> 1905 | N13: =ROUND(Assumptions!K211,0) -> 1905 | O13: =ROUND(Assumptions!L211,0) -> 1905 | ... V13: =ROUND(Assumptions!S211,0) -> 1905
A14: Maintenance | G14: =Assumptions!G341 -> 0 | H14: =ROUND(Assumptions!E227*G60+Assumptions!E228*G61+Assumptions!E229*G62+Assumptions!E230*G63+Assumptions!E231*G64+Assumptions!E232*G65+Assumptions!E233*G66,0) -> 610 | I14: =ROUND(Assumptions!E227*H60+Assumptions!E228*H61+Assumptions!E229*H62+Assumptions!E230*H63+Assumptions!E231*H64+Assumptions!E232*H65+Assumptions!E233*H66,0) -> 610 | J14: =ROUND(Assumptions!E227*I60+Assumptions!E228*I61+Assumptions!E229*I62+Assumptions!E230*I63+Assumptions!E231*I64+Assumptions!E232*I65+Assumptions!E233*I66,0) -> 610 | K14: =ROUND(Assumptions!E227*J60+Assumptions!E228*J61+Assumptions!E229*J62+Assumptions!E230*J63+Assumptions!E231*J64+Assumptions!E232*J65+Assumptions!E233*J66,0) -> 610 | L14: =ROUND(Assumptions!E227*K60+Assumptions!E228*K61+Assumptions!E229*K62+Assumptions!E230*K63+Assumptions!E231*K64+Assumptions!E232*K65+Assumptions!E233*K66,0) -> 610 | M14: =ROUND(Assumptions!E227*L60+Assumptions!E228*L61+Assumptions!E229*L62+Assumptions!E230*L63+Assumptions!E231*L64+Assumptions!E232*L65+Assumptions!E233*L66,0) -> 610 | N14: =ROUND(Assumptions!E227*M60+Assumptions!E228*M61+Assumptions!E229*M62+Assumptions!E230*M63+Assumptions!E231*M64+Assumptions!E232*M65+Assumptions!E233*M66,0) -> 610 | O14: =ROUND(Assumptions!E227*N60+Assumptions!E228*N61+Assumptions!E229*N62+Assumptions!E230*N63+Assumptions!E231*N64+Assumptions!E232*N65+Assumptions!E233*N66,0) -> 610 | P14: =ROUND(Assumptions!E227*O60+Assumptions!E228*O61+Assumptions!E229*O62+Assumptions!E230*O63+Assumptions!E231*O64+Assumptions!E232*O65+Assumptions!E233*O66,0) -> 610 | Q14: =ROUND(Assumptions!E227*P60+Assumptions!E228*P61+Assumptions!E229*P62+Assumptions!E230*P63+Assumptions!E231*P64+Assumptions!E232*P65+Assumptions!E233*P66,0) -> 610 | R14: =ROUND(Assumptions!E227*Q60+Assumptions!E228*Q61+Assumptions!E229*Q62+Assumptions!E230*Q63+Assumptions!E231*Q64+Assumptions!E232*Q65+Assumptions!E233*Q66,0) -> 610 | S14: =ROUND(Assumptions!E227*R60+Assumptions!E228*R61+Assumptions!E229*R62+Assumptions!E230*R63+Assumptions!E231*R64+Assumptions!E232*R65+Assumptions!E233*R66,0) -> 610 | T14: =ROUND(Assumptions!E227*S60+Assumptions!E228*S61+Assumptions!E229*S62+Assumptions!E230*S63+Assumptions!E231*S64+Assumptions!E232*S65+Assumptions!E233*S66,0) -> 610 | U14: =ROUND(Assumptions!E227*T60+Assumptions!E228*T61+Assumptions!E229*T62+Assumptions!E230*T63+Assumptions!E231*T64+Assumptions!E232*T65+Assumptions!E233*T66,0) -> 610 | V14: =ROUND(Assumptions!E227*U60+Assumptions!E228*U61+Assumptions!E229*U62+Assumptions!E230*U63+Assumptions!E231*U64+Assumptions!E232*U65+Assumptions!E233*U66,0) -> 610
A15: Depreciation | G15: =Assumptions!F252 -> 0 | H15: =Assumptions!G252 -> 702 | I15: =Assumptions!H252 -> 702 | J15: =Assumptions!I252 -> 702 | K15: =Assumptions!J252 -> 702 | L15: =Assumptions!K252 -> 702 | M15: =Assumptions!L252 -> 630 | N15: =Assumptions!M252 -> 630 | ... V15: =Assumptions!U252 -> 630
A16: Amortization | G16: =610+702 -> 1312 | H16: =Assumptions!G255 -> 399 | I16: =Assumptions!H255 -> 0 | J16: =Assumptions!I255 -> 0 | K16: =Assumptions!J255 -> 0 | L16: =Assumptions!K255 -> 0 | M16: =Assumptions!L255 -> 0 | N16: =Assumptions!M255 -> 0 | O16: =Assumptions!N255 -> 0 | ... V16: =Assumptions!U255 -> 0
A17: other
A18: Other | B18: 0 | C18: 0 | D18: 0 | E18: 0 | F18: 0 | G18: 0 | H18: 0 | I18: 0 | J18: 0 | K18: 0 | L18: 0 | M18: 0 | N18: 0 | O18: 0 | P18: 0 | Q18: 0 | R18: 0 | S18: 0 | T18: 0 | U18: 0 | V18: 0
A20: Total of CGS | B20: =ROUND(SUM(B10:B18),0) -> 0 | C20: =ROUND(SUM(C10:C18),0) -> 0 | D20: =ROUND(SUM(D10:D18),0) -> 0 | E20: =ROUND(SUM(E10:E18),0) -> 0 | F20: =ROUND(SUM(F10:F18),0) -> 0 | G20: =ROUND(SUM(G10:G18),0) -> 12671 | H20: =ROUND(SUM(H10:H18),0) -> 14570 | I20: =ROUND(SUM(I10:I18),0) -> 15459 | ... V20: =ROUND(SUM(V10:V18),0) -> 21199
A22: Gross Margin | B22: =B8-B20 -> 0 | C22: =C8-C20 -> 0 | D22: =D8-D20 -> 0 | E22: =E8-E20 -> 0 | F22: =F8-F20 -> 0 | G22: =G8-G20 -> 7029 | H22: =H8-H20 -> 3649 | I22: =I8-I20 -> 4905 | ... V22: =V8-V20 -> 8522
A24: Indirect Costs:
A25: Sales, Gen. & Admin. | G25: =H25 -> 1912.995 | H25: =IF(H8*Assumptions!E268<Assumptions!E267,Assumptions!E267,H8*Assumptions!E268) -> 1912.995 | I25: =IF(I8*Assumptions!F268<Assumptions!F267,Assumptions!F267,I8*Assumptions!F268) -> 2443.68 | J25: =IF(J8*Assumptions!G268<Assumptions!G267,Assumptions!G267,J8*Assumptions!G268) -> 2978.3 | K25: =IF(K8*Assumptions!H268<Assumptions!H267,Assumptions!H267,K8*Assumptions!H268) -> 3627.68 | L25: =IF(L8*Assumptions!I268<Assumptions!I267,Assumptions!I267,L8*Assumptions!I268) -> 4160.94 | M25: =IF(M8*Assumptions!I268<Assumptions!I267,Assumptions!I267,M8*Assumptions!I268) -> 4160.94 | N25: =IF(N8*Assumptions!I268<Assumptions!I267,Assumptions!I267,N8*Assumptions!I268) -> 4160.94 | O25: =IF(O8*Assumptions!I268<Assumptions!I267,Assumptions!I267,O8*Assumptions!I268) -> 4160.94 | P25: =IF(P8*Assumptions!I268<Assumptions!I267,Assumptions!I267,P8*Assumptions!I268) -> 4160.94 | Q25: =IF(Q8*Assumptions!I268<Assumptions!I267,Assumptions!I267,Q8*Assumptions!I268) -> 4160.94 | R25: =IF(R8*Assumptions!N268<Assumptions!N267,Assumptions!N267,R8*Assumptions!N268) -> 4160.94 | S25: =IF(S8*Assumptions!N268<Assumptions!N267,Assumptions!N267,S8*Assumptions!N268) -> 4160.94 | T25: =IF(T8*Assumptions!N268<Assumptions!N267,Assumptions!N267,T8*Assumptions!N268) -> 4160.94 | U25: =IF(U8*Assumptions!N268<Assumptions!N267,Assumptions!N267,U8*Assumptions!N268) -> 4160.94 | V25: =IF(V8*Assumptions!N268<Assumptions!N267,Assumptions!N267,V8*Assumptions!N268) -> 4160.94
A26: Salaries | G26: =F26 -> 0 | H26: =Assumptions!F162 -> 0 | I26: =Assumptions!G162 -> 0 | J26: =Assumptions!H162 -> 0 | K26: =Assumptions!I162 -> 0 | L26: =Assumptions!J162 -> 0 | M26: =Assumptions!K162 -> 0 | N26: =Assumptions!L162 -> 0 | O26: =Assumptions!M162 -> 0 | ... V26: =Assumptions!T162 -> 0
A27: Finance Charges | G27: =ROUND(Assumptions!E280*(F91+G135/2-G151/2)+Assumptions!E281*(F103+F94/2+G132/2)+Assumptions!E282*(F104+G133/2-G149/2)+IF(G93+G102+G147=0,0,Assumptions!F279),0) -> 0 | H27: =ROUND(Assumptions!E280*(G91+H135/2-H151/2)+Assumptions!E281*(G103+G94/2+H132/2)+Assumptions!E282*(G104+H133/2-H149/2)+IF(H93+H102+H147=0,0,Assumptions!G279),0) -> 83 | I27: =ROUND(Assumptions!E280*(H91+I135/2-I151/2)+Assumptions!E281*(H103+H94/2+I132/2)+Assumptions!E282*(H104+I133/2-I149/2)+IF(I93+I102+I147=0,0,Assumptions!H279),0) -> 83 | J27: =ROUND(Assumptions!E280*(I91+J135/2-J151/2)+Assumptions!E281*(I103+I94/2+J132/2)+Assumptions!E282*(I104+J133/2-J149/2)+IF(J93+J102+J147=0,0,Assumptions!H279),0) -> 83 | K27: =ROUND(Assumptions!E280*(J91+K135/2-K151/2)+Assumptions!E281*(J103+J94/2+K132/2)+Assumptions!E282*(J104+K133/2-K149/2)+IF(K93+K102+K147=0,0,Assumptions!H279),0) -> 83 | L27: =ROUND(Assumptions!E280*(K91+L135/2-L151/2)+Assumptions!E281*(K103+K94/2+L132/2)+Assumptions!E282*(K104+L133/2-L149/2)+IF(L93+L102+L147=0,0,Assumptions!H279),0) -> 83 | M27: =ROUND(Assumptions!E280*(L91+M135/2-M151/2)+Assumptions!E281*(L103+L94/2+M132/2)+Assumptions!E282*(L104+M133/2-M149/2)+IF(M93+M102+M147=0,0,Assumptions!H279),0) -> 83 | N27: =ROUND(Assumptions!E280*(M91+N135/2-N151/2)+Assumptions!E281*(M103+M94/2+N132/2)+Assumptions!E282*(M104+N133/2-N149/2)+IF(N93+N102+N147=0,0,Assumptions!H279),0) -> 83 | O27: =ROUND(Assumptions!E280*(N91+O135/2-O151/2)+Assumptions!E281*(N103+N94/2+O132/2)+Assumptions!E282*(N104+O133/2-O149/2)+IF(O93+O102+O147=0,0,Assumptions!H279),0) -> 0 | P27: =ROUND(Assumptions!E280*(O91+P135/2-P151/2)+Assumptions!E281*(O103+O94/2+P132/2)+Assumptions!E282*(O104+P133/2-P149/2)+IF(P93+P102+P147=0,0,Assumptions!H279),0) -> 0 | Q27: =ROUND(Assumptions!E280*(P91+Q135/2-Q151/2)+Assumptions!E281*(P103+P94/2+Q132/2)+Assumptions!E282*(P104+Q133/2-Q149/2)+IF(Q93+Q102+Q147=0,0,Assumptions!H279),0) -> 0 | R27: =ROUND(Assumptions!E280*(Q91+R135/2-R151/2)+Assumptions!E281*(Q103+Q94/2+R132/2)+Assumptions!E282*(Q104+R133/2-R149/2)+IF(R93+R102+R147=0,0,Assumptions!H279),0) -> 0 | S27: =ROUND(Assumptions!E280*(R91+S135/2-S151/2)+Assumptions!E281*(R103+R94/2+S132/2)+Assumptions!E282*(R104+S133/2-S149/2)+IF(S93+S102+S147=0,0,Assumptions!H279),0) -> 0 | T27: =ROUND(Assumptions!E280*(S91+T135/2-T151/2)+Assumptions!E281*(S103+S94/2+T132/2)+Assumptions!E282*(S104+T133/2-T149/2)+IF(T93+T102+T147=0,0,Assumptions!H279),0) -> 0 | U27: =ROUND(Assumptions!E280*(T91+U135/2-U151/2)+Assumptions!E281*(T103+T94/2+U132/2)+Assumptions!E282*(T104+U133/2-U149/2)+IF(U93+U102+U147=0,0,Assumptions!H279),0) -> 0 | V27: =ROUND(Assumptions!E280*(U91+V135/2-V151/2)+Assumptions!E281*(U103+U94/2+V132/2)+Assumptions!E282*(U104+V133/2-V149/2)+IF(V93+V102+V147=0,0,Assumptions!H279),0) -> 0
A28: Other Exp. (Income)
A29: Other Exp. (Income) | B29: 0 | C29: 0 | D29: 0 | E29: 0 | F29: 0 | G29: 0 | H29: 0 | I29: 0 | J29: 0 | K29: 0 | L29: 0 | M29: 0 | N29: 0 | O29: 0 | P29: 0 | Q29: 0 | R29: 0 | S29: 0 | T29: 0 | U29: 0 | V29: 0
A31: Total Indirect Cost | B31: =ROUND(SUM(B25:B29),0) -> 0 | C31: =ROUND(SUM(C25:C29),0) -> 0 | D31: =ROUND(SUM(D25:D29),0) -> 0 | E31: =ROUND(SUM(E25:E29),0) -> 0 | F31: =ROUND(SUM(F25:F29),0) -> 0 | G31: =ROUND(SUM(G25:G29),0) -> 1913 | H31: =ROUND(SUM(H25:H29),0) -> 1996 | I31: =ROUND(SUM(I25:I29),0) -> 2527 | ... V31: =ROUND(SUM(V25:V29),0) -> 4161
A33: Profit Before Zakat | B33: =B22-B31 -> 0 | C33: =C22-C31 -> 0 | D33: =D22-D31 -> 0 | E33: =E22-E31 -> 0 | F33: =F22-F31 -> 0 | G33: =G22-G31 -> 5116 | H33: =H22-H31 -> 1653 | I33: =I22-I31 -> 2378 | ... V33: =V22-V31 -> 4361
A34: Zakat | G34: =ROUND(IF(G33>0,0.025*G33,0),0) -> 128 | H34: =ROUND(IF(H33>0,0.025*H33,0),0) -> 41 | I34: =ROUND(IF(I33>0,0.025*I33,0),0) -> 59 | J34: =ROUND(IF(J33>0,0.025*J33,0),0) -> 70 | K34: =ROUND(IF(K33>0,0.025*K33,0),0) -> 82 | L34: =ROUND(IF(L33>0,0.025*L33,0),0) -> 105 | M34: =ROUND(IF(M33>0,0.025*M33,0),0) -> 107 | N34: =ROUND(IF(N33>0,0.025*N33,0),0) -> 107 | ... V34: =ROUND(IF(V33>0,0.025*V33,0),0) -> 109
A36: Profit After Zakat | B36: =B33-B34 -> 0 | C36: =C33-C34 -> 0 | D36: =D33-D34 -> 0 | E36: =E33-E34 -> 0 | F36: =F33-F34 -> 0 | G36: =G33-G34 -> 4988 | H36: =H33-H34 -> 1612 | I36: =I33-I34 -> 2319 | ... V36: =V33-V34 -> 4252
A37: Satutory Reserve | G37: =IF(G121<G122,0.1*G185,G121-F115) -> 498.8 | H37: =IF(H121<H122,0.1*H185,H121-G115) -> 161.2 | I37: =IF(I121<I122,0.1*I185,I121-H115) -> 231.9 | J37: =IF(J121<J122,0.1*J185,J121-I115) -> 273.6 | K37: =IF(K121<K122,0.1*K185,K121-J115) -> 320.4 | L37: =IF(L121<L122,0.1*L185,L121-K115) -> 214.1 | M37: =IF(M121<M122,0.1*M185,M121-L115) -> 0 | N37: =IF(N121<N122,0.1*N185,N121-M115) -> 0 | ... V37: =IF(V121<V122,0.1*V185,V121-U115) -> 0
A38: Dividends | G38: =ROUND(G152,0) -> 0 | H38: =ROUND(H152,0) -> 0 | I38: =ROUND(I152,0) -> 0 | J38: =ROUND(J152,0) -> 0 | K38: =ROUND(K152,0) -> 0 | L38: =ROUND(L152,0) -> 0 | M38: =ROUND(M152,0) -> 5000 | N38: =ROUND(N152,0) -> 5000 | ... V38: =ROUND(V152,0) -> 8000
A39: Retained Earnings | B39: =B36-B38-B37 -> 0 | C39: =C36-C38-C37 -> 0 | D39: =D36-D38-D37 -> 0 | E39: =E36-E38-E37 -> 0 | F39: =F36-F38-F37 -> 0 | G39: =G36-G38-G37 -> 4489.2 | H39: =H36-H38-H37 -> 1450.8 | I39: =I36-I38-I37 -> 2087.1 | ... V39: =V36-V38-V37 -> -3748
K43: Balance Sheet- Assets | P43: Attachment B-2
R46: (SR in 000s)
C47: HISTORICAL | G47: PROJECTIONS
B48: =IF(B$6=0," ",B$6) | C48: =IF(C$6=0," ",C$6) | D48: =IF(D$6=0," ",D$6) | E48: =IF(E$6=0," ",E$6) | F48: =IF(F$6=0," ",F$6) | G48: =B318 -> 2025 | H48: =C318 -> 2026 | I48: =D318 -> 2027 | J48: =E318 -> 2028 | K48: =F318 -> 2029 | L48: =G318 -> 2030 | M48: =H318 -> 2031 | N48: =I318 -> 2032 | ... V48: =Q318 -> 2040
A50: Cash | G50: =ROUND(F50+G159,0) -> 149 | H50: =ROUND(G50+H159,0) -> 2649 | I50: =ROUND(H50+I159,0) -> 4872 | J50: =ROUND(I50+J159,0) -> 6748 | K50: =ROUND(J50+K159,0) -> 8719 | L50: =ROUND(K50+L159,0) -> 11087 | M50: =ROUND(L50+M159,0) -> 9688 | N50: =ROUND(M50+N159,0) -> 8089 | ... V50: =ROUND(U50+V159,0) -> 4145
A51: Accounts Receivable | G51: =ROUND(G8*Assumptions!F293/365,0) -> 4318 | H51: =ROUND(H8*Assumptions!F293/365,0) -> 3993 | I51: =ROUND(I8*Assumptions!G293/365,0) -> 4463 | J51: =ROUND(J8*Assumptions!H293/365,0) -> 5021 | K51: =ROUND(K8*Assumptions!I293/365,0) -> 5679 | L51: =ROUND(L8*Assumptions!J293/365,0) -> 6514 | M51: =ROUND(M8*Assumptions!J293/365,0) -> 6514 | N51: =ROUND(N8*Assumptions!J293/365,0) -> 6514 | O51: =ROUND(O8*Assumptions!J293/365,0) -> 6514 | P51: =ROUND(P8*Assumptions!J293/365,0) -> 6514 | Q51: =ROUND(Q8*Assumptions!J293/365,0) -> 6514 | R51: =ROUND(R8*Assumptions!J293/365,0) -> 6514 | S51: =ROUND(S8*Assumptions!J293/365,0) -> 6514 | T51: =ROUND(T8*Assumptions!J293/365,0) -> 6514 | U51: =ROUND(U8*Assumptions!J293/365,0) -> 6514 | V51: =ROUND(V8*Assumptions!J293/365,0) -> 6514
A52: Inventory | G52: =ROUND((G20-G15-G16)*Assumptions!F295/365,0) -> 3423 | H52: =ROUND((H20-H15-H16)*Assumptions!F295/365,0) -> 4059 | I52: =ROUND((I20-I15-I16)*Assumptions!G295/365,0) -> 4447 | J52: =ROUND((J20-J15-J16)*Assumptions!H295/365,0) -> 4925 | K52: =ROUND((K20-K15-K16)*Assumptions!I295/365,0) -> 5489 | L52: =ROUND((L20-L15-L16)*Assumptions!J295/365,0) -> 6199 | M52: =ROUND((M20-M15-M16)*Assumptions!J295/365,0) -> 6199 | N52: =ROUND((N20-N15-N16)*Assumptions!J295/365,0) -> 6199 | O52: =ROUND((O20-O15-O16)*Assumptions!J295/365,0) -> 6199 | P52: =ROUND((P20-P15-P16)*Assumptions!J295/365,0) -> 6199 | Q52: =ROUND((Q20-Q15-Q16)*Assumptions!J295/365,0) -> 6199 | R52: =ROUND((R20-R15-R16)*Assumptions!J295/365,0) -> 6199 | S52: =ROUND((S20-S15-S16)*Assumptions!J295/365,0) -> 6199 | T52: =ROUND((T20-T15-T16)*Assumptions!J295/365,0) -> 6199 | U52: =ROUND((U20-U15-U16)*Assumptions!J295/365,0) -> 6199 | V52: =ROUND((V20-V15-V16)*Assumptions!J295/365,0) -> 6199
A53: L/C Margins | G53: =ROUND(G11*Assumptions!F294/365,0) -> 0 | H53: =ROUND(H11*Assumptions!F294/365,0) -> 0 | I53: =ROUND(I11*Assumptions!G294/365,0) -> 0 | J53: =ROUND(J11*Assumptions!H294/365,0) -> 0 | K53: =ROUND(K11*Assumptions!I294/365,0) -> 0 | L53: =ROUND(L11*Assumptions!J294/365,0) -> 0 | M53: =ROUND(M11*Assumptions!J294/365,0) -> 0 | N53: =ROUND(N11*Assumptions!J294/365,0) -> 0 | O53: =ROUND(O11*Assumptions!J294/365,0) -> 0 | P53: =ROUND(P11*Assumptions!J294/365,0) -> 0 | Q53: =ROUND(Q11*Assumptions!J294/365,0) -> 0 | R53: =ROUND(R11*Assumptions!J294/365,0) -> 0 | S53: =ROUND(S11*Assumptions!J294/365,0) -> 0 | T53: =ROUND(T11*Assumptions!J294/365,0) -> 0 | U53: =ROUND(U11*Assumptions!J294/365,0) -> 0 | V53: =ROUND(V11*Assumptions!J294/365,0) -> 0
A54: Prepaid expenses and other current assests
A55: Dues from related parties
A57: Current Assets | B57: =ROUND(SUM(B50:B55),0) -> 0 | C57: =ROUND(SUM(C50:C55),0) -> 0 | D57: =ROUND(SUM(D50:D55),0) -> 0 | E57: =ROUND(SUM(E50:E55),0) -> 0 | F57: =ROUND(SUM(F50:F55),0) -> 0 | G57: =ROUND(SUM(G50:G55),0) -> 7890 | H57: =ROUND(SUM(H50:H55),0) -> 10701 | I57: =ROUND(SUM(I50:I55),0) -> 13782 | ... V57: =ROUND(SUM(V50:V55),0) -> 16858
A59: Land | F59: =Assumptions!D333 -> 0 | G59: =Assumptions!F226+Assumptions!D333 -> 0 | H59: =G59+Assumptions!G226 -> 0 | I59: =H59+Assumptions!H226 -> 0 | J59: =I59+Assumptions!I226 -> 0 | K59: =J59+Assumptions!J226 -> 0 | L59: =K59+Assumptions!K226 -> 0 | M59: =L59+Assumptions!L226 -> 0 | N59: =M59+Assumptions!M226 -> 0 | O59: =N59+Assumptions!N226 -> 0 | ... V59: =U59+Assumptions!U226 -> 0
A60: Buildings | F60: =Assumptions!D334 -> 0 | G60: =Assumptions!F227+Assumptions!D334 -> 770 | H60: =G60+Assumptions!G227 -> 770 | I60: =H60+Assumptions!H227 -> 770 | J60: =I60+Assumptions!I227 -> 770 | K60: =J60+Assumptions!J227 -> 770 | L60: =K60+Assumptions!K227 -> 770 | M60: =L60+Assumptions!L227 -> 770 | N60: =M60+Assumptions!M227 -> 770 | O60: =N60+Assumptions!N227 -> 770 | ... V60: =U60+Assumptions!U227 -> 770
A61: Machinery | F61: =Assumptions!D335 -> 0 | G61: =Assumptions!F228+Assumptions!D335 -> 11353 | H61: =G61+Assumptions!G228 -> 11353 | I61: =H61+Assumptions!H228 -> 11353 | J61: =I61+Assumptions!I228 -> 11353 | K61: =J61+Assumptions!J228 -> 11353 | L61: =K61+Assumptions!K228 -> 11353 | M61: =L61+Assumptions!L228 -> 11353 | N61: =M61+Assumptions!M228 -> 11353 | O61: =N61+Assumptions!N228 -> 11353 | ... V61: =U61+Assumptions!U228 -> 11353
A62: Furniture | F62: =Assumptions!D336 -> 0 | G62: =Assumptions!F229+Assumptions!D336 -> 0 | H62: =G62+Assumptions!G229 -> 0 | I62: =H62+Assumptions!H229 -> 0 | J62: =I62+Assumptions!I229 -> 0 | K62: =J62+Assumptions!J229 -> 0 | L62: =K62+Assumptions!K229 -> 0 | M62: =L62+Assumptions!L229 -> 0 | N62: =M62+Assumptions!M229 -> 0 | O62: =N62+Assumptions!N229 -> 0 | ... V62: =U62+Assumptions!U229 -> 0
A63: Vehicles | F63: =Assumptions!D337 -> 0 | G63: =Assumptions!F230+Assumptions!D337 -> 359 | H63: =G63+Assumptions!G230 -> 359 | I63: =H63+Assumptions!H230 -> 359 | J63: =I63+Assumptions!I230 -> 359 | K63: =J63+Assumptions!J230 -> 359 | L63: =K63+Assumptions!K230 -> 359 | M63: =L63+Assumptions!L230 -> 359 | N63: =M63+Assumptions!M230 -> 359 | O63: =N63+Assumptions!N230 -> 359 | ... V63: =U63+Assumptions!U230 -> 359
A64: Loss Prevention | F64: =Assumptions!D338 -> 0 | G64: =Assumptions!F231+Assumptions!D338 -> 458 | H64: =G64+Assumptions!G231 -> 458 | I64: =H64+Assumptions!H231 -> 458 | J64: =I64+Assumptions!I231 -> 458 | K64: =J64+Assumptions!J231 -> 458 | L64: =K64+Assumptions!K231 -> 458 | M64: =L64+Assumptions!L231 -> 458 | N64: =M64+Assumptions!M231 -> 458 | O64: =N64+Assumptions!N231 -> 458 | ... V64: =U64+Assumptions!U231 -> 458
A65: WUC | F65: =Assumptions!D339 -> 0 | G65: =Assumptions!F232+Assumptions!D339 -> 0 | H65: =G65+Assumptions!G232 -> 0 | I65: =H65+Assumptions!H232 -> 0 | J65: =I65+Assumptions!I232 -> 0 | K65: =J65+Assumptions!J232 -> 0 | L65: =K65+Assumptions!K232 -> 0 | M65: =L65+Assumptions!L232 -> 0 | N65: =M65+Assumptions!M232 -> 0 | O65: =N65+Assumptions!N232 -> 0 | ... V65: =U65+Assumptions!U232 -> 0
A66: Contingencies | B66: NA | C66: NA | D66: NA | E66: NA | F66: NA | G66: =Assumptions!F233 -> 0 | H66: =G66+Assumptions!G233 -> 0 | I66: =SUM(Assumptions!F233:H233) -> 0 | J66: =SUM(Assumptions!F233:I233) -> 0 | K66: =SUM(Assumptions!F233:J233) -> 0 | L66: =SUM(Assumptions!F233:K233) -> 0 | M66: =SUM(Assumptions!F233:L233) -> 0 | N66: =SUM(Assumptions!F233:M233) -> 0 | O66: =SUM(Assumptions!F233:N233) -> 0 | P66: =SUM(Assumptions!F233:O233) -> 0 | Q66: =SUM(Assumptions!F233:P233) -> 0 | R66: =SUM(Assumptions!F233:Q233) -> 0 | S66: =SUM(Assumptions!F233:R233) -> 0 | T66: =SUM(Assumptions!F233:S233) -> 0 | U66: =SUM(Assumptions!F233:T233) -> 0 | V66: =SUM(Assumptions!F233:U233) -> 0
A68: Total Fixed Assets | B68: =SUM(B59:B65) -> 0 | C68: =SUM(C59:C65) -> 0 | D68: =SUM(D59:D65) -> 0 | E68: =SUM(E59:E65) -> 0 | F68: =Assumptions!D341 -> 0 | G68: =SUM(G59:G66) -> 12940 | H68: =SUM(H59:H66) -> 12940 | I68: =SUM(I59:I66) -> 12940 | J68: =SUM(J59:J66) -> 12940 | K68: =SUM(K59:K66) -> 12940 | L68: =SUM(L59:L66) -> 12940 | M68: =SUM(M59:M66) -> 12940 | N68: =SUM(N59:N66) -> 12940 | ... V68: =SUM(V59:V66) -> 12940
A69: Accum. Depreciation | F69: =Assumptions!E341 -> 0 | G69: =G15+Assumptions!E341 -> 0 | H69: =H15+G69 -> 702 | I69: =I15+H69 -> 1404 | J69: =J15+I69 -> 2106 | K69: =K15+J69 -> 2808 | L69: =K69+L15 -> 3510 | M69: =L69+M15 -> 4140 | N69: =M69+N15 -> 4770 | O69: =N69+O15 -> 5400 | P69: =O69+P15 -> 6030 | Q69: =P69+Q15 -> 6660 | R69: =Q69+R15 -> 7290 | S69: =R69+S15 -> 7920 | ... V69: =U69+V15 -> 9810
A70: Net Fixed Assets | B70: =B68-B69 -> 0 | C70: =C68-C69 -> 0 | D70: =D68-D69 -> 0 | E70: =E68-E69 -> 0 | F70: =Assumptions!D341-Assumptions!E341 -> 0 | G70: =G68-G69 -> 12940 | H70: =H68-H69 -> 12238 | I70: =I68-I69 -> 11536 | J70: =J68-J69 -> 10834 | K70: =K68-K69 -> 10132 | L70: =L68-L69 -> 9430 | M70: =M68-M69 -> 8800 | N70: =N68-N69 -> 8170 | ... V70: =V68-V69 -> 3130
A72: puc
A74: SIDF Charge | F74: =Assumptions!D343 -> 0 | G74: =Assumptions!F236+Assumptions!D343 -> 300 | H74: =G74+Assumptions!G236 -> 300 | I74: =H74+Assumptions!H236 -> 300 | J74: =I74+Assumptions!I236 -> 300 | K74: =J74+Assumptions!J236 -> 300 | L74: =K74+Assumptions!K236 -> 300 | M74: =L74+Assumptions!L236 -> 300 | N74: =M74+Assumptions!M236 -> 300 | O74: =N74+Assumptions!N236 -> 300 | ... V74: =U74+Assumptions!U236 -> 300
A75: Preoperating Expense | F75: =Assumptions!D344 -> 0 | G75: =Assumptions!F237+Assumptions!D344 -> 99 | H75: =G75+Assumptions!G237 -> 99 | I75: =H75+Assumptions!H237 -> 99 | J75: =I75+Assumptions!I237 -> 99 | K75: =J75+Assumptions!J237 -> 99 | L75: =K75+Assumptions!K237 -> 99 | M75: =L75+Assumptions!L237 -> 99 | N75: =M75+Assumptions!M237 -> 99 | O75: =N75+Assumptions!N237 -> 99 | ... V75: =U75+Assumptions!U237 -> 99
A76: Total Intangibles | B76: =SUM(B74:B75) -> 0 | C76: =SUM(C74:C75) -> 0 | D76: =SUM(D74:D75) -> 0 | E76: =SUM(E74:E75) -> 0 | F76: =Assumptions!D346 -> 0 | G76: =SUM(G74:G75) -> 399 | H76: =SUM(H74:H75) -> 399 | I76: =SUM(I74:I75) -> 399 | J76: =SUM(J74:J75) -> 399 | K76: =SUM(K74:K75) -> 399 | L76: =SUM(L74:L75) -> 399 | M76: =SUM(M74:M75) -> 399 | N76: =SUM(N74:N75) -> 399 | ... V76: =SUM(V74:V75) -> 399
A77: Accum. Amortization | F77: =Assumptions!E346 -> 0 | G77: =Assumptions!E346+G16 -> 1312 | H77: =G77+H16 -> 1711 | I77: =H77+I16 -> 1711 | J77: =I77+J16 -> 1711 | K77: =J77+K16 -> 1711 | L77: =K77+L16 -> 1711 | M77: =L77+M16 -> 1711 | N77: =M77+N16 -> 1711 | O77: =N77+O16 -> 1711 | ... V77: =U77+V16 -> 1711
A78: Net Intangibles | B78: =B76-B77 -> 0 | C78: =C76-C77 -> 0 | D78: =D76-D77 -> 0 | E78: =E76-E77 -> 0 | F78: =Assumptions!D346-Assumptions!E346 -> 0 | G78: =G76-G77 -> -913 | H78: =H76-H77 -> -1312 | I78: =I76-I77 -> -1312 | J78: =J76-J77 -> -1312 | K78: =K76-K77 -> -1312 | L78: =L76-L77 -> -1312 | M78: =M76-M77 -> -1312 | N78: =N76-N77 -> -1312 | ... V78: =V76-V77 -> -1312
A80: Total Assets | B80: =B57+B70+B72+B78 -> 0 | C80: =C57+C70+C72+C78 -> 0 | D80: =D57+D70+D72+D78 -> 0 | E80: =E57+E70+E72+E78 -> 0 | F80: =F57+F70+F72+F78 -> 0 | G80: =ROUND(G57+G70+G72+G78,0) -> 19917 | H80: =ROUND(H57+H70+H72+H78,0) -> 21627 | I80: =ROUND(I57+I70+I72+I78,0) -> 24006 | J80: =ROUND(J57+J70+J72+J78,0) -> 26216 | K80: =ROUND(K57+K70+K72+K78,0) -> 28707 | L80: =ROUND(L57+L70+L72+L78,0) -> 31918 | M80: =ROUND(M57+M70+M72+M78,0) -> 29889 | N80: =ROUND(N57+N70+N72+N78,0) -> 27660 | ... V80: =ROUND(V57+V70+V72+V78,0) -> 18676
J83: Balance Sheet- Liabilities & Equity | P83: Attachment B-3
S85: (SR in 000s)
G86: =IF(G185>0,F115+0.1*G185,F115) -> 498.8 | H86: =IF(H185>0,G115+0.1*H185,G115) -> 660 | I86: =IF(I185>0,H115+0.1*I185,H115) -> 891.9 | J86: =IF(J185>0,I115+0.1*J185,I115) -> 1165.5 | K86: =IF(K185>0,J115+0.1*K185,J115) -> 1485.9 | L86: =IF(L185>0,K115+0.1*L185,K115) -> 1896 | M86: =IF(M185>0,L115+0.1*M185,L115) -> 2117.1 | N86: =IF(N185>0,M115+0.1*N185,M115) -> 2117.1 | ... AB86: =IF(AB185>0,AA115+0.1*AB185,AA115) -> 0
C87: HISTORICAL | G87: PROJECTIONS
B88: =IF(B$6=0," ",B$6) | C88: =IF(C$6=0," ",C$6) | D88: =IF(D$6=0," ",D$6) | E88: =IF(E$6=0," ",E$6) | F88: =IF(F$6=0," ",F$6) | G88: =B318 -> 2025 | H88: =C318 -> 2026 | I88: =D318 -> 2027 | J88: =E318 -> 2028 | K88: =F318 -> 2029 | L88: =G318 -> 2030 | M88: =H318 -> 2031 | N88: =I318 -> 2032 | ... V88: =Q318 -> 2040
A90: Accounts Payable | G90: =ROUND((G20-G16-G15)*Assumptions!F296/365,0) -> 529 | H90: =ROUND((H20-H16-H15)*Assumptions!F296/365,0) -> 627 | I90: =ROUND((I20-I16-I15)*Assumptions!G296/365,0) -> 687 | J90: =ROUND((J20-J16-J15)*Assumptions!H296/365,0) -> 761 | K90: =ROUND((K20-K16-K15)*Assumptions!I296/365,0) -> 848 | L90: =ROUND((L20-L16-L15)*Assumptions!J296/365,0) -> 958 | M90: =ROUND((M20-M16-M15)*Assumptions!J296/365,0) -> 958 | N90: =ROUND((N20-N16-N15)*Assumptions!J296/365,0) -> 958 | O90: =ROUND((O20-O16-O15)*Assumptions!J296/365,0) -> 958 | P90: =ROUND((P20-P16-P15)*Assumptions!J296/365,0) -> 958 | Q90: =ROUND((Q20-Q16-Q15)*Assumptions!J296/365,0) -> 958 | R90: =ROUND((R20-R16-R15)*Assumptions!J296/365,0) -> 958 | S90: =ROUND((S20-S16-S15)*Assumptions!J296/365,0) -> 958 | T90: =ROUND((T20-T16-T15)*Assumptions!J296/365,0) -> 958 | U90: =ROUND((U20-U16-U15)*Assumptions!J296/365,0) -> 958 | V90: =ROUND((V20-V16-V15)*Assumptions!J296/365,0) -> 958
A91: STD | G91: =ROUND(F91+G135-G151,0) -> 0 | H91: =ROUND(G91+H135-H151,0) -> 0 | I91: =ROUND(H91+I135-I151,0) -> 0 | J91: =ROUND(I91+J135-J151,0) -> 0 | K91: =ROUND(J91+K135-K151,0) -> 0 | L91: =ROUND(K91+L135-L151,0) -> 0 | M91: =ROUND(L91+M135-M151,0) -> 0 | N91: =ROUND(M91+N135-N151,0) -> 0 | ... V91: =ROUND(U91+V135-V151,0) -> 0
A92: Accruals
A93: CPLTD - SIDF | G93: =Assumptions!D307 -> 0 | H93: =Assumptions!D308 -> 0 | I93: =Assumptions!D309 -> 600 | J93: =Assumptions!D310 -> 800 | K93: =L147 -> 1000 | L93: =M147 -> 1200 | M93: =N147 -> 1400 | N93: =O147 -> 0 | O93: =P147 -> 0 | P93: =Q147 -> 0 | Q93: =R147 -> 0 | R93: =S147 -> 0 | ... V93: =W147 -> 0
A94: - Bank | G94: =Assumptions!E307 -> 0 | H94: =Assumptions!E308 -> 0 | I94: =Assumptions!E309 -> 0 | J94: =Assumptions!E310 -> 0 | K94: =Assumptions!E311 -> 0 | L94: =Assumptions!E312 -> 0 | M94: =Assumptions!E313 -> 0 | N94: =Assumptions!E314 -> 0 | O94: =Assumptions!E315 -> 0 | P94: =Assumptions!E316 -> 0 | Q94: =Assumptions!H306 -> 0 | R94: =Assumptions!H307 -> 0 | S94: =Assumptions!H308 -> 0 | T94: =Assumptions!H309 -> 0 | U94: =Assumptions!H310 -> 0 | V94: 0
A95: =" - "&A104 -> - | G95: =H149 -> 0 | H95: =I149 -> 0 | I95: =J149 -> 0 | J95: =K149 -> 0 | K95: =L149 -> 0 | L95: =M149 -> 0 | M95: =N149 -> 0 | N95: =O149 -> 0 | ... U95: =V149 -> 0 | V95: 0
A99: Current Liabilities | B99: =ROUND(SUM(B90:B97),0) -> 0 | C99: =ROUND(SUM(C90:C97),0) -> 0 | D99: =ROUND(SUM(D90:D97),0) -> 0 | E99: =ROUND(SUM(E90:E97),0) -> 0 | F99: =ROUND(SUM(F90:F97),0) -> 0 | G99: =ROUND(SUM(G90:G97),0) -> 529 | H99: =ROUND(SUM(H90:H97),0) -> 627 | I99: =ROUND(SUM(I90:I97),0) -> 1287 | ... P99: =ROUND(SUM(P90:P97),0) -> 958 | Q99: =SUM(Q90:Q97) -> 958 | R99: =ROUND(SUM(R90:R97),0) -> 958 | S99: =ROUND(SUM(S90:S97),0) -> 958 | T99: =ROUND(SUM(T90:T97),0) -> 958 | U99: =ROUND(SUM(U90:U97),0) -> 958 | V99: =SUM(V90:V97) -> 958
A101: Long Term Debt:
A102: SIDF | G102: =ROUND(F102+G131-G93,0) -> 5000 | H102: =ROUND(G102+H131-H93,0) -> 5000 | I102: =ROUND(H102+I131-I93,0) -> 4400 | J102: =ROUND(I102+J131-J93,0) -> 3600 | K102: =ROUND(J102+K131-K93,0) -> 2600 | L102: =ROUND(K102+L131-L93,0) -> 1400 | M102: =ROUND(L102+M131-M93,0) -> 0 | N102: =ROUND(M102+N131-N93,0) -> 0 | ... V102: =ROUND(U102+V131-V93,0) -> 0
A103: Bank | G103: =ROUND(F103+G132-G94,0) -> 0 | H103: =ROUND(G103+H132-H94,0) -> 0 | I103: =ROUND(H103+I132-I94,0) -> 0 | J103: =ROUND(I103+J132-J94,0) -> 0 | K103: =ROUND(J103+K132-K94,0) -> 0 | L103: =ROUND(K103+L132-L94,0) -> 0 | M103: =ROUND(L103+M132-M94,0) -> 0 | N103: =ROUND(M103+N132-N94,0) -> 0 | ... V103: =ROUND(U103+V132-V94,0) -> 0
G104: =ROUND(F104+G133-G95,0) -> 0 | H104: =ROUND(G104+H133-H95,0) -> 0 | I104: =ROUND(H104+I133-I95,0) -> 0 | J104: =ROUND(I104+J133-J95,0) -> 0 | K104: =ROUND(J104+K133-K95,0) -> 0 | L104: =ROUND(K104+L133-L95,0) -> 0 | M104: =ROUND(L104+M133-M95,0) -> 0 | N104: =ROUND(M104+N133-N95,0) -> 0 | ... V104: =ROUND(U104+V133-V95,0) -> 0
A106: Long Term Debt | B106: =SUM(B102:B104) -> 0 | C106: =SUM(C102:C104) -> 0 | D106: =SUM(D102:D104) -> 0 | E106: =SUM(E102:E104) -> 0 | F106: =ROUND(SUM(F102:F104),0) -> 0 | G106: =SUM(G102:G104) -> 5000 | H106: =SUM(H102:H104) -> 5000 | I106: =SUM(I102:I104) -> 4400 | J106: =SUM(J102:J104) -> 3600 | K106: =SUM(K102:K104) -> 2600 | L106: =SUM(L102:L104) -> 1400 | M106: =SUM(M102:M104) -> 0 | N106: =SUM(N102:N104) -> 0 | ... V106: =SUM(V102:V104) -> 0
A108: end
A110: Total Liabilities | B110: =ROUND(B99+B106+B108,0) -> 0 | C110: =ROUND(C99+C106+C108,0) -> 0 | D110: =ROUND(D99+D106+D108,0) -> 0 | E110: =ROUND(E99+E106+E108,0) -> 0 | F110: =ROUND(F99+F106+F108,0) -> 0 | G110: =ROUND(G99+G106+G108,0) -> 5529 | H110: =ROUND(H99+H106+H108,0) -> 5627 | I110: =ROUND(I99+I106+I108,0) -> 5687 | ... V110: =ROUND(V99+V106+V108,0) -> 958
A112: Paid in Capital | G112: =ROUND(G130+F112,0) -> 3400 | H112: =ROUND(H130+G112,0) -> 3400 | I112: =ROUND(I130+H112,0) -> 3400 | J112: =ROUND(J130+I112,0) -> 3400 | K112: =ROUND(K130+J112,0) -> 3400 | L112: =ROUND(L130+K112,0) -> 3400 | M112: =ROUND(M130+L112,0) -> 3400 | N112: =ROUND(N130+M112,0) -> 3400 | ... V112: =ROUND(V130+U112,0) -> 3400
A113: Subordinated Debt | G113: =ROUND(F113+G134-G150,0) -> 0 | H113: =ROUND(G113+H134-H150,0) -> 0 | I113: =ROUND(H113+I134-I150,0) -> 0 | J113: =ROUND(I113+J134-J150,0) -> 0 | K113: =ROUND(J113+K134-K150,0) -> 0 | L113: =ROUND(K113+L134-L150,0) -> 0 | M113: =ROUND(L113+M134-M150,0) -> 0 | N113: =ROUND(M113+N134-N150,0) -> 0 | ... V113: =ROUND(U113+V134-V150,0) -> 0
A114: Retained Earnings | G114: =ROUND(F114+G39,0) -> 4489 | H114: =G114+H39 -> 5939.8 | I114: =H114+I39 -> 8026.9 | J114: =I114+J39 -> 10489.3 | K114: =J114+K39 -> 13372.9 | L114: =K114+L39 -> 17259.8 | M114: =L114+M39 -> 16430.8 | N114: =M114+N39 -> 15601.8 | O114: =N114+O39 -> 14853.8 | ... V114: =U114+V39 -> 6617.8
A115: Satutory Reserve | G115: =IF(G37=0,F115,G121) -> 498.8 | H115: =IF(H37=0,G115,H121) -> 660 | I115: =IF(I37=0,H115,I121) -> 891.9 | J115: =IF(J37=0,I115,J121) -> 1165.5 | K115: =IF(K37=0,J115,K121) -> 1485.9 | L115: =IF(L37=0,K115,L121) -> 1700 | M115: =IF(M37=0,L115,M121) -> 1700 | N115: =IF(N37=0,M115,N121) -> 1700 | ... V115: =IF(V37=0,U115,V121) -> 1700
G116: 6000 | H116: 6000 | I116: 6000 | J116: 6000 | K116: 6000 | L116: 6000 | M116: 6000 | N116: 6000 | O116: 6000 | P116: 6000 | Q116: 6000 | R116: 6000 | S116: 6000 | T116: 6000 | U116: 6000 | V116: 6000
A118: Total Equity | B118: =ROUND(SUM(B112:B116),0) -> 0 | C118: =ROUND(SUM(C112:C116),0) -> 0 | D118: =ROUND(SUM(D112:D116),0) -> 0 | E118: =ROUND(SUM(E112:E116),0) -> 0 | F118: =ROUND(SUM(F112:F116),0) -> 0 | G118: =ROUND(SUM(G112:G116),0) -> 14388 | H118: =ROUND(SUM(H112:H116),0) -> 16000 | I118: =ROUND(SUM(I112:I116),0) -> 18319 | ... V118: =ROUND(SUM(V112:V116),0) -> 17718
A120: Total Liab & Equity | B120: =B110+B118 -> 0 | C120: =C110+C118 -> 0 | D120: =D110+D118 -> 0 | E120: =E110+E118 -> 0 | F120: =F110+F118 -> 0 | G120: =ROUND(G110+G118,0) -> 19917 | H120: =ROUND(H110+H118,0) -> 21627 | I120: =ROUND(I110+I118,0) -> 24006 | J120: =ROUND(J110+J118,0) -> 26216 | K120: =ROUND(K110+K118,0) -> 28707 | L120: =ROUND(L110+L118,0) -> 31918 | M120: =ROUND(M110+M118,0) -> 29889 | N120: =ROUND(N110+N118,0) -> 27660 | ... V120: =ROUND(V110+V118,0) -> 18676
G121: =IF(G86>0.5*G112,0.5*G112,G86) -> 498.8 | H121: =IF(H86>0.5*H112,0.5*H112,H86) -> 660 | I121: =IF(I86>0.5*I112,0.5*I112,I86) -> 891.9 | J121: =IF(J86>0.5*J112,0.5*J112,J86) -> 1165.5 | K121: =IF(K86>0.5*K112,0.5*K112,K86) -> 1485.9 | L121: =IF(L86>0.5*L112,0.5*L112,L86) -> 1700 | M121: =IF(M86>0.5*M112,0.5*M112,M86) -> 1700 | N121: =IF(N86>0.5*N112,0.5*N112,N86) -> 1700 | ... V121: =IF(V86>0.5*V112,0.5*V112,V86) -> 1700
J123: Source And Application Of Cash | P123: Attachment B-4
B125: =B93+B91+B94+B95+B27 -> 0 | C125: =C93+C91+C94+C95+C27 -> 0 | D125: =D93+D91+D94+D95+D27 -> 0 | E125: =E93+E91+E94+E95+E27 -> 0 | F125: =F93+F91+F94+F95+F27 -> 0 | G125: =G93+G91+G94+G95+G27 -> 0 | H125: =H93+H91+H94+H95+H27 -> 83 | I125: =I93+I91+I94+I95+I27 -> 683 | ... V125: =V93+V91+V94+V95+V27 -> 0
R126: (SR in 000s)
C127: HISTORICAL | G127: PROJECTIONS
B128: =IF(B$6=0," ",B$6) | C128: =IF(C$6=0," ",C$6) | D128: =IF(D$6=0," ",D$6) | E128: =IF(E$6=0," ",E$6) | F128: =IF(F$6=0," ",F$6) | G128: =B318 -> 2025 | H128: =C318 -> 2026 | I128: =D318 -> 2027 | J128: =E318 -> 2028 | K128: =F318 -> 2029 | L128: =G318 -> 2030 | M128: =H318 -> 2031 | N128: =I318 -> 2032 | ... V128: =Q318 -> 2040
A129: Sources of Cash:
A130: Paid in Capital | B130: NA | C130: =IF(C112-B112>0,C112-B112,0) -> 0 | D130: =IF(D112-C112>0,D112-C112,0) -> 0 | E130: =IF(E112-D112>0,E112-D112,0) -> 0 | F130: =IF(F112-E112>0,F112-E112,0) -> 0 | G130: ='Attachment "A"'!F23 -> 3400
A131: LTD - SIDF | B131: NA | C131: =IF(C102+C93-B102-B93>0,C102+C93-B102-B93,0) -> 0 | D131: =IF(D102+D93-C102-C93>0,D102+D93-C102-C93,0) -> 0 | E131: =IF(E102+E93-D102-D93>0,E102+E93-D102-D93,0) -> 0 | F131: =IF(F102+F93-E102-E93>0,F102+F93-E102-E93,0) -> 0 | G131: ='Attachment "A"'!F22 -> 5000
A132: LTD - Bank | B132: NA | C132: =IF(C103+C94-B103-B94>0,C103+C94-B103-B94,0) -> 0 | D132: =IF(D103+D94-C103-C94>0,D103+D94-C103-C94,0) -> 0 | E132: =IF(E103+E94-D103-D94>0,E103+E94-D103-D94,0) -> 0 | F132: =IF(F103+F94-E103-E94>0,F103+F94-E103-E94,0) -> 0
A133: =LEFT("LTD - ",6)&A104 -> LTD - | B133: NA | C133: =IF(C104+C95-B104-B95>0,C104+C95-B104-B95,0) -> 0 | D133: =IF(D104+D95-C104-C95>0,D104+D95-C104-C95,0) -> 0 | E133: =IF(E104+E95-D104-D95>0,E104+E95-D104-D95,0) -> 0 | F133: =IF(F104+F95-E104-E95>0,F104+F95-E104-E95,0) -> 0
A134: Subordinated Debt | B134: NA | C134: =IF(C113-B113>0,C113-B113,0) -> 0 | D134: =IF(D113-C113>0,D113-C113,0) -> 0 | E134: =IF(E113-D113>0,E113-D113,0) -> 0 | F134: =IF(F113-E113>0,F113-E113,0) -> 0
A135: STD | B135: NA | C135: =IF(C91-B91>0,C91-B91,0) -> 0 | D135: =IF(D91-C91>0,D91-C91,0) -> 0 | E135: =IF(E91-D91>0,E91-D91,0) -> 0 | F135: =IF(F91-E91>0,F91-E91,0) -> 0
A136: Other Assets | B136: NA | C136: =IF(B$54+B$55+B$72-C$54-C$55-C$72>0,B$54+B$55+B$72-C$54-C$55-C$72,0) -> 0 | D136: =IF(C$54+C$55+C$72-D$54-D$55-D$72>0,C$54+C$55+C$72-D$54-D$55-D$72,0) -> 0 | E136: =IF(D$54+D$55+D$72-E$54-E$55-E$72>0,D$54+D$55+D$72-E$54-E$55-E$72,0) -> 0 | F136: =IF(E$54+E$55+E$72-F$54-F$55-F$72>0,E$54+E$55+E$72-F$54-F$55-F$72,0) -> 0 | G136: =IF(F$54+F$55+F$72-G$54-G$55-G$72>0,F$54+F$55+F$72-G$54-G$55-G$72,0) -> 0 | H136: =IF(G$54+G$55+G$72-H$54-H$55-H$72>0,G$54+G$55+G$72-H$54-H$55-H$72,0) -> 0 | I136: =IF(H$54+H$55+H$72-I$54-I$55-I$72>0,H$54+H$55+H$72-I$54-I$55-I$72,0) -> 0 | J136: =IF(I$54+I$55+I$72-J$54-J$55-J$72>0,I$54+I$55+I$72-J$54-J$55-J$72,0) -> 0 | ... V136: =IF(U$54+U$55+U$72-V$54-V$55-V$72>0,U$54+U$55+U$72-V$54-V$55-V$72,0) -> 0
A137: Other Liabilities & Equity | B137: NA | C137: =IF(C$96+C$97+C$108+C$116-B$96-B$97-B$108-B$116>0,C$96+C$97+C$108+C$116-B$96-B$97-B$108-B$116,0) -> 0 | D137: =IF(D$96+D$97+D$108+D$116-C$96-C$97-C$108-C$116>0,D$96+D$97+D$108+D$116-C$96-C$97-C$108-C$116,0) -> 0 | E137: =IF(E$96+E$97+E$108+E$116-D$96-D$97-D$108-D$116>0,E$96+E$97+E$108+E$116-D$96-D$97-D$108-D$116,0) -> 0 | F137: =IF(F$96+F$97+F$108+F$116-E$96-E$97-E$108-E$116>0,F$96+F$97+F$108+F$116-E$96-E$97-E$108-E$116,0) -> 0 | G137: =IF(G$96+G$97+G$108+G$116-F$96-F$97-F$108-F$116>0,G$96+G$97+G$108+G$116-F$96-F$97-F$108-F$116,0) -> 6000 | H137: =IF(H$96+H$97+H$108+H$116-G$96-G$97-G$108-G$116>0,H$96+H$97+H$108+H$116-G$96-G$97-G$108-G$116,0) -> 0 | I137: =IF(I$96+I$97+I$108+I$116-H$96-H$97-H$108-H$116>0,I$96+I$97+I$108+I$116-H$96-H$97-H$108-H$116,0) -> 0 | J137: =IF(J$96+J$97+J$108+J$116-I$96-I$97-I$108-I$116>0,J$96+J$97+J$108+J$116-I$96-I$97-I$108-I$116,0) -> 0 | ... V137: =IF(V$96+V$97+V$108+V$116-U$96-U$97-U$108-U$116>0,V$96+V$97+V$108+V$116-U$96-U$97-U$108-U$116,0) -> 0
A138: Profit | B138: NA | C138: =C36 -> 0 | D138: =D36 -> 0 | E138: =E36 -> 0 | F138: =F36 -> 0 | G138: =G36 -> 4988 | H138: =H36 -> 1612 | I138: =I36 -> 2319 | J138: =J36 -> 2736 | ... V138: =V36 -> 4252
...

Sheet Attachment "A"
A1: Attachment "A" | I1: Implementation Starting year | J1: 2024 | K1: To Be Filled If There is a Disbursement Through L/C | AC1: Yes | AD1: 2021
M2: =J1 -> 2024 | Q2: =M2+1 -> 2025 | AC2: No | AD2: 2022
K3: L/C? | L3: Amount SR '000 | M3: 1st Q | N3: 2nd Q | O3: 3rd Q | P3: 4th Q | Q3: 1st Q | R3: 2nd Q | S3: 3rd Q | T3: 4th Q | AD3: 2023
F4: SIDF Loan | G4: 0.39 | AD4: 2024
A5: Project Cost | AD5: 2025
A6: Items | D6: Total Projected | E6: Non Financeable | F6: Total Financeable | AD6: 2026
D7: SR '000 | AD7: 2027
A8: Land | D8: 0 | E8: 0 | F8: =D8-E8 -> 0 | AD8: 2028
A9: Building & Civil works | D9: =Assumptions!F227+Assumptions!G227 -> 770 | E9: 0 | F9: =D9-E9 -> 770 | M9: steps: 1- L/C?: choose Yes or No? 2- Amount: insert the amount of the LC 3- Choose which Quarter by Choosing Yes or No 4- Insert the amount under the chosen Quarter 5- It will be reflect directly on the liquidity needed table (row 40) | AD9: 2029
A10: Loss Prevention | D10: =Assumptions!F231+Assumptions!G231 -> 458 | E10: 0 | F10: =D10-E10 -> 458 | AD10: 2030
A11: Machinary & Equipment | D11: =Assumptions!F228+Assumptions!G228 -> 11353 | E11: 0 | F11: =D11-E11 -> 11353 | AD11: 2031
A12: Vehicles | D12: =Assumptions!F230+Assumptions!G230 -> 359 | E12: 0 | F12: =D12-E12 -> 359 | AD12: 2032
A13: Office Furniture | D13: =Assumptions!F229+Assumptions!G229 -> 0 | E13: 0 | F13: =D13-E13 -> 0 | AD13: 2033
A14: Funded Working Capital | D14: 0 | E14: 0 | F14: =D14-E14 -> 0 | AD14: 2034
A15: Pre-Operating Expenses | D15: =Assumptions!F237 -> 99 | E15: 0 | F15: =D15-E15 -> 99 | AD15: 2035
A16: Contingencies | D16: 0 | E16: 0 | F16: =D16-E16 -> 0 | AD16: 2036
A17: SIDF Evaluation Charges | D17: =Assumptions!F236+Assumptions!G236 -> 300 | E17: =D17 -> 300 | F17: =D17-E17 -> 0 | AD17: 2037
A18: Total Project Costs | D18: =SUM(D8:D17) -> 13339 | E18: =SUM(E8:E17) -> 300 | F18: =SUM(F8:F17) -> 13039 | AD18: 2038
A19: Source of Finance | AD19: 2039
A20: Items | AD20: 2040
A21: To be Financed by: | D21: % | E21: SR'000 | F21: Say | G21: % Of Project Cost | AD21: 2040
A22: SIDF Loan | D22: =IF(F22=0,"0",F22/$F$26) -> 0.37484069 | E22: =ROUND(G4*F18,0) -> 5085 | F22: =ROUNDDOWN(E22,-2) -> 5000 | G22: =F22/F26 -> 0.37484069
A23: Paid in Capital | D23: =IF(F23=0,"0",F23/$F$26) -> 0.25489167 | E23: =D18*0.25 -> 3334.75 | F23: =ROUNDUP(E23,-2) -> 3400 | G23: =F23/F26 -> 0.25489167
A24: Internally Generated Fund | D24: =IF(F24=0,"0",F24/$F$26) -> 0.37026764 | E24: =D18-F23-F22 -> 4939 | F24: =E24 -> 4939 | G24: =F24/F26 -> 0.37026764
D25: =IF(F25=0,"0",F25/$F$26) -> 0 | E25: 0 | F25: =E25 -> 0 | G25: =F25/F26 -> 0
A26: Total | D26: =SUM(D22:D25) -> 1 | F26: =SUM(F22:F25) -> 13339
A28: Implementation Status | M28: 1- Insert the % of implementation completion for each category under each Quarter 2-The cumulative completion % of each category should not exceed 100% (check column j) 3- M&E % completion should not include any L/C in the Implementation status table as it should be reflected in the L/C table above
B29: =J1 -> 2024 | F29: =B29+1 -> 2025 | J29: completion %
A30: % | B30: 1st Q | C30: 2nd Q | D30: 3rd Q | E30: 4th Q | F30: 1st Q | G30: 2nd Q | H30: 3rd Q | I30: 4th Q
A31: Items
A32: Building & Civil works | B32: 0.3 | C32: 0.4 | D32: 0.3 | J32: =SUM(B32:I32) -> 1
A33: Loss Prevention | D33: 0.4 | E33: 0.6 | J33: =SUM(B33:I33) -> 1
A34: Machinary & Equipment | C34: 0.3 | D34: 0.3 | E34: 0.4 | J34: =SUM(B34:I34) -> 1
A35: Vehicles | D35: 0.5 | E35: 0.5 | J35: =SUM(B35:I35) -> 1
A36: Office Furniture | E36: 0.5 | F36: 0.5 | J36: =SUM(B36:I36) -> 1 | N36: To validate the following: 1- SIDF loan (row 44) should not exceed the approved loan amount minus Evaluation fees 2- L/C amount (row 45) should not exceed the approved loan amount. If there is no LC the row should be colored black and if there is an LC it will automatically be reflected from the LC table above 3- Evaluation Cost (row 46) should not exceed the approved Evaluation cost 4- The sum of SIDF loan, L/C and Evaluation Cost should not exceed the approved Loan amount 5- Total SIDF disbursements should be equal to SIDF loan minus SIDF evaluation Cost
A37: Funded Working Capital | J37: =SUM(B37:I37) -> 0
A38: Pre-Operating Expenses | D38: 0.3 | E38: 0.7 | J38: =SUM(B38:I38) -> 1
A39: Contingencies | J39: =SUM(B39:I39) -> 0
A41: Liquidity Needed (Automatically Filled)
A42: SR '000 | B42: =B29 -> 2024 | F42: =F29 -> 2025 | K42: Valdiation
A43: Quarter | B43: =B30 -> 1st Q | C43: =C30 -> 2nd Q | D43: =D30 -> 3rd Q | E43: =E30 -> 4th Q | F43: =F30 -> 1st Q | G43: =G30 -> 2nd Q | H43: =H30 -> 3rd Q | I43: =I30 -> 4th Q
A44: Liquidity Need | B44: =ROUND(($F$9*B32),2)+ROUND(($F$10*B33),2)+ROUND(($F$11*B34),2)+ROUND(($F$12*B35),2)+ROUND(($F$13*B36),2)+ROUND(($F$14*B37),2)+ROUND(($F$15*B38),2)+ROUND(($F$16*B39),2) -> 231 | C44: =ROUND(($F$9*C32),2)+ROUND(($F$10*C33),2)+ROUND(($F$11*C34),2)+ROUND(($F$12*C35),2)+ROUND(($F$13*C36),2)+ROUND(($F$14*C37),2)+ROUND(($F$15*C38),2)+ROUND(($F$16*C39),2) -> 3713.9 | D44: =ROUND(($F$9*D32),2)+ROUND(($F$10*D33),2)+ROUND(($F$11*D34),2)+ROUND(($F$12*D35),2)+ROUND(($F$13*D36),2)+ROUND(($F$14*D37),2)+ROUND(($F$15*D38),2)+ROUND(($F$16*D39),2) -> 4029.3 | E44: =ROUND(($F$9*E32),2)+ROUND(($F$10*E33),2)+ROUND(($F$11*E34),2)+ROUND(($F$12*E35),2)+ROUND(($F$13*E36),2)+ROUND(($F$14*E37),2)+ROUND(($F$15*E38),2)+ROUND(($F$16*E39),2) -> 5064.8 | F44: =ROUND(($F$9*F32),2)+ROUND(($F$10*F33),2)+ROUND(($F$11*F34),2)+ROUND(($F$12*F35),2)+ROUND(($F$13*F36),2)+ROUND(($F$14*F37),2)+ROUND(($F$15*F38),2)+ROUND(($F$16*F39),2) -> 0 | G44: =ROUND(($F$9*G32),2)+ROUND(($F$10*G33),2)+ROUND(($F$11*G34),2)+ROUND(($F$12*G35),2)+ROUND(($F$13*G36),2)+ROUND(($F$14*G37),2)+ROUND(($F$15*G38),2)+ROUND(($F$16*G39),2) -> 0 | H44: =ROUND(($F$9*H32),2)+ROUND(($F$10*H33),2)+ROUND(($F$11*H34),2)+ROUND(($F$12*H35),2)+ROUND(($F$13*H36),2)+ROUND(($F$14*H37),2)+ROUND(($F$15*H38),2)+ROUND(($F$16*H39),2) -> 0 | I44: =ROUND(($F$9*I32),2)+ROUND(($F$10*I33),2)+ROUND(($F$11*I34),2)+ROUND(($F$12*I35),2)+ROUND(($F$13*I36),2)+ROUND(($F$14*I37),2)+ROUND(($F$15*I38),2)+ROUND(($F$16*I39),2) -> 0 | K44: =SUM(B44:I44) -> 13039
A45: SIDF Loan | B45: 0 | C45: =ROUND(IF(((B44*$G$4))<0,0,((B44*$G$4)))-(((B44*$G$4)/$F$22)*$D$17),100) -> 84.6846 | D45: =ROUND(IF(((C44*$G$4))<0,0,((C44*$G$4)))-(((C44*$G$4)/$F$22)*$D$17),100) -> 1361.5157 | E45: =ROUND(IF(((D44*$G$4))<0,0,((D44*$G$4)))-(((D44*$G$4)/$F$22)*$D$17),100) -> 1477.1414 | F45: =ROUND(IF(((E44*$G$4))<0,0,((E44*$G$4)))-(((E44*$G$4)/$F$22)*$D$17),100) -> 1856.7557 | G45: =ROUND(IF(((F44*$G$4))<0,0,((F44*$G$4)))-(((F44*$G$4)/$F$22)*$D$17),100) -> 0 | H45: =ROUND(IF(((G44*$G$4))<0,0,((G44*$G$4)))-(((G44*$G$4)/$F$22)*$D$17),100) -> 0 | I45: =ROUND(IF(((H44*$G$4))<0,0,((H44*$G$4)))-(((H44*$G$4)/$F$22)*$D$17),100) -> 0 | J45: =ROUND(IF(((I44*$G$4))<0,0,((I44*$G$4)))-(((I44*$G$4)/$F$22)*$D$17),100) -> 0 | K45: =SUM(B45:J45) -> 4780.0974 | L45: =CONCATENATE("Warning : Exceeded Loan Amount by ","SR ",W46) -> Warning : Exceeded Loan Amount by SR 85
A46: L/C | B46: =M5 -> 0 | C46: =N5 -> 0 | D46: =O5 -> 0 | E46: =P5 -> 0 | F46: =Q5 -> 0 | G46: =R5 -> 0 | H46: =S5 -> 0 | I46: =T5 -> 0 | K46: =SUM(B46:J46) -> 0 | W46: =ROUND((F22-(K45+K46+K47))*-1,0) -> 85
A47: Add: Evaluation Cost | B47: =IF(B46>0,((B46/F22)*D17),0) -> 0 | C47: =ROUND(((B44*$G$4)/$F$22)*$D$17,100)+ROUND(IF(C46>0,((C46/$F$22)*$D$17),0),100) -> 5.4054 | D47: =ROUND(((C44*$G$4)/$F$22)*$D$17,100)+ROUND(IF(D46>0,((D46/$F$22)*$D$17),0),100) -> 86.90526 | E47: =ROUND(((D44*$G$4)/$F$22)*$D$17,100)+ROUND(IF(E46>0,((E46/$F$22)*$D$17),0),100) -> 94.28562 | F47: =ROUND(((E44*$G$4)/$F$22)*$D$17,100)+ROUND(IF(F46>0,((F46/$F$22)*$D$17),0),100) -> 118.51632 | G47: =ROUND(((F44*$G$4)/$F$22)*$D$17,100)+ROUND(IF(G46>0,((G46/$F$22)*$D$17),0),100) -> 0 | H47: =ROUND(((G44*$G$4)/$F$22)*$D$17,100)+ROUND(IF(H46>0,((H46/$F$22)*$D$17),0),100) -> 0 | I47: =ROUND(((H44*$G$4)/$F$22)*$D$17,100)+ROUND(IF(I46>0,((I46/$F$22)*$D$17),0),100) -> 0 | J47: =ROUND(((I44*$G$4)/$F$22)*$D$17,100)+ROUND(IF(J46>0,((J46/$F$22)*$D$17),0),100) -> 0 | K47: =SUM(B47:J47) -> 305.1126
A48: Liquidity Needed by Client | B48: =ROUND(B44-B45+B47,100) -> 231 | C48: =ROUND(C44-C45+C47,100) -> 3634.6208 | D48: =ROUND(D44-D45+D47,100) -> 2754.6895 | E48: =ROUND(E44-E45+E47,100) -> 3681.9442 | F48: =ROUND(F44-F45+F47,100) -> -1738.2394 | G48: =ROUND(G44-G45+G47,100) -> 0 | H48: =ROUND(H44-H45+H47,100) -> 0 | I48: =ROUND(I44-I45+I47,100) -> 0 | J48: =ROUND(J44-J45+J47,100) -> 0 | K48: =SUM(B48:J48)-K47 -> 8258.9026
A49: Total SIDF Disbursments | B49: =C45+B46 -> 84.6846 | C49: =D45+C46 -> 1361.5157 | D49: =E45+D46 -> 1477.1414 | E49: =F45+E46 -> 1856.7557 | F49: =G45+F46 -> 0 | G49: =H45+G46 -> 0 | H49: =I45+H46 -> 0 | I49: =J45+I46 -> 0
A51: Source of Liquidity
A52: SR '000 | B52: =B29 -> 2024 | F52: =F29 -> 2025
A53: Quarter | B53: =B30 -> 1st Q | C53: =C30 -> 2nd Q | D53: =D30 -> 3rd Q | E53: =E30 -> 4th Q | F53: =F30 -> 1st Q | G53: =G30 -> 2nd Q | H53: =H30 -> 3rd Q | I53: =I30 -> 4th Q | M53: Negotiation with client: Liquidity Need with/without LC
A54: Paid in Capital | B54: =ROUND(B44*($F$23/$F$18),0) -> 60 | C54: =ROUND(C44*($F$23/$F$18),0) -> 968 | D54: =ROUND(D44*($F$23/$F$18),0) -> 1051 | E54: =ROUND(E44*($F$23/$F$18),0) -> 1321 | F54: =ROUND(F44*($F$23/$F$18),0) -> 0 | G54: =ROUND(G44*($F$23/$F$18),0) -> 0 | H54: =ROUND(H44*($F$23/$F$18),0) -> 0 | I54: =ROUND(I44*($F$23/$F$18),0) -> 0 | J54: =ROUND(J44*($F$23/$F$18),0) -> 0 | M54: LC % | O54: 0.3 | P54: 0.5 | Q54: 0.7 | R54: 1
A55: Commercial Loan | M55: Without LC prior to full reimbursment | O55: =SUMIF($B$48:$I$48,">0",$B$48:$I$48) -> 10302.255 | P55: =SUMIF($B$48:$I$48,">0",$B$48:$I$48) -> 10302.255 | Q55: =SUMIF($B$48:$I$48,">0",$B$48:$I$48) -> 10302.255 | R55: =SUMIF($B$48:$I$48,">0",$B$48:$I$48) -> 10302.255 | S55: =SUMIF($B$48:$I$48,">0",$B$48:$I$48) -> 10302.255
A56: Internally Generated Fund | M56: With LC | O56: =IF(SUMIF($B$48:$I$48,">0",$B$48:$I$48)-(O$54*$F$18)<0,0,SUMIF($B$48:$I$48,">0",$B$48:$I$48)-(O$54*$F$18)) -> 6390.5546 | P56: =IF(SUMIF($B$48:$I$48,">0",$B$48:$I$48)-(P$54*$F$18)<0,0,SUMIF($B$48:$I$48,">0",$B$48:$I$48)-(P$54*$F$18)) -> 3782.7546 | Q56: =IF(SUMIF($B$48:$I$48,">0",$B$48:$I$48)-(Q$54*$F$18)<0,0,SUMIF($B$48:$I$48,">0",$B$48:$I$48)-(Q$54*$F$18)) -> 1174.9546 | R56: =IF(SUMIF($B$48:$I$48,">0",$B$48:$I$48)-(R$54*$F$18)<0,0,SUMIF($B$48:$I$48,">0",$B$48:$I$48)-(R$54*$F$18)) -> 0 | S56: =IF(SUMIF($B$48:$I$48,">0",$B$48:$I$48)-(S$54*$F$18)<0,0,SUMIF($B$48:$I$48,">0",$B$48:$I$48)-(S$54*$F$18)) -> 10302.255
A57: Equity | M57: Liquidity Saving | O57: =O55-O56 -> 3911.7 | P57: =P55-P56 -> 6519.5 | Q57: =Q55-Q56 -> 9127.3 | R57: =R55-R56 -> 10302.255 | S57: =S55-S56 -> 0
A58: Subordinated Shareholder loan
A59: Other
A60: Other | L60: 1- This table is a comparison between reimbursement and LC to help in negotiation with the client on the liquidity benefit of LC 2- The table will not count for equity participation as the source of liquidity table (on the left) will do 3- In order for this table to be valid the implementation status table above should be completed 4- Cell# S53 is highlighted in yellow to allow using different LC percentages
A61: Other
A62: Other | B62: =B48-B54-B55-B56-B57-B58-B59-B60-B61 -> 171 | C62: =C48-C54-C55-C56-C57-C58-C59-C60-C61 -> 2666.6208 | D62: =D48-D54-D55-D56-D57-D58-D59-D60-D61 -> 1703.6895 | E62: =E48-E54-E55-E56-E57-E58-E59-E60-E61 -> 2360.9442 | F62: =F48-F54-F55-F56-F57-F58-F59-F60-F61 -> -1738.2394 | G62: =G48-G54-G55-G56-G57-G58-G59-G60-G61 -> 0 | H62: =H48-H54-H55-H56-H57-H58-H59-H60-H61 -> 0 | I62: =I48-I54-I55-I56-I57-I58-I59-I60-I61 -> 0
A63: Source of Liquidity | B63: =SUM(B54:B62) -> 231 | C63: =SUM(C54:C62) -> 3634.6208 | D63: =SUM(D54:D62) -> 2754.6895 | E63: =SUM(E54:E62) -> 3681.9442 | F63: =SUM(F54:F62) -> -1738.2394 | G63: =SUM(G54:G62) -> 0 | H63: =SUM(H54:H62) -> 0 | I63: =SUM(I54:I62) -> 0 | J63: =SUM(J54:J62) -> 0
C67: 1-Paid In Capital is automatically calculated at 25% from the submitted claims 2-The remaining sources of liquidity should be manually filled 3- Make sure the Source of Liquidity (row 62) is equal to the Liquidity needed by Client (row 47) RM/PM to make sure it's liquid assets (example: cash) not fixed assets
A77: "Attachment "A-1"
A78: Working Capital is as follows:
A79: Items | D79: First Year | E79: Financeable Cost
D80: SR '000 | E80: SR '000
A81: Raw Material | D81: ='Financial Stat.'!G11 -> 8136
A82: a. local 1 month | C82: 1 | D82: =D81*C82 -> 8136 | E82: =D81*C82/4 -> 2034
A83: b. Import 3 month | C83: =100%-C82 -> 0 | D83: =D81*C83 -> 0 | E83: =D81*C83/4 -> 0
A84: Labour | D84: ='Financial Stat.'!G12 -> 2233 | E84: =D84/4 -> 558.25
A85: Utilities | D85: ='Financial Stat.'!G13 -> 990 | E85: =D85/4 -> 247.5
A86: Maintenance | D86: ='Financial Stat.'!H14 -> 610 | E86: =D86/4 -> 152.5
A87: SG&A | D87: ='Financial Stat.'!G25+'Financial Stat.'!G26 -> 1912.995 | E87: =D87/4 -> 478.24875
A88: Total | D88: =D81+D84+D85+D86+D87 -> 13881.995 | E88: =SUM(E82:E87) -> 3470.4987
A89: Total Recommended Working Capital | E89: =ROUNDDOWN(E88,-2) -> 3400

Sheet IS
A1: Year | B1: =#REF! -> #REF! | C1: =#REF! -> #REF! | D1: =#REF! -> #REF! | E1: =#REF! -> #REF! | F1: =#REF! -> #REF! | G1: =#REF! -> #REF! | H1: =#REF! -> #REF! | I1: =#REF! -> #REF! | ... Q1: =#REF! -> #REF!
A2: Sales | B2: =#REF!*1000 -> #REF! | C2: =#REF!*1000 -> #REF! | D2: =#REF!*1000 -> #REF! | E2: =#REF!*1000 -> #REF! | F2: =#REF!*1000 -> #REF! | G2: =#REF!*1000 -> #REF! | H2: =#REF!*1000 -> #REF! | I2: =#REF!*1000 -> #REF! | ... Q2: =#REF!*1000 -> #REF!
A3: Rawmat | B3: =#REF!*1000 -> #REF! | C3: =#REF!*1000 -> #REF! | D3: =#REF!*1000 -> #REF! | E3: =#REF!*1000 -> #REF! | F3: =#REF!*1000 -> #REF! | G3: =#REF!*1000 -> #REF! | H3: =#REF!*1000 -> #REF! | I3: =#REF!*1000 -> #REF! | ... Q3: =#REF!*1000 -> #REF!
A4: Dirlab | B4: =#REF!*1000 -> #REF! | C4: =#REF!*1000 -> #REF! | D4: =#REF!*1000 -> #REF! | E4: =#REF!*1000 -> #REF! | F4: =#REF!*1000 -> #REF! | G4: =#REF!*1000 -> #REF! | H4: =#REF!*1000 -> #REF! | I4: =#REF!*1000 -> #REF! | ... Q4: =#REF!*1000 -> #REF!
A5: Utils | B5: =#REF!*1000 -> #REF! | C5: =#REF!*1000 -> #REF! | D5: =#REF!*1000 -> #REF! | E5: =#REF!*1000 -> #REF! | F5: =#REF!*1000 -> #REF! | G5: =#REF!*1000 -> #REF! | H5: =#REF!*1000 -> #REF! | I5: =#REF!*1000 -> #REF! | ... Q5: =#REF!*1000 -> #REF!
A6: Maint | B6: =#REF!*1000 -> #REF! | C6: =#REF!*1000 -> #REF! | D6: =#REF!*1000 -> #REF! | E6: =#REF!*1000 -> #REF! | F6: =#REF!*1000 -> #REF! | G6: =#REF!*1000 -> #REF! | H6: =#REF!*1000 -> #REF! | I6: =#REF!*1000 -> #REF! | ... Q6: =#REF!*1000 -> #REF!
A7: Deprec | B7: =#REF!*1000 -> #REF! | C7: =#REF!*1000 -> #REF! | D7: =#REF!*1000 -> #REF! | E7: =#REF!*1000 -> #REF! | F7: =#REF!*1000 -> #REF! | G7: =#REF!*1000 -> #REF! | H7: =#REF!*1000 -> #REF! | I7: =#REF!*1000 -> #REF! | ... Q7: =#REF!*1000 -> #REF!
A8: Amort | B8: =#REF!*1000 -> #REF! | C8: =#REF!*1000 -> #REF! | D8: =#REF!*1000 -> #REF! | E8: =#REF!*1000 -> #REF! | F8: =#REF!*1000 -> #REF! | G8: =#REF!*1000 -> #REF! | H8: =#REF!*1000 -> #REF! | I8: =#REF!*1000 -> #REF! | ... Q8: =#REF!*1000 -> #REF!
A9: Othdirexp | B9: =#REF!*1000 -> #REF! | C9: =#REF!*1000 -> #REF! | D9: =#REF!*1000 -> #REF! | E9: =#REF!*1000 -> #REF! | F9: =#REF!*1000 -> #REF! | G9: =#REF!*1000 -> #REF! | H9: =#REF!*1000 -> #REF! | I9: =#REF!*1000 -> #REF! | ... Q9: =#REF!*1000 -> #REF!
A10: Cgs | B10: =#REF!*1000 -> #REF! | C10: =#REF!*1000 -> #REF! | D10: =#REF!*1000 -> #REF! | E10: =#REF!*1000 -> #REF! | F10: =#REF!*1000 -> #REF! | G10: =#REF!*1000 -> #REF! | H10: =#REF!*1000 -> #REF! | I10: =#REF!*1000 -> #REF! | ... Q10: =#REF!*1000 -> #REF!
A11: Grossmar | B11: =#REF!*1000 -> #REF! | C11: =#REF!*1000 -> #REF! | D11: =#REF!*1000 -> #REF! | E11: =#REF!*1000 -> #REF! | F11: =#REF!*1000 -> #REF! | G11: =#REF!*1000 -> #REF! | H11: =#REF!*1000 -> #REF! | I11: =#REF!*1000 -> #REF! | ... Q11: =#REF!*1000 -> #REF!
A12: Salesad | B12: =#REF!*1000 -> #REF! | C12: =#REF!*1000 -> #REF! | D12: =#REF!*1000 -> #REF! | E12: =#REF!*1000 -> #REF! | F12: =#REF!*1000 -> #REF! | G12: =#REF!*1000 -> #REF! | H12: =#REF!*1000 -> #REF! | I12: =#REF!*1000 -> #REF! | ... Q12: =#REF!*1000 -> #REF!
A13: Salar | B13: =#REF!*1000 -> #REF! | C13: =#REF!*1000 -> #REF! | D13: =#REF!*1000 -> #REF! | E13: =#REF!*1000 -> #REF! | F13: =#REF!*1000 -> #REF! | G13: =#REF!*1000 -> #REF! | H13: =#REF!*1000 -> #REF! | I13: =#REF!*1000 -> #REF! | ... Q13: =#REF!*1000 -> #REF!
... A22: Retear | B22: =#REF!*1000 -> #REF! | C22: =#REF!*1000 -> #REF! | D22: =#REF!*1000 -> #REF! | E22: =#REF!*1000 -> #REF! | F22: =#REF!*1000 -> #REF! | G22: =#REF!*1000 -> #REF! | H22: =#REF!*1000 -> #REF! | I22: =#REF!*1000 -> #REF! | ... Q22: =#REF!*1000 -> #REF!

Sheet BSA
A1: Year | B1: =#REF! -> #REF! | C1: =#REF! -> #REF! | D1: =#REF! -> #REF! | E1: =#REF! -> #REF! | F1: =#REF! -> #REF! | G1: =#REF! -> #REF! | H1: =#REF! -> #REF! | I1: =#REF! -> #REF! | ... Q1: =#REF! -> #REF!
A2: Factorycash | B2: =#REF!*1000 -> #REF! | C2: =#REF!*1000 -> #REF! | D2: =#REF!*1000 -> #REF! | E2: =#REF!*1000 -> #REF! | F2: =#REF!*1000 -> #REF! | G2: =#REF!*1000 -> #REF! | H2: =#REF!*1000 -> #REF! | I2: =#REF!*1000 -> #REF! | ... Q2: =#REF!*1000 -> #REF!
A3: Accntsrec | B3: =#REF!*1000 -> #REF! | C3: =#REF!*1000 -> #REF! | D3: =#REF!*1000 -> #REF! | E3: =#REF!*1000 -> #REF! | F3: =#REF!*1000 -> #REF! | G3: =#REF!*1000 -> #REF! | H3: =#REF!*1000 -> #REF! | I3: =#REF!*1000 -> #REF! | ... Q3: =#REF!*1000 -> #REF!
A4: Inventory | B4: =#REF!*1000 -> #REF! | C4: =#REF!*1000 -> #REF! | D4: =#REF!*1000 -> #REF! | E4: =#REF!*1000 -> #REF! | F4: =#REF!*1000 -> #REF! | G4: =#REF!*1000 -> #REF! | H4: =#REF!*1000 -> #REF! | I4: =#REF!*1000 -> #REF! | ... Q4: =#REF!*1000 -> #REF!
A5: Lcmargins | B5: =#REF!*1000 -> #REF! | C5: =#REF!*1000 -> #REF! | D5: =#REF!*1000 -> #REF! | E5: =#REF!*1000 -> #REF! | F5: =#REF!*1000 -> #REF! | G5: =#REF!*1000 -> #REF! | H5: =#REF!*1000 -> #REF! | I5: =#REF!*1000 -> #REF! | ... Q5: =#REF!*1000 -> #REF!
A6: Prepaid | B6: =#REF!*1000 -> #REF! | C6: =#REF!*1000 -> #REF! | D6: =#REF!*1000 -> #REF! | E6: =#REF!*1000 -> #REF! | F6: =#REF!*1000 -> #REF! | G6: =#REF!*1000 -> #REF! | H6: =#REF!*1000 -> #REF! | I6: =#REF!*1000 -> #REF! | ... Q6: =#REF!*1000 -> #REF!
A7: Other1 | B7: =#REF!*1000 -> #REF! | C7: =#REF!*1000 -> #REF! | D7: =#REF!*1000 -> #REF! | E7: =#REF!*1000 -> #REF! | F7: =#REF!*1000 -> #REF! | G7: =#REF!*1000 -> #REF! | H7: =#REF!*1000 -> #REF! | I7: =#REF!*1000 -> #REF! | ... Q7: =#REF!*1000 -> #REF!
A8: Currentassets | B8: =#REF!*1000 -> #REF! | C8: =#REF!*1000 -> #REF! | D8: =#REF!*1000 -> #REF! | E8: =#REF!*1000 -> #REF! | F8: =#REF!*1000 -> #REF! | G8: =#REF!*1000 -> #REF! | H8: =#REF!*1000 -> #REF! | I8: =#REF!*1000 -> #REF! | ... Q8: =#REF!*1000 -> #REF!
A9: Land | B9: =#REF!*1000 -> #REF! | C9: =#REF!*1000 -> #REF! | D9: =#REF!*1000 -> #REF! | E9: =#REF!*1000 -> #REF! | F9: =#REF!*1000 -> #REF! | G9: =#REF!*1000 -> #REF! | H9: =#REF!*1000 -> #REF! | I9: =#REF!*1000 -> #REF! | ... Q9: =#REF!*1000 -> #REF!
A10: Buildings | B10: =#REF!*1000 -> #REF! | C10: =#REF!*1000 -> #REF! | D10: =#REF!*1000 -> #REF! | E10: =#REF!*1000 -> #REF! | F10: =#REF!*1000 -> #REF! | G10: =#REF!*1000 -> #REF! | H10: =#REF!*1000 -> #REF! | I10: =#REF!*1000 -> #REF! | ... Q10: =#REF!*1000 -> #REF!
A11: Machinery | B11: =#REF!*1000 -> #REF! | C11: =#REF!*1000 -> #REF! | D11: =#REF!*1000 -> #REF! | E11: =#REF!*1000 -> #REF! | F11: =#REF!*1000 -> #REF! | G11: =#REF!*1000 -> #REF! | H11: =#REF!*1000 -> #REF! | I11: =#REF!*1000 -> #REF! | ... Q11: =#REF!*1000 -> #REF!
A12: Furniture | B12: =#REF!*1000 -> #REF! | C12: =#REF!*1000 -> #REF! | D12: =#REF!*1000 -> #REF! | E12: =#REF!*1000 -> #REF! | F12: =#REF!*1000 -> #REF! | G12: =#REF!*1000 -> #REF! | H12: =#REF!*1000 -> #REF! | I12: =#REF!*1000 -> #REF! | ... Q12: =#REF!*1000 -> #REF!
A13: Vehicles | B13: =#REF!*1000 -> #REF! | C13: =#REF!*1000 -> #REF! | D13: =#REF!*1000 -> #REF! | E13: =#REF!*1000 -> #REF! | F13: =#REF!*1000 -> #REF! | G13: =#REF!*1000 -> #REF! | H13: =#REF!*1000 -> #REF! | I13: =#REF!*1000 -> #REF! | ... Q13: =#REF!*1000 -> #REF!
... A26: Totassets | B26: =#REF!*1000 -> #REF! | C26: =#REF!*1000 -> #REF! | D26: =#REF!*1000 -> #REF! | E26: =#REF!*1000 -> #REF! | F26: =#REF!*1000 -> #REF! | G26: =#REF!*1000 -> #REF! | H26: =#REF!*1000 -> #REF! | I26: =#REF!*1000 -> #REF! | ... Q26: =#REF!*1000 -> #REF!

Sheet BSL
A1: Year | B1: =#REF! -> #REF! | C1: =#REF! -> #REF! | D1: =#REF! -> #REF! | E1: =#REF! -> #REF! | F1: =#REF! -> #REF! | G1: =#REF! -> #REF! | H1: =#REF! -> #REF! | I1: =#REF! -> #REF! | ... Q1: =#REF! -> #REF!
A2: Acpay | B2: =#REF!*1000 -> #REF! | C2: =#REF!*1000 -> #REF! | D2: =#REF!*1000 -> #REF! | E2: =#REF!*1000 -> #REF! | F2: =#REF!*1000 -> #REF! | G2: =#REF!*1000 -> #REF! | H2: =#REF!*1000 -> #REF! | I2: =#REF!*1000 -> #REF! | ... Q2: =#REF!*1000 -> #REF!
A3: Std | B3: =#REF!*1000 -> #REF! | C3: =#REF!*1000 -> #REF! | D3: =#REF!*1000 -> #REF! | E3: =#REF!*1000 -> #REF! | F3: =#REF!*1000 -> #REF! | G3: =#REF!*1000 -> #REF! | H3: =#REF!*1000 -> #REF! | I3: =#REF!*1000 -> #REF! | ... Q3: =#REF!*1000 -> #REF!
A4: Accruals | B4: =#REF!*1000 -> #REF! | C4: =#REF!*1000 -> #REF! | D4: =#REF!*1000 -> #REF! | E4: =#REF!*1000 -> #REF! | F4: =#REF!*1000 -> #REF! | G4: =#REF!*1000 -> #REF! | H4: =#REF!*1000 -> #REF! | I4: =#REF!*1000 -> #REF! | ... Q4: =#REF!*1000 -> #REF!
A5: Cplsidf | B5: =#REF!*1000 -> #REF! | C5: =#REF!*1000 -> #REF! | D5: =#REF!*1000 -> #REF! | E5: =#REF!*1000 -> #REF! | F5: =#REF!*1000 -> #REF! | G5: =#REF!*1000 -> #REF! | H5: =#REF!*1000 -> #REF! | I5: =#REF!*1000 -> #REF! | ... Q5: =#REF!*1000 -> #REF!
A6: Cplbank | B6: =#REF!*1000 -> #REF! | C6: =#REF!*1000 -> #REF! | D6: =#REF!*1000 -> #REF! | E6: =#REF!*1000 -> #REF! | F6: =#REF!*1000 -> #REF! | G6: =#REF!*1000 -> #REF! | H6: =#REF!*1000 -> #REF! | I6: =#REF!*1000 -> #REF! | ... Q6: =#REF!*1000 -> #REF!
A7: Cplother | B7: =#REF!*1000 -> #REF! | C7: =#REF!*1000 -> #REF! | D7: =#REF!*1000 -> #REF! | E7: =#REF!*1000 -> #REF! | F7: =#REF!*1000 -> #REF! | G7: =#REF!*1000 -> #REF! | H7: =#REF!*1000 -> #REF! | I7: =#REF!*1000 -> #REF! | ... Q7: =#REF!*1000 -> #REF!
A8: Other1 | B8: =#REF!*1000 -> #REF! | C8: =#REF!*1000 -> #REF! | D8: =#REF!*1000 -> #REF! | E8: =#REF!*1000 -> #REF! | F8: =#REF!*1000 -> #REF! | G8: =#REF!*1000 -> #REF! | H8: =#REF!*1000 -> #REF! | I8: =#REF!*1000 -> #REF! | ... Q8: =#REF!*1000 -> #REF!
A9: Other2 | B9: =#REF!*1000 -> #REF! | C9: =#REF!*1000 -> #REF! | D9: =#REF!*1000 -> #REF! | E9: =#REF!*1000 -> #REF! | F9: =#REF!*1000 -> #REF! | G9: =#REF!*1000 -> #REF! | H9: =#REF!*1000 -> #REF! | I9: =#REF!*1000 -> #REF! | ... Q9: =#REF!*1000 -> #REF!
A10: Currentliab | B10: =#REF!*1000 -> #REF! | C10: =#REF!*1000 -> #REF! | D10: =#REF!*1000 -> #REF! | E10: =#REF!*1000 -> #REF! | F10: =#REF!*1000 -> #REF! | G10: =#REF!*1000 -> #REF! | H10: =#REF!*1000 -> #REF! | I10: =#REF!*1000 -> #REF! | ... Q10: =#REF!*1000 -> #REF!
A11: Ltdsidf | B11: =#REF!*1000 -> #REF! | C11: =#REF!*1000 -> #REF! | D11: =#REF!*1000 -> #REF! | E11: =#REF!*1000 -> #REF! | F11: =#REF!*1000 -> #REF! | G11: =#REF!*1000 -> #REF! | H11: =#REF!*1000 -> #REF! | I11: =#REF!*1000 -> #REF! | ... Q11: =#REF!*1000 -> #REF!
A12: Ltdbank | B12: =#REF!*1000 -> #REF! | C12: =#REF!*1000 -> #REF! | D12: =#REF!*1000 -> #REF! | E12: =#REF!*1000 -> #REF! | F12: =#REF!*1000 -> #REF! | G12: =#REF!*1000 -> #REF! | H12: =#REF!*1000 -> #REF! | I12: =#REF!*1000 -> #REF! | ... Q12: =#REF!*1000 -> #REF!
A13: Ltdother | B13: =#REF!*1000 -> #REF! | C13: =#REF!*1000 -> #REF! | D13: =#REF!*1000 -> #REF! | E13: =#REF!*1000 -> #REF! | F13: =#REF!*1000 -> #REF! | G13: =#REF!*1000 -> #REF! | H13: =#REF!*1000 -> #REF! | I13: =#REF!*1000 -> #REF! | ... Q13: =#REF!*1000 -> #REF!
... A23: Totliabeq | B23: =#REF!*1000 -> #REF! | C23: =#REF!*1000 -> #REF! | D23: =#REF!*1000 -> #REF! | E23: =#REF!*1000 -> #REF! | F23: =#REF!*1000 -> #REF! | G23: =#REF!*1000 -> #REF! | H23: =#REF!*1000 -> #REF! | I23: =#REF!*1000 -> #REF! | ... Q23: =#REF!*1000 -> #REF!

Sheet SA
A1: =SUBSTITUTE(TRIM(#REF!)," ","") -> #REF! | B1: =#REF! -> #REF! | C1: =#REF! -> #REF!
A2: =SUBSTITUTE(TRIM(#REF!)," ","") -> #REF! | B2: =#REF! -> #REF! | C2: =#REF! -> #REF!
A3: =SUBSTITUTE(TRIM(#REF!)," ","") -> #REF! | B3: =#REF! -> #REF! | C3: =#REF! -> #REF!
A4: =SUBSTITUTE(TRIM(#REF!)," ","") -> #REF! | B4: =#REF! -> #REF! | C4: =#REF! -> #REF!

Sheet NPV
A1: =#REF! -> #REF! | B1: =#REF!*1000 -> #REF! | C1: =#REF!*1000 -> #REF!
A2: =#REF! -> #REF! | B2: =#REF!*1000 -> #REF! | C2: =#REF!*1000 -> #REF!
A3: =#REF! -> #REF! | B3: =#REF!*1000 -> #REF! | C3: =#REF!*1000 -> #REF!
A4: =#REF! -> #REF! | B4: =#REF!*1000 -> #REF! | C4: =#REF!*1000 -> #REF!

Sheet IRR
A1: =#REF! -> #REF! | B1: =#REF! -> #REF! | C1: =#REF! -> #REF! | D1: =#REF! -> #REF! | E1: =#REF! -> #REF! | F1: =#REF! -> #REF! | G1: =#REF! -> #REF! | H1: =#REF! -> #REF! | ... Q1: =#REF! -> #REF!
A2: =SUBSTITUTE(#REF!," ","") -> #REF! | B2: =#REF!*1000 -> #REF! | C2: =#REF!*1000 -> #REF! | D2: =#REF!*1000 -> #REF! | E2: =#REF!*1000 -> #REF! | F2: =#REF!*1000 -> #REF! | G2: =#REF!*1000 -> #REF! | H2: =#REF!*1000 -> #REF! | I2: =#REF!*1000 -> #REF! | ... Q2: =#REF!*1000 -> #REF!
A3: =SUBSTITUTE(#REF!," ","") -> #REF! | B3: =#REF!*1000 -> #REF! | C3: =#REF!*1000 -> #REF! | D3: =#REF!*1000 -> #REF! | E3: =#REF!*1000 -> #REF! | F3: =#REF!*1000 -> #REF! | G3: =#REF!*1000 -> #REF! | H3: =#REF!*1000 -> #REF! | I3: =#REF!*1000 -> #REF! | ... Q3: =#REF!*1000 -> #REF!
A4: =SUBSTITUTE(#REF!," ","") -> #REF! | B4: =#REF!*1000 -> #REF! | C4: =#REF!*1000 -> #REF! | D4: =#REF!*1000 -> #REF! | E4: =#REF!*1000 -> #REF! | F4: =#REF!*1000 -> #REF! | G4: =#REF!*1000 -> #REF! | H4: =#REF!*1000 -> #REF! | I4: =#REF!*1000 -> #REF! | ... Q4: =#REF!*1000 -> #REF!
A5: =SUBSTITUTE(#REF!," ","") -> #REF! | B5: =#REF!*1000 -> #REF! | C5: =#REF!*1000 -> #REF! | D5: =#REF!*1000 -> #REF! | E5: =#REF!*1000 -> #REF! | F5: =#REF!*1000 -> #REF! | G5: =#REF!*1000 -> #REF! | H5: =#REF!*1000 -> #REF! | I5: =#REF!*1000 -> #REF! | ... Q5: =#REF!*1000 -> #REF!
A6: =SUBSTITUTE(#REF!," ","") -> #REF! | B6: =#REF!*1000 -> #REF! | C6: =#REF!*1000 -> #REF! | D6: =#REF!*1000 -> #REF! | E6: =#REF!*1000 -> #REF! | F6: =#REF!*1000 -> #REF! | G6: =#REF!*1000 -> #REF! | H6: =#REF!*1000 -> #REF! | I6: =#REF!*1000 -> #REF! | ... Q6: =#REF!*1000 -> #REF!
A7: =SUBSTITUTE(#REF!," ","") -> #REF! | B7: =#REF!*1000 -> #REF! | C7: =#REF!*1000 -> #REF! | D7: =#REF!*1000 -> #REF! | E7: =#REF!*1000 -> #REF! | F7: =#REF!*1000 -> #REF! | G7: =#REF!*1000 -> #REF! | H7: =#REF!*1000 -> #REF! | I7: =#REF!*1000 -> #REF! | ... Q7: =#REF!*1000 -> #REF!
A8: =SUBSTITUTE(#REF!," ","") -> #REF! | B8: =#REF!*1000 -> #REF! | C8: =#REF!*1000 -> #REF! | D8: =#REF!*1000 -> #REF! | E8: =#REF!*1000 -> #REF! | F8: =#REF!*1000 -> #REF! | G8: =#REF!*1000 -> #REF! | H8: =#REF!*1000 -> #REF! | I8: =#REF!*1000 -> #REF! | ... Q8: =#REF!*1000 -> #REF!
A9: =SUBSTITUTE(#REF!," ","") -> #REF! | B9: =#REF!*1000 -> #REF! | C9: =#REF!*1000 -> #REF! | D9: =#REF!*1000 -> #REF! | E9: =#REF!*1000 -> #REF! | F9: =#REF!*1000 -> #REF! | G9: =#REF!*1000 -> #REF! | H9: =#REF!*1000 -> #REF! | I9: =#REF!*1000 -> #REF! | ... Q9: =#REF!*1000 -> #REF!
A10: =SUBSTITUTE(#REF!," ","") -> #REF! | B10: =#REF!*1000 -> #REF! | C10: =#REF!*1000 -> #REF! | D10: =#REF!*1000 -> #REF! | E10: =#REF!*1000 -> #REF! | F10: =#REF!*1000 -> #REF! | G10: =#REF!*1000 -> #REF! | H10: =#REF!*1000 -> #REF! | I10: =#REF!*1000 -> #REF! | ... Q10: =#REF!*1000 -> #REF!
A11: =SUBSTITUTE(#REF!," ","") -> #REF! | B11: =#REF!*1000 -> #REF! | C11: =#REF!*1000 -> #REF! | D11: =#REF!*1000 -> #REF! | E11: =#REF!*1000 -> #REF! | F11: =#REF!*1000 -> #REF! | G11: =#REF!*1000 -> #REF! | H11: =#REF!*1000 -> #REF! | I11: =#REF!*1000 -> #REF! | ... Q11: =#REF!*1000 -> #REF!
A12: =SUBSTITUTE(#REF!," ","") -> #REF! | B12: =#REF!*1000 -> #REF! | C12: =#REF!*1000 -> #REF! | D12: =#REF!*1000 -> #REF! | E12: =#REF!*1000 -> #REF! | F12: =#REF!*1000 -> #REF! | G12: =#REF!*1000 -> #REF! | H12: =#REF!*1000 -> #REF! | I12: =#REF!*1000 -> #REF! | ... Q12: =#REF!*1000 -> #REF!
A13: =SUBSTITUTE(#REF!," ","") -> #REF! | B13: =#REF!*1000 -> #REF! | C13: =#REF!*1000 -> #REF! | D13: =#REF!*1000 -> #REF! | E13: =#REF!*1000 -> #REF! | F13: =#REF!*1000 -> #REF! | G13: =#REF!*1000 -> #REF! | H13: =#REF!*1000 -> #REF! | I13: =#REF!*1000 -> #REF! | ... Q13: =#REF!*1000 -> #REF!

Sheet LIRR
A1: =#REF! -> #REF! | B1: =#REF! -> #REF! | C1: =#REF! -> #REF!
A2: =#REF! -> #REF! | B2: =#REF! -> #REF! | C2: =#REF! -> #REF!

Sheet ULIRR
A1: =#REF! -> #REF! | B1: =#REF! -> #REF! | C1: =#REF! -> #REF!
A2: =#REF! -> #REF! | B2: =#REF! -> #REF! | C2: =#REF! -> #REF!

Sheet SAC
A1: =#REF! -> #REF! | B1: =#REF! -> #REF! | C1: =#REF! -> #REF! | D1: =#REF! -> #REF! | E1: =#REF! -> #REF! | F1: =#REF! -> #REF! | G1: =#REF! -> #REF! | H1: =#REF! -> #REF! | ... Q1: =#REF! -> #REF!
A2: =SUBSTITUTE(#REF!," ","") -> #REF! | B2: =#REF! -> #REF! | C2: =#REF! -> #REF! | D2: =#REF! -> #REF! | E2: =#REF! -> #REF! | F2: =#REF! -> #REF! | G2: =#REF! -> #REF! | H2: =#REF! -> #REF! | I2: =#REF! -> #REF! | ... Q2: =#REF! -> #REF!
A3: =SUBSTITUTE(#REF!," ","") -> #REF! | B3: =#REF! -> #REF! | C3: =#REF! -> #REF! | D3: =#REF! -> #REF! | E3: =#REF! -> #REF! | F3: =#REF! -> #REF! | G3: =#REF! -> #REF! | H3: =#REF! -> #REF! | I3: =#REF! -> #REF! | ... Q3: =#REF! -> #REF!
A4: =SUBSTITUTE(#REF!," ","") -> #REF! | B4: =#REF! -> #REF! | C4: =#REF! -> #REF! | D4: =#REF! -> #REF! | E4: =#REF! -> #REF! | F4: =#REF! -> #REF! | G4: =#REF! -> #REF! | H4: =#REF! -> #REF! | I4: =#REF! -> #REF! | ... Q4: =#REF! -> #REF!
A5: =SUBSTITUTE(#REF!," ","") -> #REF! | B5: =#REF! -> #REF! | C5: =#REF! -> #REF! | D5: =#REF! -> #REF! | E5: =#REF! -> #REF! | F5: =#REF! -> #REF! | G5: =#REF! -> #REF! | H5: =#REF! -> #REF! | I5: =#REF! -> #REF! | ... Q5: =#REF! -> #REF!
A6: =SUBSTITUTE(#REF!," ","") -> #REF! | B6: =#REF! -> #REF! | C6: =#REF! -> #REF! | D6: =#REF! -> #REF! | E6: =#REF! -> #REF! | F6: =#REF! -> #REF! | G6: =#REF! -> #REF! | H6: =#REF! -> #REF! | I6: =#REF! -> #REF! | ... Q6: =#REF! -> #REF!
A7: =SUBSTITUTE(#REF!," ","") -> #REF! | B7: =#REF! -> #REF! | C7: =#REF! -> #REF! | D7: =#REF! -> #REF! | E7: =#REF! -> #REF! | F7: =#REF! -> #REF! | G7: =#REF! -> #REF! | H7: =#REF! -> #REF! | I7: =#REF! -> #REF! | ... Q7: =#REF! -> #REF!
A8: =SUBSTITUTE(#REF!," ","") -> #REF! | B8: =#REF! -> #REF! | C8: =#REF! -> #REF! | D8: =#REF! -> #REF! | E8: =#REF! -> #REF! | F8: =#REF! -> #REF! | G8: =#REF! -> #REF! | H8: =#REF! -> #REF! | I8: =#REF! -> #REF! | ... Q8: =#REF! -> #REF!
A9: =SUBSTITUTE(#REF!," ","") -> #REF! | B9: =#REF! -> #REF! | C9: =#REF! -> #REF! | D9: =#REF! -> #REF! | E9: =#REF! -> #REF! | F9: =#REF! -> #REF! | G9: =#REF! -> #REF! | H9: =#REF! -> #REF! | I9: =#REF! -> #REF! | ... Q9: =#REF! -> #REF!
A10: =SUBSTITUTE(#REF!," ","") -> #REF! | B10: =#REF! -> #REF! | C10: =#REF! -> #REF! | D10: =#REF! -> #REF! | E10: =#REF! -> #REF! | F10: =#REF! -> #REF! | G10: =#REF! -> #REF! | H10: =#REF! -> #REF! | I10: =#REF! -> #REF! | ... Q10: =#REF! -> #REF!
A11: =SUBSTITUTE(#REF!," ","") -> #REF! | B11: =#REF! -> #REF! | C11: =#REF! -> #REF! | D11: =#REF! -> #REF! | E11: =#REF! -> #REF! | F11: =#REF! -> #REF! | G11: =#REF! -> #REF! | H11: =#REF! -> #REF! | I11: =#REF! -> #REF! | ... Q11: =#REF! -> #REF!
A12: =SUBSTITUTE(#REF!," ","") -> #REF! | B12: =#REF! -> #REF! | C12: =#REF! -> #REF! | D12: =#REF! -> #REF! | E12: =#REF! -> #REF! | F12: =#REF! -> #REF! | G12: =#REF! -> #REF! | H12: =#REF! -> #REF! | I12: =#REF! -> #REF! | ... Q12: =#REF! -> #REF!
A13: =SUBSTITUTE(#REF!," ","") -> #REF! | B13: =#REF! -> #REF! | C13: =#REF! -> #REF! | D13: =#REF! -> #REF! | E13: =#REF! -> #REF! | F13: =#REF! -> #REF! | G13: =#REF! -> #REF! | H13: =#REF! -> #REF! | I13: =#REF! -> #REF! | ... Q13: =#REF! -> #REF!
... A26: =SUBSTITUTE(#REF!," ","") -> #REF! | B26: =#REF! -> #REF! | C26: =#REF! -> #REF! | D26: =#REF! -> #REF! | E26: =#REF! -> #REF! | F26: =#REF! -> #REF! | G26: =#REF! -> #REF! | H26: =#REF! -> #REF! | I26: =#REF! -> #REF! | ... Q26: =#REF! -> #REF!

Sheet ATT_D
D5: Attachment - D
B7: "ECONOMIC EVALUATION"

Sheet ATT_C
D5: Attachment - C
B7: "ASSUMPTIONS TO PROJECTION"

Sheet ATT_B
D5: Attachment - B
B7: "FINANCIAL STATEMENTS PROJECTIONS"

Sheet WC
A1: =#REF! -> #REF! | B1: =#REF!*1000 -> #REF! | C1: =#REF!*1000 -> #REF! | F1: =(C2*12)/B1 -> #REF!
A2: =TRIM(#REF!) -> #REF! | B2: =#REF!*1000 -> #REF! | C2: =#REF!*1000 -> #REF! | F2: =(C3*4)/B1 -> #REF!
A3: =TRIM(#REF!) -> #REF! | B3: =#REF!*1000 -> #REF! | C3: =#REF!*1000 -> #REF!
A4: =#REF! -> #REF! | B4: =#REF!*1000 -> #REF! | C4: =#REF!*1000 -> #REF!
A5: =#REF! -> #REF! | B5: =#REF!*1000 -> #REF! | C5: =#REF!*1000 -> #REF!
A6: =#REF! -> #REF! | B6: =#REF!*1000 -> #REF! | C6: =#REF!*1000 -> #REF!
A7: =#REF! -> #REF! | B7: =#REF!*1000 -> #REF! | C7: =#REF!*1000 -> #REF!
A8: =#REF! -> #REF! | B8: =#REF!*1000 -> #REF! | C8: =#REF!*1000 -> #REF!

Sheet AA
A1: =#REF! -> #REF! | B1: =#REF!*1000 -> #REF! | C1: =#REF!*1000 -> #REF! | D1: =#REF!*1000 -> #REF! | E1: LA
A2: =#REF! -> #REF! | B2: =#REF!*1000 -> #REF! | C2: =#REF!*1000 -> #REF! | D2: =#REF!*1000 -> #REF! | E2: BC
A3: =#REF! -> #REF! | B3: =#REF!*1000 -> #REF! | C3: =#REF!*1000 -> #REF! | D3: =#REF!*1000 -> #REF! | E3: SA
A4: =#REF! -> #REF! | B4: =#REF!*1000 -> #REF! | C4: =#REF!*1000 -> #REF! | D4: =#REF!*1000 -> #REF! | E4: ME
A5: =#REF! -> #REF! | B5: =#REF!*1000 -> #REF! | C5: =#REF!*1000 -> #REF! | D5: =#REF!*1000 -> #REF! | E5: VE
A6: =#REF! -> #REF! | B6: =#REF!*1000 -> #REF! | C6: =#REF!*1000 -> #REF! | D6: =#REF!*1000 -> #REF! | E6: FU
A7: =#REF! -> #REF! | B7: =#REF!*1000 -> #REF! | C7: =#REF!*1000 -> #REF! | D7: =#REF!*1000 -> #REF! | E7: WC
A8: =#REF! -> #REF! | B8: =#REF!*1000 -> #REF! | C8: =#REF!*1000 -> #REF! | D8: =#REF!*1000 -> #REF! | E8: PR
A9: =#REF! -> #REF! | B9: =#REF!*1000 -> #REF! | C9: =#REF!*1000 -> #REF! | D9: =#REF!*1000 -> #REF! | E9: CO
A10: =#REF! -> #REF! | B10: =#REF!*1000 -> #REF! | C10: =#REF!*1000 -> #REF! | D10: =#REF!*1000 -> #REF! | E10: EC
A11: =#REF! -> #REF! | B11: =#REF!*1000 -> #REF! | C11: =#REF!*1000 -> #REF! | D11: =#REF!*1000 -> #REF! | E11: PC

Sheet SF
A1: =#REF! -> #REF! | B1: =#REF!*1000 -> #REF! | C1: =#REF! -> #REF! | D1: SIDF
A2: =#REF! -> #REF! | B2: =#REF!*1000 -> #REF! | C2: =#REF! -> #REF! | D2: PIC
A3: =#REF! -> #REF! | B3: =#REF!*1000 -> #REF! | C3: =#REF! -> #REF! | D3: CL
A4: =#REF! -> #REF! | B4: =#REF!*1000 -> #REF! | C4: =#REF! -> #REF! | D4: IGF

Sheet Attachment E
B2: Attachement E
B6: Application#
B7: Project Name
B8: Sector
B9: Products
B13: Loan amount (SR’000”) | C13: =#REF! -> #REF!
B14: Project cost (SR’000”) | C14: =#REF! -> #REF!
B15: Labour (SR’000”) | C15: =#REF! -> #REF!
B16: Gross Added Value / Capital Cost | C16: =#REF! -> #REF!
B17: Total sales (maximum year) (SR’000”) | C17: =#REF! -> #REF!
B18: Added value- Year 10 (SR’000”) | C18: =#REF! -> #REF!
B19: Unlevered IRR | C19: =#REF! -> #REF!

Sheet Summ.
B1: Historical | G1: PROJECTIONS
B2: =#REF! -> #REF! | C2: =#REF! -> #REF! | D2: =#REF! -> #REF! | E2: =#REF! -> #REF! | F2: =#REF! -> #REF! | G2: =#REF! -> #REF! | H2: =#REF! -> #REF! | I2: =#REF! -> #REF! | ... P2: =#REF! -> #REF!
A3: Current Assets | B3: =#REF! -> #REF! | C3: =#REF! -> #REF! | D3: =#REF! -> #REF! | E3: =#REF! -> #REF! | F3: =#REF! -> #REF! | G3: =#REF! -> #REF! | H3: =#REF! -> #REF! | I3: =#REF! -> #REF! | ... P3: =#REF! -> #REF!
A4: Current Liabilities | B4: =#REF! -> #REF! | C4: =#REF! -> #REF! | D4: =#REF! -> #REF! | E4: =#REF! -> #REF! | F4: =#REF! -> #REF! | G4: =#REF! -> #REF! | H4: =#REF! -> #REF! | I4: =#REF! -> #REF! | ... P4: =#REF! -> #REF!
A5: Working Capital | B5: =B3-B4 -> #REF! | C5: =C3-C4 -> #REF! | D5: =D3-D4 -> #REF! | E5: =E3-E4 -> #REF! | F5: =F3-F4 -> #REF! | G5: =G3-G4 -> #REF! | H5: =H3-H4 -> #REF! | I5: =I3-I4 -> #REF! | ... P5: =P3-P4 -> #REF!
A6: Net Fixed Assets | B6: =#REF! -> #REF! | C6: =#REF! -> #REF! | D6: =#REF! -> #REF! | E6: =#REF! -> #REF! | F6: =#REF! -> #REF! | G6: =#REF! -> #REF! | H6: =#REF! -> #REF! | I6: =#REF! -> #REF! | ... P6: =#REF! -> #REF!
A7: Long Term Debt | B7: =#REF! -> #REF! | C7: =#REF! -> #REF! | D7: =#REF! -> #REF! | E7: =#REF! -> #REF! | F7: =#REF! -> #REF! | G7: =#REF! -> #REF! | H7: =#REF! -> #REF! | I7: =#REF! -> #REF! | ... P7: =#REF! -> #REF!
A8: Tangible Net Worth | B8: =#REF! -> #REF! | C8: =#REF! -> #REF! | D8: =#REF! -> #REF! | E8: =#REF! -> #REF! | F8: =#REF! -> #REF! | G8: =#REF! -> #REF! | H8: =#REF! -> #REF! | I8: =#REF! -> #REF! | ... P8: =#REF! -> #REF!
A9: Sales | B9: =#REF! -> #REF! | C9: =#REF! -> #REF! | D9: =#REF! -> #REF! | E9: =#REF! -> #REF! | F9: =#REF! -> #REF! | G9: =#REF! -> #REF! | H9: =#REF! -> #REF! | I9: =#REF! -> #REF! | ... P9: =#REF! -> #REF!
A10: Gross Margin | B10: =#REF! -> #REF! | C10: =#REF! -> #REF! | D10: =#REF! -> #REF! | E10: =#REF! -> #REF! | F10: =#REF! -> #REF! | G10: =#REF! -> #REF! | H10: =#REF! -> #REF! | I10: =#REF! -> #REF! | ... P10: =#REF! -> #REF!
A11: Profit After Zakat | B11: =#REF! -> #REF! | C11: =#REF! -> #REF! | D11: =#REF! -> #REF! | E11: =#REF! -> #REF! | F11: =#REF! -> #REF! | G11: =#REF! -> #REF! | H11: =#REF! -> #REF! | I11: =#REF! -> #REF! | ... P11: =#REF! -> #REF!
A12: EBITDA | B12: =#REF! -> #REF! | C12: =#REF! -> #REF! | D12: =#REF! -> #REF! | E12: =#REF! -> #REF! | F12: =#REF! -> #REF! | G12: =#REF! -> #REF! | H12: =#REF! -> #REF! | I12: =#REF! -> #REF! | ... P12: =#REF! -> #REF!
A13: Operating Cash Flow | B13: =#REF! -> #REF! | C13: =#REF! -> #REF! | D13: =#REF! -> #REF! | E13: =#REF! -> #REF! | F13: =#REF! -> #REF! | G13: =#REF! -> #REF! | H13: =#REF! -> #REF! | I13: =#REF! -> #REF! | ... P13: =#REF! -> #REF!
A14: Ratios/Percentages
A15: Current Ratio | B15: =#REF! -> #REF! | C15: =#REF! -> #REF! | D15: =#REF! -> #REF! | E15: =#REF! -> #REF! | F15: =#REF! -> #REF! | G15: =#REF! -> #REF! | H15: =#REF! -> #REF! | I15: =#REF! -> #REF! | ... P15: =#REF! -> #REF!
A16: Leverage Ratio | B16: =#REF! -> #REF! | C16: =#REF! -> #REF! | D16: =#REF! -> #REF! | E16: =#REF! -> #REF! | F16: =#REF! -> #REF! | G16: =#REF! -> #REF! | H16: =#REF! -> #REF! | I16: =#REF! -> #REF! | ... P16: =#REF! -> #REF!
A17: Debt Service Coverage Ratio | B17: =#REF! -> #REF! | C17: =#REF! -> #REF! | D17: =#REF! -> #REF! | E17: =#REF! -> #REF! | F17: =#REF! -> #REF! | G17: =#REF! -> #REF! | H17: =#REF! -> #REF! | I17: =#REF! -> #REF! | ... P17: =#REF! -> #REF!
A18: Gross Margin/Sales | B18: =#REF! -> #REF! | C18: =#REF! -> #REF! | D18: =#REF! -> #REF! | E18: =#REF! -> #REF! | F18: =#REF! -> #REF! | G18: =#REF! -> #REF! | H18: =#REF! -> #REF! | I18: =#REF! -> #REF! | ... P18: =#REF! -> #REF!
A19: Prof. Aft. Zakat/Sales | B19: =#REF! -> #REF! | C19: =#REF! -> #REF! | D19: =#REF! -> #REF! | E19: =#REF! -> #REF! | F19: =#REF! -> #REF! | G19: =#REF! -> #REF! | H19: =#REF! -> #REF! | I19: =#REF! -> #REF! | ... P19: =#REF! -> #REF!
A20: Cash Flow/Sales | B20: =#REF! -> #REF! | C20: =#REF! -> #REF! | D20: =#REF! -> #REF! | E20: =#REF! -> #REF! | F20: =#REF! -> #REF! | G20: =#REF! -> #REF! | H20: =#REF! -> #REF! | I20: =#REF! -> #REF! | ... P20: =#REF! -> #REF!
B22: Avg. Debt Service Coverage Ratio | F22: =AVERAGE(I17:M17) -> #REF!
